Workbook

Sheet Teaser
B2: ='Data Sheet'!B2&" - Company Snapshot" -> TITAN COMPANY LTD - Company Snapshot
C4: HOLD
C5: Target Price: | D5: ='P E Valuation'!H4 -> 5088.2674
C6: CMP: | D6: =B11 -> 5169
C7: Downside %: | D7: ='P E Valuation'!$I$4 -> -0.015618619
C8: Target Period: | D8: ='P E Valuation'!$J$4 -> 12 months
B10: ="NSE: "&Comps_Val!$C$9 -> NSE: TITAN | C10: BSE: 500114
B11: 5169 | C11: (28th August, 2026 - close price)
B12: 52-wk high: ₹5,187.45 | C12: 52-wk low: ₹3,307.35
B14: About the Company:
B15: Titan Company Ltd is among India’s most respected lifestyle companies. It has established leadership positions in the Watches, Jewellery and Eyewear categories led by its trusted brands and differentiated customer experience. It was founded in 1984 as a joint-venture between TATA Group and Tamilnadu Industrial Development Corporation (TIDCO).
B17: Figures in INR Crores
B18: Key Historical Financial Metrics | C18: =HistoricalFS!H3 -> 44651 | D18: =HistoricalFS!I3 -> 45016 | E18: =HistoricalFS!J3 -> 45382 | F18: =HistoricalFS!K3 -> 45747 | G18: =HistoricalFS!L3 -> 46112 | I18: Rapid Growth with Stable Margins
B19: Revenue | C19: =HistoricalFS!H6 -> 28799 | D19: =HistoricalFS!I6 -> 40575 | E19: =HistoricalFS!J6 -> 51084 | F19: =HistoricalFS!K6 -> 60456 | G19: =HistoricalFS!L6 -> 87584
B20: Revenue Growth | C20: =HistoricalFS!H7 -> 0.3305766 | D20: =HistoricalFS!I7 -> 0.40890309 | E20: =HistoricalFS!J7 -> 0.25900185 | F20: =HistoricalFS!K7 -> 0.18346253 | G20: =HistoricalFS!L7 -> 0.44872304
B21: Gross Profit Margin | C21: =HistoricalFS!H13 -> 0.19354839 | D21: =HistoricalFS!I13 -> 0.20406654 | E21: =HistoricalFS!J13 -> 0.18440216 | F21: =HistoricalFS!K13 -> 0.17255525 | G21: =HistoricalFS!L13 -> 0.16125091
B22: EBITDA Margin | C22: =HistoricalFS!H19 -> 0.11611514 | D22: =HistoricalFS!I19 -> 0.12032039 | E22: =HistoricalFS!J19 -> 0.10359408 | F22: =HistoricalFS!K19 -> 0.0941842 | G22: =HistoricalFS!L19 -> 0.095416971
B23: EBIT Margin | C23: ='Ratio Analysis'!H13 -> 0.1022605 | D23: ='Ratio Analysis'!I13 -> 0.10945163 | E23: ='Ratio Analysis'!J13 -> 0.092161929 | F23: ='Ratio Analysis'!K13 -> 0.082721318 | G23: ='Ratio Analysis'!L13 -> 0.085986025
B24: Net Profit Margin | C24: =HistoricalFS!H40 -> 0.076322095 | D24: =HistoricalFS!I40 -> 0.08069008 | E24: =HistoricalFS!J40 -> 0.068436301 | F24: =HistoricalFS!K40 -> 0.055197168 | G24: =HistoricalFS!L40 -> 0.057921538
B25: EPS | C25: =HistoricalFS!H44 -> 24.757828 | D25: =HistoricalFS!I44 -> 36.877675 | E25: =HistoricalFS!J44 -> 39.378238 | F25: =HistoricalFS!K44 -> 37.587294 | G25: =HistoricalFS!L44 -> 57.141248
B26: EPS Growth | C26: =HistoricalFS!H45 -> 1.2566735 | D26: =HistoricalFS!I45 -> 0.48953594 | E26: =HistoricalFS!J45 -> 0.067806964 | F26: =HistoricalFS!K45 -> -0.045480549 | G26: =HistoricalFS!L45 -> 0.52022775
B27: Dividend per Share | C27: =HistoricalFS!H48 -> 7.5185853 | D27: =HistoricalFS!I48 -> 10.02478 | E27: =HistoricalFS!J48 -> 11.027258 | F27: =HistoricalFS!K48 -> 11.027258 | G27: =HistoricalFS!L48 -> 15.037171
B28: DPS Growth | C28: =HistoricalFS!H48/HistoricalFS!G48-1 -> 0.875 | D28: =D27/C27-1 -> 0.33333333 | E28: =E27/D27-1 -> 0.1 | F28: =F27/E27-1 -> 0 | G28: =G27/F27-1 -> 0.36363636
B30: Key Financial Ratios | C30: =C18 -> 44651 | D30: =D18 -> 45016 | E30: =E18 -> 45382 | F30: =F18 -> 45747 | G30: =G18 -> 46112 | I30: Share Price - 5Y
B31: Price to Earnings | C31: ='Ratio Analysis'!H27 -> 102.43831 | D31: ='Ratio Analysis'!I27 -> 68.195731 | E31: ='Ratio Analysis'!J27 -> 96.545711 | F31: ='Ratio Analysis'!K27 -> 81.499614 | G31: ='Ratio Analysis'!L27 -> 69.151447
B32: EV/EBITDA | C32: ='Ratio Analysis'!H28 -> 69.037499 | D32: ='Ratio Analysis'!I28 -> 47.377473 | E32: ='Ratio Analysis'!J28 -> 66.425889 | F32: ='Ratio Analysis'!K28 -> 51.134038 | G32: ='Ratio Analysis'!L28 -> 45.412145
B33: EV/Sales | C33: ='Ratio Analysis'!H29 -> 8.0162991 | D33: ='Ratio Analysis'!I29 -> 5.7004762 | E33: ='Ratio Analysis'!J29 -> 6.8813289 | F33: ='Ratio Analysis'!K29 -> 4.8160185 | G33: ='Ratio Analysis'!L29 -> 4.3330893
B34: Price to Book Value | C34: ='Ratio Analysis'!H30 -> 24.20288 | D34: ='Ratio Analysis'!I30 -> 18.839998 | E34: ='Ratio Analysis'!J30 -> 35.933547 | F34: ='Ratio Analysis'!K30 -> 23.396784 | G34: ='Ratio Analysis'!L30 -> 22.340017
B35: Return on Equity | C35: ='Ratio Analysis'!H23 -> 0.23626787 | D35: ='Ratio Analysis'!I23 -> 0.27626361 | E35: ='Ratio Analysis'!J23 -> 0.37219206 | F35: ='Ratio Analysis'!K23 -> 0.28707846 | G35: ='Ratio Analysis'!L23 -> 0.32305929
B36: Return on Capital Employed | C36: ='Ratio Analysis'!H21 -> 0.17764507 | D36: ='Ratio Analysis'!I21 -> 0.20930342 | E36: ='Ratio Analysis'!J21 -> 0.18891698 | F36: ='Ratio Analysis'!K21 -> 0.15434709 | G36: ='Ratio Analysis'!L21 -> 0.16257232
B38: Estimates | C38: ='P E Valuation'!D11 -> 46112 | D38: ='P E Valuation'!E11 -> 46477 | E38: ='P E Valuation'!F11 -> 46842
B39: Revenue | C39: ='P E Valuation'!D13 -> 87584 | D39: ='P E Valuation'!E13 -> 100721.6 | E39: ='P E Valuation'!F13 -> 115829.84
B40: ='P E Valuation'!B16 -> EBITDA | C40: ='P E Valuation'!D16 -> 8357 | D40: ='P E Valuation'!E16 -> 10072.16 | E40: ='P E Valuation'!F16 -> 11582.984
B41: ='DCF - Exit Multiple'!B4 -> EBIT | C41: ='DCF - Exit Multiple'!D4 -> 7981 | D41: ='DCF - Exit Multiple'!E4 -> 9178.15 | E41: ='DCF - Exit Multiple'!F4 -> 10554.872
B42: ='P E Valuation'!B19 -> Net Profit | C42: ='P E Valuation'!D19 -> 5073 | D42: ='P E Valuation'!E19 -> 6043.296 | E42: ='P E Valuation'!F19 -> 6949.7904
B43: ='P E Valuation'!B24 -> EPS | C43: ='P E Valuation'!D24 -> 57.141248 | D43: ='P E Valuation'!E24 -> 68.070466 | E43: ='P E Valuation'!F24 -> 78.281036
B45: Valuation | C45: Implied Value / Share
B46: P/E Valuation | C46: ='P E Valuation'!H4 -> 5088.2674
B47: DCF - Exit Multiple | C47: ='DCF - Exit Multiple'!C34 -> 4211.4835
B48: Probability weighted Scenario | C48: ='Scenario Analysis'!N6 -> 5141.0627
B49: Trading Comps - P/E | C49: =Comps_Val!Q34 -> 2376.3465
B50: Trading Comps - EV/EBITDA | C50: =Comps_Val!P34 -> 2345.3786

Sheet Financials>

Sheet HistoricalFS
B2: ="Historical Financial Statement - "&'Data Sheet'!B2 -> Historical Financial Statement - TITAN COMPANY LTD
B3: Years | C3: ='Data Sheet'!B17 -> 42825 | D3: ='Data Sheet'!C17 -> 43190 | E3: ='Data Sheet'!D17 -> 43555 | F3: ='Data Sheet'!E17 -> 43921 | G3: ='Data Sheet'!F17 -> 44286 | H3: ='Data Sheet'!G17 -> 44651 | I3: ='Data Sheet'!H17 -> 45016 | J3: ='Data Sheet'!I17 -> 45382 | ... L3: ='Data Sheet'!K17 -> 46112
A5: # | B5: Income statement
B6: Sales | C6: =IFERROR('Data Sheet'!B18,0) -> 13260.83 | D6: =IFERROR('Data Sheet'!C18,0) -> 16119.77 | E6: =IFERROR('Data Sheet'!D18,0) -> 19778.52 | F6: =IFERROR('Data Sheet'!E18,0) -> 21052 | G6: =IFERROR('Data Sheet'!F18,0) -> 21644 | H6: =IFERROR('Data Sheet'!G18,0) -> 28799 | I6: =IFERROR('Data Sheet'!H18,0) -> 40575 | J6: =IFERROR('Data Sheet'!I18,0) -> 51084 | ... L6: =IFERROR('Data Sheet'!K18,0) -> 87584
B7: Sales Growth | C7: - | D7: =IFERROR((D6/C6)-1,0) -> 0.21559284 | E7: =IFERROR((E6/D6)-1,0) -> 0.22697284 | F7: =IFERROR((F6/E6)-1,0) -> 0.064387022 | G7: =IFERROR((G6/F6)-1,0) -> 0.028120844 | H7: =IFERROR((H6/G6)-1,0) -> 0.3305766 | I7: =IFERROR((I6/H6)-1,0) -> 0.40890309 | J7: =IFERROR((J6/I6)-1,0) -> 0.25900185 | K7: =IFERROR((K6/J6)-1,0) -> 0.18346253 | L7: =IFERROR((L6/K6)-1,0) -> 0.44872304
B9: COGS | C9: =IFERROR(SUM('Data Sheet'!B19,'Data Sheet'!B21:B23)-1*'Data Sheet'!B20,0) -> 10606.01 | D9: =IFERROR(SUM('Data Sheet'!C19,'Data Sheet'!C21:C23)-1*'Data Sheet'!C20,0) -> 12762.63 | E9: =IFERROR(SUM('Data Sheet'!D19,'Data Sheet'!D21:D23)-1*'Data Sheet'!D20,0) -> 15660.48 | F9: =IFERROR(SUM('Data Sheet'!E19,'Data Sheet'!E21:E23)-1*'Data Sheet'!E20,0) -> 16626 | G9: =IFERROR(SUM('Data Sheet'!F19,'Data Sheet'!F21:F23)-1*'Data Sheet'!F20,0) -> 17661 | H9: =IFERROR(SUM('Data Sheet'!G19,'Data Sheet'!G21:G23)-1*'Data Sheet'!G20,0) -> 23225 | I9: =IFERROR(SUM('Data Sheet'!H19,'Data Sheet'!H21:H23)-1*'Data Sheet'!H20,0) -> 32295 | J9: =IFERROR(SUM('Data Sheet'!I19,'Data Sheet'!I21:I23)-1*'Data Sheet'!I20,0) -> 41664 | ... L9: =IFERROR(SUM('Data Sheet'!K19,'Data Sheet'!K21:K23)-1*'Data Sheet'!K20,0) -> 73461
B10: COGS as % of sales | C10: =IFERROR(C9/C6,0) -> 0.79979986 | D10: =IFERROR(D9/D6,0) -> 0.79173772 | E10: =IFERROR(E9/E6,0) -> 0.79179231 | F10: =IFERROR(F9/F6,0) -> 0.78975869 | G10: =IFERROR(G9/G6,0) -> 0.81597671 | H10: =IFERROR(H9/H6,0) -> 0.80645161 | I10: =IFERROR(I9/I6,0) -> 0.79593346 | J10: =IFERROR(J9/J6,0) -> 0.81559784 | ... L10: =IFERROR(L9/L6,0) -> 0.83874909
B12: Gross Profit | C12: =IFERROR(C6-C9,0) -> 2654.82 | D12: =IFERROR(D6-D9,0) -> 3357.14 | E12: =IFERROR(E6-E9,0) -> 4118.04 | F12: =IFERROR(F6-F9,0) -> 4426 | G12: =IFERROR(G6-G9,0) -> 3983 | H12: =IFERROR(H6-H9,0) -> 5574 | I12: =IFERROR(I6-I9,0) -> 8280 | J12: =IFERROR(J6-J9,0) -> 9420 | ... L12: =IFERROR(L6-L9,0) -> 14123
B13: Gross Margin | C13: =IFERROR(C12/C6,0) -> 0.20020014 | D13: =IFERROR(D12/D6,0) -> 0.20826228 | E13: =IFERROR(E12/E6,0) -> 0.20820769 | F13: =IFERROR(F12/F6,0) -> 0.21024131 | G13: =IFERROR(G12/G6,0) -> 0.18402329 | H13: =IFERROR(H12/H6,0) -> 0.19354839 | I13: =IFERROR(I12/I6,0) -> 0.20406654 | J13: =IFERROR(J12/J6,0) -> 0.18440216 | ... L13: =IFERROR(L12/L6,0) -> 0.16125091
B15: SG&A Expenses | C15: =IFERROR(SUM('Data Sheet'!B24:B25),0) -> 1490.92 | D15: =IFERROR(SUM('Data Sheet'!C24:C25),0) -> 1712.94 | E15: =IFERROR(SUM('Data Sheet'!D24:D25),0) -> 2124.25 | F15: =IFERROR(SUM('Data Sheet'!E24:E25),0) -> 1963 | G15: =IFERROR(SUM('Data Sheet'!F24:F25),0) -> 2258 | H15: =IFERROR(SUM('Data Sheet'!G24:G25),0) -> 2230 | I15: =IFERROR(SUM('Data Sheet'!H24:H25),0) -> 3398 | J15: =IFERROR(SUM('Data Sheet'!I24:I25),0) -> 4128 | ... L15: =IFERROR(SUM('Data Sheet'!K24:K25),0) -> 5766
B16: SG&A Expenses as % of sales | C16: =IFERROR(C15/C6,0) -> 0.11243037 | D16: =IFERROR(D15/D6,0) -> 0.1062633 | E16: =IFERROR(E15/E6,0) -> 0.10740187 | F16: =IFERROR(F15/F6,0) -> 0.093245297 | G16: =IFERROR(G15/G6,0) -> 0.10432452 | H16: =IFERROR(H15/H6,0) -> 0.077433244 | I16: =IFERROR(I15/I6,0) -> 0.083746149 | J16: =IFERROR(J15/J6,0) -> 0.080808081 | ... L16: =IFERROR(L15/L6,0) -> 0.065833942
B18: EBITDA | C18: =C12-C15 -> 1163.9 | D18: =D12-D15 -> 1644.2 | E18: =E12-E15 -> 1993.79 | F18: =F12-F15 -> 2463 | G18: =G12-G15 -> 1725 | H18: =H12-H15 -> 3344 | I18: =I12-I15 -> 4882 | J18: =J12-J15 -> 5292 | ... L18: =L12-L15 -> 8357
B19: EBITDA margin | C19: =IFERROR(C18/C6,0) -> 0.08776977 | D19: =IFERROR(D18/D6,0) -> 0.10199897 | E19: =IFERROR(E18/E6,0) -> 0.10080582 | F19: =IFERROR(F18/F6,0) -> 0.11699601 | G19: =IFERROR(G18/G6,0) -> 0.079698762 | H19: =IFERROR(H18/H6,0) -> 0.11611514 | I19: =IFERROR(I18/I6,0) -> 0.12032039 | J19: =IFERROR(J18/J6,0) -> 0.10359408 | ... L19: =IFERROR(L18/L6,0) -> 0.095416971
B21: Interest | C21: =IFERROR('Data Sheet'!B28,0) -> 37.74 | D21: =IFERROR('Data Sheet'!C28,0) -> 52.92 | E21: =IFERROR('Data Sheet'!D28,0) -> 52.54 | F21: =IFERROR('Data Sheet'!E28,0) -> 166 | G21: =IFERROR('Data Sheet'!F28,0) -> 203 | H21: =IFERROR('Data Sheet'!G28,0) -> 218 | I21: =IFERROR('Data Sheet'!H28,0) -> 300 | J21: =IFERROR('Data Sheet'!I28,0) -> 619 | ... L21: =IFERROR('Data Sheet'!K28,0) -> 1180
B22: Interest as % of sales | C22: =IFERROR(C21/C6,0) -> 0.0028459757 | D22: =IFERROR(D21/D6,0) -> 0.0032829253 | E22: =IFERROR(E21/E6,0) -> 0.0026564172 | F22: =IFERROR(F21/F6,0) -> 0.0078852366 | G22: =IFERROR(G21/G6,0) -> 0.0093790427 | H22: =IFERROR(H21/H6,0) -> 0.0075697073 | I22: =IFERROR(I21/I6,0) -> 0.0073937153 | J22: =IFERROR(J21/J6,0) -> 0.012117297 | ... L22: =IFERROR(L21/L6,0) -> 0.01347278
B24: Depreciation | C24: =IFERROR('Data Sheet'!B27,0) -> 110.53 | D24: =IFERROR('Data Sheet'!C27,0) -> 131.43 | E24: =IFERROR('Data Sheet'!D27,0) -> 162.84 | F24: =IFERROR('Data Sheet'!E27,0) -> 348 | G24: =IFERROR('Data Sheet'!F27,0) -> 375 | H24: =IFERROR('Data Sheet'!G27,0) -> 399 | I24: =IFERROR('Data Sheet'!H27,0) -> 441 | J24: =IFERROR('Data Sheet'!I27,0) -> 584 | ... L24: =IFERROR('Data Sheet'!K27,0) -> 826
B25: Depreciation as % of sales | C25: =IFERROR(C24/C6,0) -> 0.008335074 | D25: =IFERROR(D24/D6,0) -> 0.0081533421 | E25: =IFERROR(E24/E6,0) -> 0.0082331742 | F25: =IFERROR(F24/F6,0) -> 0.016530496 | G25: =IFERROR(G24/G6,0) -> 0.017325818 | H25: =IFERROR(H24/H6,0) -> 0.013854648 | I25: =IFERROR(I24/I6,0) -> 0.010868762 | J25: =IFERROR(J24/J6,0) -> 0.011432151 | ... L25: =IFERROR(L24/L6,0) -> 0.0094309463
B27: EBIT | C27: =C18-C24 -> 1053.37 | D27: =D18-D24 -> 1512.77 | E27: =E18-E24 -> 1830.95 | F27: =F18-F24 -> 2115 | G27: =G18-G24 -> 1350 | H27: =H18-H24 -> 2945 | I27: =I18-I24 -> 4441 | J27: =J18-J24 -> 4708 | ... L27: =L18-L24 -> 7531
B28: EBIT as % of sales | C28: =C27/C6 -> 0.079434696 | D28: =D27/D6 -> 0.093845632 | E28: =E27/E6 -> 0.09257265 | F28: =F27/F6 -> 0.10046551 | G28: =G27/G6 -> 0.062372944 | H28: =H27/H6 -> 0.1022605 | I28: =I27/I6 -> 0.10945163 | J28: =J27/J6 -> 0.092161929 | ... L28: =L27/L6 -> 0.085986025
B30: Other Income | C30: ='Data Sheet'!B26 -> -42.38 | D30: ='Data Sheet'!C26 -> 69.93 | E30: ='Data Sheet'!D26 -> 178.48 | F30: ='Data Sheet'!E26 -> 153 | G30: ='Data Sheet'!F26 -> 180 | H30: ='Data Sheet'!G26 -> 177 | I30: ='Data Sheet'!H26 -> 306 | J30: ='Data Sheet'!I26 -> 534 | ... L30: ='Data Sheet'!K26 -> 450
B31: Other Income as % of sales | C31: =C30/C6 -> -0.0031958784 | D31: =D30/D6 -> 0.0043381512 | E31: =E30/E6 -> 0.009023931 | F31: =F30/F6 -> 0.007267718 | G31: =G30/G6 -> 0.0083163925 | H31: =H30/H6 -> 0.0061460467 | I31: =I30/I6 -> 0.0075415896 | J31: =J30/J6 -> 0.010453371 | ... L31: =L30/L6 -> 0.0051379247
B33: EBT | C33: =IFERROR(C27+C30-C21,0) -> 973.25 | D33: =IFERROR(D27+D30-D21,0) -> 1529.78 | E33: =IFERROR(E27+E30-E21,0) -> 1956.89 | F33: =IFERROR(F27+F30-F21,0) -> 2102 | G33: =IFERROR(G27+G30-G21,0) -> 1327 | H33: =IFERROR(H27+H30-H21,0) -> 2904 | I33: =IFERROR(I27+I30-I21,0) -> 4447 | J33: =IFERROR(J27+J30-J21,0) -> 4623 | ... L33: =IFERROR(L27+L30-L21,0) -> 6801
B34: EBT Margin | C34: =IFERROR(C33/C6,0) -> 0.073392842 | D34: =IFERROR(D33/D6,0) -> 0.094900858 | E34: =IFERROR(E33/E6,0) -> 0.098940163 | F34: =IFERROR(F33/F6,0) -> 0.099847995 | G34: =IFERROR(G33/G6,0) -> 0.061310294 | H34: =IFERROR(H33/H6,0) -> 0.10083683 | I34: =IFERROR(I33/I6,0) -> 0.10959951 | J34: =IFERROR(J33/J6,0) -> 0.090498003 | ... L34: =IFERROR(L33/L6,0) -> 0.077651169
B36: Tax | C36: =IFERROR('Data Sheet'!B30,0) -> 275.97 | D36: =IFERROR('Data Sheet'!C30,0) -> 427.87 | E36: =IFERROR('Data Sheet'!D30,0) -> 568.24 | F36: =IFERROR('Data Sheet'!E30,0) -> 609 | G36: =IFERROR('Data Sheet'!F30,0) -> 353 | H36: =IFERROR('Data Sheet'!G30,0) -> 706 | I36: =IFERROR('Data Sheet'!H30,0) -> 1173 | J36: =IFERROR('Data Sheet'!I30,0) -> 1127 | ... L36: =IFERROR('Data Sheet'!K30,0) -> 1728
B37: Effective Tax rate | C37: =IFERROR(C36/C33,0) -> 0.2835551 | D37: =IFERROR(D36/D33,0) -> 0.27969381 | E37: =IFERROR(E36/E33,0) -> 0.29037912 | F37: =IFERROR(F36/F33,0) -> 0.28972407 | G37: =IFERROR(G36/G33,0) -> 0.26601356 | H37: =IFERROR(H36/H33,0) -> 0.24311295 | I37: =IFERROR(I36/I33,0) -> 0.26377333 | J37: =IFERROR(J36/J33,0) -> 0.24378109 | ... L37: =IFERROR(L36/L33,0) -> 0.25408028
B39: Net Profit | C39: =IFERROR(C33-C36,0) -> 697.28 | D39: =IFERROR(D33-D36,0) -> 1101.91 | E39: =IFERROR(E33-E36,0) -> 1388.65 | F39: =IFERROR(F33-F36,0) -> 1493 | G39: =IFERROR(G33-G36,0) -> 974 | H39: =IFERROR(H33-H36,0) -> 2198 | I39: =IFERROR(I33-I36,0) -> 3274 | J39: =IFERROR(J33-J36,0) -> 3496 | ... L39: =IFERROR(L33-L36,0) -> 5073
B40: Net Profit Margin | C40: =IFERROR(C39/C6,0) -> 0.052581927 | D40: =IFERROR(D39/D6,0) -> 0.068357675 | E40: =IFERROR(E39/E6,0) -> 0.070210006 | F40: =IFERROR(F39/F6,0) -> 0.070919628 | G40: =IFERROR(G39/G6,0) -> 0.045000924 | H40: =IFERROR(H39/H6,0) -> 0.076322095 | I40: =IFERROR(I39/I6,0) -> 0.08069008 | J40: =IFERROR(J39/J6,0) -> 0.068436301 | ... L40: =IFERROR(L39/L6,0) -> 0.057921538
B42: Equity shares outstanding | C42: =IFERROR('Data Sheet'!B96,0) -> 88.78 | D42: =IFERROR('Data Sheet'!C96,0) -> 88.78 | E42: =IFERROR('Data Sheet'!D96,0) -> 88.78 | F42: =IFERROR('Data Sheet'!E96,0) -> 88.78 | G42: =IFERROR('Data Sheet'!F96,0) -> 88.78 | H42: =IFERROR('Data Sheet'!G96,0) -> 88.78 | I42: =IFERROR('Data Sheet'!H96,0) -> 88.78 | J42: =IFERROR('Data Sheet'!I96,0) -> 88.78 | ... L42: =IFERROR('Data Sheet'!K96,0) -> 88.78
B44: EPS | C44: =IFERROR((C39/C42),0) -> 7.8540212 | D44: =IFERROR((D39/D42),0) -> 12.411692 | E44: =IFERROR((E39/E42),0) -> 15.641473 | F44: =IFERROR((F39/F42),0) -> 16.816851 | G44: =IFERROR((G39/G42),0) -> 10.970939 | H44: =IFERROR((H39/H42),0) -> 24.757828 | I44: =IFERROR((I39/I42),0) -> 36.877675 | J44: =IFERROR((J39/J42),0) -> 39.378238 | ... L44: =IFERROR((L39/L42),0) -> 57.141248
B45: EPS Growth % | C45: - | D45: =IFERROR((D44/C44)-1,0) -> 0.58029773 | E45: =IFERROR((E44/D44)-1,0) -> 0.26022089 | F45: =IFERROR((F44/E44)-1,0) -> 0.075144925 | G45: =IFERROR((G44/F44)-1,0) -> -0.34762224 | H45: =IFERROR((H44/G44)-1,0) -> 1.2566735 | I45: =IFERROR((I44/H44)-1,0) -> 0.48953594 | J45: =IFERROR((J44/I44)-1,0) -> 0.067806964 | K45: =IFERROR((K44/J44)-1,0) -> -0.045480549 | L45: =IFERROR((L44/K44)-1,0) -> 0.52022775
B47: Dividend | C47: =IFERROR('Data Sheet'!B32,0) -> 230.83 | D47: =IFERROR('Data Sheet'!C32,0) -> 332.92 | E47: =IFERROR('Data Sheet'!D32,0) -> 443.9 | F47: =IFERROR('Data Sheet'!E32,0) -> 356 | G47: =IFERROR('Data Sheet'!F32,0) -> 356 | H47: =IFERROR('Data Sheet'!G32,0) -> 667.5 | I47: =IFERROR('Data Sheet'!H32,0) -> 890 | J47: =IFERROR('Data Sheet'!I32,0) -> 979 | ... L47: =IFERROR('Data Sheet'!K32,0) -> 1335
B48: Dividend per share | C48: =IFERROR((C47/C42),0) -> 2.6000225 | D48: =IFERROR((D47/D42),0) -> 3.7499437 | E48: =IFERROR((E47/E42),0) -> 5 | F48: =IFERROR((F47/F42),0) -> 4.0099121 | G48: =IFERROR((G47/G42),0) -> 4.0099121 | H48: =IFERROR((H47/H42),0) -> 7.5185853 | I48: =IFERROR((I47/I42),0) -> 10.02478 | J48: =IFERROR((J47/J42),0) -> 11.027258 | ... L48: =IFERROR((L47/L42),0) -> 15.037171
B49: Divident payout ratio | C49: =IFERROR((C48/C44),0) -> 0.33104348 | D49: =IFERROR((D48/D44),0) -> 0.30212994 | E49: =IFERROR((E48/E44),0) -> 0.31966298 | F49: =IFERROR((F48/F44),0) -> 0.23844608 | G49: =IFERROR((G48/G44),0) -> 0.36550308 | H49: =IFERROR((H48/H44),0) -> 0.30368517 | I49: =IFERROR((I48/I44),0) -> 0.27183873 | J49: =IFERROR((J48/J44),0) -> 0.28003432 | ... L49: =IFERROR((L48/L44),0) -> 0.26315789
B51: Retained earnings | C51: =IFERROR(IF(C44>C48,1-C49,0),0) -> 0.66895652 | D51: =IFERROR(IF(D44>D48,1-D49,0),0) -> 0.69787006 | E51: =IFERROR(IF(E44>E48,1-E49,0),0) -> 0.68033702 | F51: =IFERROR(IF(F44>F48,1-F49,0),0) -> 0.76155392 | G51: =IFERROR(IF(G44>G48,1-G49,0),0) -> 0.63449692 | H51: =IFERROR(IF(H44>H48,1-H49,0),0) -> 0.69631483 | I51: =IFERROR(IF(I44>I48,1-I49,0),0) -> 0.72816127 | J51: =IFERROR(IF(J44>J48,1-J49,0),0) -> 0.71996568 | ... L51: =IFERROR(IF(L44>L48,1-L49,0),0) -> 0.73684211
A53: # | B53: Balance Sheet
B54: Equity Share Capital | C54: =IFERROR('Data Sheet'!B58,0) -> 88.78 | D54: =IFERROR('Data Sheet'!C58,0) -> 88.78 | E54: =IFERROR('Data Sheet'!D58,0) -> 88.78 | F54: =IFERROR('Data Sheet'!E58,0) -> 89 | G54: =IFERROR('Data Sheet'!F58,0) -> 89 | H54: =IFERROR('Data Sheet'!G58,0) -> 89 | I54: =IFERROR('Data Sheet'!H58,0) -> 89 | J54: =IFERROR('Data Sheet'!I58,0) -> 89 | ... L54: =IFERROR('Data Sheet'!K58,0) -> 89
B55: Reserves | C55: =IFERROR('Data Sheet'!B59,0) -> 4143.6 | D55: =IFERROR('Data Sheet'!C59,0) -> 5001.1 | E55: =IFERROR('Data Sheet'!D59,0) -> 5981.37 | F55: =IFERROR('Data Sheet'!E59,0) -> 6580 | G55: =IFERROR('Data Sheet'!F59,0) -> 7408 | H55: =IFERROR('Data Sheet'!G59,0) -> 9214 | I55: =IFERROR('Data Sheet'!H59,0) -> 11762 | J55: =IFERROR('Data Sheet'!I59,0) -> 9304 | ... L55: =IFERROR('Data Sheet'!K59,0) -> 15614
B56: Borrowings | C56: =IFERROR('Data Sheet'!B60,0) -> 1882.43 | D56: =IFERROR('Data Sheet'!C60,0) -> 1691.01 | E56: =IFERROR('Data Sheet'!D60,0) -> 2392.98 | F56: =IFERROR('Data Sheet'!E60,0) -> 3562 | G56: =IFERROR('Data Sheet'!F60,0) -> 5638 | H56: =IFERROR('Data Sheet'!G60,0) -> 7275 | I56: =IFERROR('Data Sheet'!H60,0) -> 9367 | J56: =IFERROR('Data Sheet'!I60,0) -> 15528 | ... L56: =IFERROR('Data Sheet'!K60,0) -> 30621
B57: Other Liabilities | C57: =IFERROR('Data Sheet'!B61,0) -> 2292.76 | D57: =IFERROR('Data Sheet'!C61,0) -> 2740.15 | E57: =IFERROR('Data Sheet'!D61,0) -> 3246.71 | F57: =IFERROR('Data Sheet'!E61,0) -> 3313 | G57: =IFERROR('Data Sheet'!F61,0) -> 3309 | H57: =IFERROR('Data Sheet'!G61,0) -> 4610 | I57: =IFERROR('Data Sheet'!H61,0) -> 5802 | J57: =IFERROR('Data Sheet'!I61,0) -> 6626 | ... L57: =IFERROR('Data Sheet'!K61,0) -> 14237
B58: Total Liabilities | C58: =IFERROR('Data Sheet'!B63,0) -> 8407.57 | D58: =IFERROR('Data Sheet'!C63,0) -> 9521.04 | E58: =IFERROR('Data Sheet'!D63,0) -> 11709.84 | F58: =IFERROR('Data Sheet'!E63,0) -> 13544 | G58: =IFERROR('Data Sheet'!F63,0) -> 16444 | H58: =IFERROR('Data Sheet'!G63,0) -> 21188 | I58: =IFERROR('Data Sheet'!H63,0) -> 27020 | J58: =IFERROR('Data Sheet'!I63,0) -> 31547 | ... L58: =IFERROR('Data Sheet'!K63,0) -> 60561
B60: Fixed Assets Net Block | C60: =IFERROR('Data Sheet'!B64,0) -> 1188.72 | D60: =IFERROR('Data Sheet'!C64,0) -> 1473.81 | E60: =IFERROR('Data Sheet'!D64,0) -> 1566.63 | F60: =IFERROR('Data Sheet'!E64,0) -> 2633 | G60: =IFERROR('Data Sheet'!F64,0) -> 2523 | H60: =IFERROR('Data Sheet'!G64,0) -> 2544 | I60: =IFERROR('Data Sheet'!H64,0) -> 2998 | J60: =IFERROR('Data Sheet'!I64,0) -> 3709 | ... L60: =IFERROR('Data Sheet'!K64,0) -> 6878
B61: Capital Work in Progress | C61: =IFERROR('Data Sheet'!B65,0) -> 152.07 | D61: =IFERROR('Data Sheet'!C65,0) -> 43.37 | E61: =IFERROR('Data Sheet'!D65,0) -> 31.77 | F61: =IFERROR('Data Sheet'!E65,0) -> 18 | G61: =IFERROR('Data Sheet'!F65,0) -> 32 | H61: =IFERROR('Data Sheet'!G65,0) -> 85 | I61: =IFERROR('Data Sheet'!H65,0) -> 144 | J61: =IFERROR('Data Sheet'!I65,0) -> 97 | ... L61: =IFERROR('Data Sheet'!K65,0) -> 163
B62: Investments | C62: =IFERROR('Data Sheet'!B66,0) -> 430.73 | D62: =IFERROR('Data Sheet'!C66,0) -> 35.99 | E62: =IFERROR('Data Sheet'!D66,0) -> 108.42 | F62: =IFERROR('Data Sheet'!E66,0) -> 158 | G62: =IFERROR('Data Sheet'!F66,0) -> 2824 | H62: =IFERROR('Data Sheet'!G66,0) -> 294 | I62: =IFERROR('Data Sheet'!H66,0) -> 2515 | J62: =IFERROR('Data Sheet'!I66,0) -> 2345 | ... L62: =IFERROR('Data Sheet'!K66,0) -> 3506
B63: Other Non current Assets | C63: =IFERROR('Data Sheet'!B67-SUM('Data Sheet'!B69:B71),0) -> 723.78 | D63: =IFERROR('Data Sheet'!C67-SUM('Data Sheet'!C69:C71),0) -> 1129.43 | E63: =IFERROR('Data Sheet'!D67-SUM('Data Sheet'!D69:D71),0) -> 1477.27 | F63: =IFERROR('Data Sheet'!E67-SUM('Data Sheet'!E69:E71),0) -> 1939 | G63: =IFERROR('Data Sheet'!F67-SUM('Data Sheet'!F69:F71),0) -> 1731 | H63: =IFERROR('Data Sheet'!G67-SUM('Data Sheet'!G69:G71),0) -> 2518 | I63: =IFERROR('Data Sheet'!H67-SUM('Data Sheet'!H69:H71),0) -> 2762 | J63: =IFERROR('Data Sheet'!I67-SUM('Data Sheet'!I69:I71),0) -> 3801 | ... L63: =IFERROR('Data Sheet'!K67-SUM('Data Sheet'!K69:K71),0) -> 4438
B64: Total Non Current Assets | C64: =IFERROR(SUM(C60:C63),0) -> 2495.3 | D64: =IFERROR(SUM(D60:D63),0) -> 2682.6 | E64: =IFERROR(SUM(E60:E63),0) -> 3184.09 | F64: =IFERROR(SUM(F60:F63),0) -> 4748 | G64: =IFERROR(SUM(G60:G63),0) -> 7110 | H64: =IFERROR(SUM(H60:H63),0) -> 5441 | I64: =IFERROR(SUM(I60:I63),0) -> 8419 | J64: =IFERROR(SUM(J60:J63),0) -> 9952 | ... L64: =IFERROR(SUM(L60:L63),0) -> 14985
B66: Receivables | C66: =IFERROR('Data Sheet'!B69,0) -> 207.6 | D66: =IFERROR('Data Sheet'!C69,0) -> 295.69 | E66: =IFERROR('Data Sheet'!D69,0) -> 420.45 | F66: =IFERROR('Data Sheet'!E69,0) -> 312 | G66: =IFERROR('Data Sheet'!F69,0) -> 366 | H66: =IFERROR('Data Sheet'!G69,0) -> 565 | I66: =IFERROR('Data Sheet'!H69,0) -> 674 | J66: =IFERROR('Data Sheet'!I69,0) -> 1018 | ... L66: =IFERROR('Data Sheet'!K69,0) -> 916
B67: Inventory | C67: =IFERROR('Data Sheet'!B70,0) -> 4925.74 | D67: =IFERROR('Data Sheet'!C70,0) -> 5924.84 | E67: =IFERROR('Data Sheet'!D70,0) -> 7038.82 | F67: =IFERROR('Data Sheet'!E70,0) -> 8103 | G67: =IFERROR('Data Sheet'!F70,0) -> 8408 | H67: =IFERROR('Data Sheet'!G70,0) -> 13609 | I67: =IFERROR('Data Sheet'!H70,0) -> 16584 | J67: =IFERROR('Data Sheet'!I70,0) -> 19051 | ... L67: =IFERROR('Data Sheet'!K70,0) -> 42743
B68: Cash & Bank | C68: =IFERROR('Data Sheet'!B71,0) -> 778.93 | D68: =IFERROR('Data Sheet'!C71,0) -> 617.91 | E68: =IFERROR('Data Sheet'!D71,0) -> 1066.48 | F68: =IFERROR('Data Sheet'!E71,0) -> 381 | G68: =IFERROR('Data Sheet'!F71,0) -> 560 | H68: =IFERROR('Data Sheet'!G71,0) -> 1573 | I68: =IFERROR('Data Sheet'!H71,0) -> 1343 | J68: =IFERROR('Data Sheet'!I71,0) -> 1526 | ... L68: =IFERROR('Data Sheet'!K71,0) -> 1917
B69: Total Current Assets | C69: =IFERROR(SUM(C66:C68),0) -> 5912.27 | D69: =IFERROR(SUM(D66:D68),0) -> 6838.44 | E69: =IFERROR(SUM(E66:E68),0) -> 8525.75 | F69: =IFERROR(SUM(F66:F68),0) -> 8796 | G69: =IFERROR(SUM(G66:G68),0) -> 9334 | H69: =IFERROR(SUM(H66:H68),0) -> 15747 | I69: =IFERROR(SUM(I66:I68),0) -> 18601 | J69: =IFERROR(SUM(J66:J68),0) -> 21595 | ... L69: =IFERROR(SUM(L66:L68),0) -> 45576
B71: Total Assets | C71: =IFERROR(C69+C64,0) -> 8407.57 | D71: =IFERROR(D69+D64,0) -> 9521.04 | E71: =IFERROR(E69+E64,0) -> 11709.84 | F71: =IFERROR(F69+F64,0) -> 13544 | G71: =IFERROR(G69+G64,0) -> 16444 | H71: =IFERROR(H69+H64,0) -> 21188 | I71: =IFERROR(I69+I64,0) -> 27020 | J71: =IFERROR(J69+J64,0) -> 31547 | ... L71: =IFERROR(L69+L64,0) -> 60561
A73: # | B73: Cash Flow Statement
B74: Operating Activites
B75: Profit from operations | C75: =IFERROR('cash flow data'!E4,0) -> 1073 | D75: =IFERROR('cash flow data'!F4,0) -> 1642 | E75: =IFERROR('cash flow data'!G4,0) -> 2183 | F75: =IFERROR('cash flow data'!H4,0) -> 2481 | G75: =IFERROR('cash flow data'!I4,0) -> 1789 | H75: =IFERROR('cash flow data'!J4,0) -> 3298 | I75: =IFERROR('cash flow data'!K4,0) -> 4937 | J75: =IFERROR('cash flow data'!L4,0) -> 5404 | ... L75: =IFERROR('cash flow data'!N4,0) -> 8447
B76: Receivables | C76: =IFERROR('cash flow data'!E5,0) -> -12 | D76: =IFERROR('cash flow data'!F5,0) -> -90 | E76: =IFERROR('cash flow data'!G5,0) -> -139 | F76: =IFERROR('cash flow data'!H5,0) -> 109 | G76: =IFERROR('cash flow data'!I5,0) -> -59 | H76: =IFERROR('cash flow data'!J5,0) -> -207 | I76: =IFERROR('cash flow data'!K5,0) -> -112 | J76: =IFERROR('cash flow data'!L5,0) -> -348 | ... L76: =IFERROR('cash flow data'!N5,0) -> 210
B77: Inventory | C77: =IFERROR('cash flow data'!E6,0) -> -448 | D77: =IFERROR('cash flow data'!F6,0) -> -996 | E77: =IFERROR('cash flow data'!G6,0) -> -1120 | F77: =IFERROR('cash flow data'!H6,0) -> -1057 | G77: =IFERROR('cash flow data'!I6,0) -> -316 | H77: =IFERROR('cash flow data'!J6,0) -> -5199 | I77: =IFERROR('cash flow data'!K6,0) -> -2977 | J77: =IFERROR('cash flow data'!L6,0) -> -2462 | ... L77: =IFERROR('cash flow data'!N6,0) -> -11592
B78: Payables | C78: =IFERROR('cash flow data'!E7,0) -> 238 | D78: =IFERROR('cash flow data'!F7,0) -> 95 | E78: =IFERROR('cash flow data'!G7,0) -> 32 | F78: =IFERROR('cash flow data'!H7,0) -> -310 | G78: =IFERROR('cash flow data'!I7,0) -> 195 | H78: =IFERROR('cash flow data'!J7,0) -> 504 | I78: =IFERROR('cash flow data'!K7,0) -> -89 | J78: =IFERROR('cash flow data'!L7,0) -> 196 | ... L78: =IFERROR('cash flow data'!N7,0) -> 472
B79: Loans Advances | C79: =IFERROR('cash flow data'!E8,0) -> 0 | D79: =IFERROR('cash flow data'!F8,0) -> 3 | E79: =IFERROR('cash flow data'!G8,0) -> -24 | F79: =IFERROR('cash flow data'!H8,0) -> -20 | G79: =IFERROR('cash flow data'!I8,0) -> -8 | H79: =IFERROR('cash flow data'!J8,0) -> -3 | I79: =IFERROR('cash flow data'!K8,0) -> -18 | J79: =IFERROR('cash flow data'!L8,0) -> -21 | ... L79: =IFERROR('cash flow data'!N8,0) -> -8
B80: Other WC items | C80: =IFERROR('cash flow data'!E9,0) -> 375 | D80: =IFERROR('cash flow data'!F9,0) -> 22 | E80: =IFERROR('cash flow data'!G9,0) -> 206 | F80: =IFERROR('cash flow data'!H9,0) -> -226 | G80: =IFERROR('cash flow data'!I9,0) -> 184 | H80: =IFERROR('cash flow data'!J9,0) -> 497 | I80: =IFERROR('cash flow data'!K9,0) -> 882 | J80: =IFERROR('cash flow data'!L9,0) -> 57 | ... L80: =IFERROR('cash flow data'!N9,0) -> 2494
B81: Working capital changes | C81: =IFERROR('cash flow data'!E10,0) -> 916 | D81: =IFERROR('cash flow data'!F10,0) -> -1237 | E81: =IFERROR('cash flow data'!G10,0) -> -304 | F81: =IFERROR('cash flow data'!H10,0) -> -2272 | G81: =IFERROR('cash flow data'!I10,0) -> 2621 | H81: =IFERROR('cash flow data'!J10,0) -> -3220 | I81: =IFERROR('cash flow data'!K10,0) -> -2413 | J81: =IFERROR('cash flow data'!L10,0) -> -2536 | ... L81: =IFERROR('cash flow data'!N10,0) -> -1120
B82: Direct taxes | C82: =IFERROR('cash flow data'!E11,0) -> -277 | D82: =IFERROR('cash flow data'!F11,0) -> -456 | E82: =IFERROR('cash flow data'!G11,0) -> -636 | F82: =IFERROR('cash flow data'!H11,0) -> -557 | G82: =IFERROR('cash flow data'!I11,0) -> -271 | H82: =IFERROR('cash flow data'!J11,0) -> -802 | I82: =IFERROR('cash flow data'!K11,0) -> -1154 | J82: =IFERROR('cash flow data'!L11,0) -> -1173 | ... L82: =IFERROR('cash flow data'!N11,0) -> -1737
B83: Cash from Operating activities | C83: =IFERROR(SUM(C75:C82),0) -> 1865 | D83: =IFERROR(SUM(D75:D82),0) -> -1017 | E83: =IFERROR(SUM(E75:E82),0) -> 198 | F83: =IFERROR(SUM(F75:F82),0) -> -1852 | G83: =IFERROR(SUM(G75:G82),0) -> 4135 | H83: =IFERROR(SUM(H75:H82),0) -> -5132 | I83: =IFERROR(SUM(I75:I82),0) -> -944 | J83: =IFERROR(SUM(J75:J82),0) -> -883 | ... L83: =IFERROR(SUM(L75:L82),0) -> -2834
B85: Investing Activites
B86: Fixed assets purchased | C86: =IFERROR('cash flow data'!E13,0) -> -256 | D86: =IFERROR('cash flow data'!F13,0) -> -305 | E86: =IFERROR('cash flow data'!G13,0) -> -265 | F86: =IFERROR('cash flow data'!H13,0) -> -355 | G86: =IFERROR('cash flow data'!I13,0) -> -146 | H86: =IFERROR('cash flow data'!J13,0) -> -224 | I86: =IFERROR('cash flow data'!K13,0) -> -432 | J86: =IFERROR('cash flow data'!L13,0) -> -691 | ... L86: =IFERROR('cash flow data'!N13,0) -> -902
B87: Fixed assets sold | C87: =IFERROR('cash flow data'!E14,0) -> 5 | D87: =IFERROR('cash flow data'!F14,0) -> 6 | E87: =IFERROR('cash flow data'!G14,0) -> 1 | F87: =IFERROR('cash flow data'!H14,0) -> 10 | G87: =IFERROR('cash flow data'!I14,0) -> 7 | H87: =IFERROR('cash flow data'!J14,0) -> 8 | I87: =IFERROR('cash flow data'!K14,0) -> 12 | J87: =IFERROR('cash flow data'!L14,0) -> 20 | ... L87: =IFERROR('cash flow data'!N14,0) -> 25
B88: Investments purchased | C88: =IFERROR('cash flow data'!E15,0) -> -325 | D88: =IFERROR('cash flow data'!F15,0) -> 0 | E88: =IFERROR('cash flow data'!G15,0) -> -36 | F88: =IFERROR('cash flow data'!H15,0) -> -13 | G88: =IFERROR('cash flow data'!I15,0) -> -2656 | H88: =IFERROR('cash flow data'!J15,0) -> -253 | I88: =IFERROR('cash flow data'!K15,0) -> -2104 | J88: =IFERROR('cash flow data'!L15,0) -> -21893 | ... L88: =IFERROR('cash flow data'!N15,0) -> -22035
B89: Investments sold | C89: =IFERROR('cash flow data'!E16,0) -> 0 | D89: =IFERROR('cash flow data'!F16,0) -> 412 | E89: =IFERROR('cash flow data'!G16,0) -> 18 | F89: =IFERROR('cash flow data'!H16,0) -> 0 | G89: =IFERROR('cash flow data'!I16,0) -> 43 | H89: =IFERROR('cash flow data'!J16,0) -> 2870 | I89: =IFERROR('cash flow data'!K16,0) -> 0 | J89: =IFERROR('cash flow data'!L16,0) -> 22213 | ... L89: =IFERROR('cash flow data'!N16,0) -> 20797
B90: Interest received | C90: =IFERROR('cash flow data'!E17,0) -> 41 | D90: =IFERROR('cash flow data'!F17,0) -> 64 | E90: =IFERROR('cash flow data'!G17,0) -> 85 | F90: =IFERROR('cash flow data'!H17,0) -> 73 | G90: =IFERROR('cash flow data'!I17,0) -> 49 | H90: =IFERROR('cash flow data'!J17,0) -> 56 | I90: =IFERROR('cash flow data'!K17,0) -> 143 | J90: =IFERROR('cash flow data'!L17,0) -> 249 | ... L90: =IFERROR('cash flow data'!N17,0) -> 227
B91: Dividends received | C91: =IFERROR('cash flow data'!E18,0) -> 0 | D91: =IFERROR('cash flow data'!F18,0) -> 0 | E91: =IFERROR('cash flow data'!G18,0) -> 0 | F91: =IFERROR('cash flow data'!H18,0) -> 0 | G91: =IFERROR('cash flow data'!I18,0) -> 0 | H91: =IFERROR('cash flow data'!J18,0) -> 0 | I91: =IFERROR('cash flow data'!K18,0) -> 0 | J91: =IFERROR('cash flow data'!L18,0) -> 0 | ... L91: =IFERROR('cash flow data'!N18,0) -> 0
B92: Invest in subsidiaries | C92: =IFERROR('cash flow data'!E19,0) -> 0 | D92: =IFERROR('cash flow data'!F19,0) -> 0 | E92: =IFERROR('cash flow data'!G19,0) -> 0 | F92: =IFERROR('cash flow data'!H19,0) -> -39 | G92: =IFERROR('cash flow data'!I19,0) -> 0 | H92: =IFERROR('cash flow data'!J19,0) -> 0 | I92: =IFERROR('cash flow data'!K19,0) -> 0 | J92: =IFERROR('cash flow data'!L19,0) -> 0 | ... L92: =IFERROR('cash flow data'!N19,0) -> 0
B93: Investment in group cos | C93: =IFERROR('cash flow data'!E20,0) -> 0 | D93: =IFERROR('cash flow data'!F20,0) -> 0 | E93: =IFERROR('cash flow data'!G20,0) -> 0 | F93: =IFERROR('cash flow data'!H20,0) -> 0 | G93: =IFERROR('cash flow data'!I20,0) -> 0 | H93: =IFERROR('cash flow data'!J20,0) -> 0 | I93: =IFERROR('cash flow data'!K20,0) -> 0 | J93: =IFERROR('cash flow data'!L20,0) -> 0 | ... L93: =IFERROR('cash flow data'!N20,0) -> 0
B94: Redemp n Canc of Shares | C94: =IFERROR('cash flow data'!E21,0) -> 0 | D94: =IFERROR('cash flow data'!F21,0) -> 0 | E94: =IFERROR('cash flow data'!G21,0) -> 0 | F94: =IFERROR('cash flow data'!H21,0) -> 0 | G94: =IFERROR('cash flow data'!I21,0) -> 0 | H94: =IFERROR('cash flow data'!J21,0) -> 0 | I94: =IFERROR('cash flow data'!K21,0) -> 0 | J94: =IFERROR('cash flow data'!L21,0) -> 0 | ... L94: =IFERROR('cash flow data'!N21,0) -> 0
B95: Acquisition of companies | C95: =IFERROR('cash flow data'!E22,0) -> -385 | D95: =IFERROR('cash flow data'!F22,0) -> 0 | E95: =IFERROR('cash flow data'!G22,0) -> 0 | F95: =IFERROR('cash flow data'!H22,0) -> 0 | G95: =IFERROR('cash flow data'!I22,0) -> 0 | H95: =IFERROR('cash flow data'!J22,0) -> 0 | I95: =IFERROR('cash flow data'!K22,0) -> 0 | J95: =IFERROR('cash flow data'!L22,0) -> 0 | ... L95: =IFERROR('cash flow data'!N22,0) -> 0
B96: Inter corporate deposits | C96: =IFERROR('cash flow data'!E23,0) -> 5 | D96: =IFERROR('cash flow data'!F23,0) -> -35 | E96: =IFERROR('cash flow data'!G23,0) -> -115 | F96: =IFERROR('cash flow data'!H23,0) -> 200 | G96: =IFERROR('cash flow data'!I23,0) -> -50 | H96: =IFERROR('cash flow data'!J23,0) -> -344 | I96: =IFERROR('cash flow data'!K23,0) -> 294 | J96: =IFERROR('cash flow data'!L23,0) -> -143 | ... L96: =IFERROR('cash flow data'!N23,0) -> 0
B97: Other investing items | C97: =IFERROR('cash flow data'!E24,0) -> -38 | D97: =IFERROR('cash flow data'!F24,0) -> -43 | E97: =IFERROR('cash flow data'!G24,0) -> -485 | F97: =IFERROR('cash flow data'!H24,0) -> 359 | G97: =IFERROR('cash flow data'!I24,0) -> -46 | H97: =IFERROR('cash flow data'!J24,0) -> -948 | I97: =IFERROR('cash flow data'!K24,0) -> 273 | J97: =IFERROR('cash flow data'!L24,0) -> 56 | ... L97: =IFERROR('cash flow data'!N24,0) -> -1077
B98: Cash from Investing activities | C98: =IFERROR(SUM(C86:C97),0) -> -953 | D98: =IFERROR(SUM(D86:D97),0) -> 99 | E98: =IFERROR(SUM(E86:E97),0) -> -797 | F98: =IFERROR(SUM(F86:F97),0) -> 235 | G98: =IFERROR(SUM(G86:G97),0) -> -2799 | H98: =IFERROR(SUM(H86:H97),0) -> 1165 | I98: =IFERROR(SUM(I86:I97),0) -> -1814 | J98: =IFERROR(SUM(J86:J97),0) -> -189 | ... L98: =IFERROR(SUM(L86:L97),0) -> -2965
B100: Financing Activities
B101: Proceeds from shares | C101: =IFERROR('cash flow data'!E26,0) -> 0 | D101: =IFERROR('cash flow data'!F26,0) -> 0 | E101: =IFERROR('cash flow data'!G26,0) -> 0 | F101: =IFERROR('cash flow data'!H26,0) -> 0 | G101: =IFERROR('cash flow data'!I26,0) -> 0 | H101: =IFERROR('cash flow data'!J26,0) -> 0 | I101: =IFERROR('cash flow data'!K26,0) -> 0 | J101: =IFERROR('cash flow data'!L26,0) -> 0 | ... L101: =IFERROR('cash flow data'!N26,0) -> 0
B102: Redemption of debentures | C102: =IFERROR('cash flow data'!E27,0) -> 0 | D102: =IFERROR('cash flow data'!F27,0) -> 0 | E102: =IFERROR('cash flow data'!G27,0) -> 0 | F102: =IFERROR('cash flow data'!H27,0) -> 0 | G102: =IFERROR('cash flow data'!I27,0) -> 0 | H102: =IFERROR('cash flow data'!J27,0) -> 0 | I102: =IFERROR('cash flow data'!K27,0) -> 0 | J102: =IFERROR('cash flow data'!L27,0) -> 0 | ... L102: =IFERROR('cash flow data'!N27,0) -> 0
B103: Proceeds from borrowings | C103: =IFERROR('cash flow data'!E28,0) -> 0 | D103: =IFERROR('cash flow data'!F28,0) -> 0 | E103: =IFERROR('cash flow data'!G28,0) -> 0 | F103: =IFERROR('cash flow data'!H28,0) -> 693 | G103: =IFERROR('cash flow data'!I28,0) -> 0 | H103: =IFERROR('cash flow data'!J28,0) -> 349 | I103: =IFERROR('cash flow data'!K28,0) -> 1684 | J103: =IFERROR('cash flow data'!L28,0) -> 5629 | ... L103: =IFERROR('cash flow data'!N28,0) -> 3314
B104: Repayment of borrowings | C104: =IFERROR('cash flow data'!E29,0) -> 0 | D104: =IFERROR('cash flow data'!F29,0) -> 0 | E104: =IFERROR('cash flow data'!G29,0) -> -39 | F104: =IFERROR('cash flow data'!H29,0) -> 0 | G104: =IFERROR('cash flow data'!I29,0) -> -562 | H104: =IFERROR('cash flow data'!J29,0) -> -7 | I104: =IFERROR('cash flow data'!K29,0) -> -7 | J104: =IFERROR('cash flow data'!L29,0) -> 0 | ... L104: =IFERROR('cash flow data'!N29,0) -> -2632
B105: Proceeds from deposits | C105: =IFERROR('cash flow data'!E30,0) -> 0 | D105: =IFERROR('cash flow data'!F30,0) -> 0 | E105: =IFERROR('cash flow data'!G30,0) -> 0 | F105: =IFERROR('cash flow data'!H30,0) -> 0 | G105: =IFERROR('cash flow data'!I30,0) -> 0 | H105: =IFERROR('cash flow data'!J30,0) -> 0 | I105: =IFERROR('cash flow data'!K30,0) -> 0 | J105: =IFERROR('cash flow data'!L30,0) -> 0 | ... L105: =IFERROR('cash flow data'!N30,0) -> 0
B106: Interest paid fin | C106: =IFERROR('cash flow data'!E31,0) -> -38 | D106: =IFERROR('cash flow data'!F31,0) -> -54 | E106: =IFERROR('cash flow data'!G31,0) -> -53 | F106: =IFERROR('cash flow data'!H31,0) -> -399 | G106: =IFERROR('cash flow data'!I31,0) -> -317 | H106: =IFERROR('cash flow data'!J31,0) -> -218 | I106: =IFERROR('cash flow data'!K31,0) -> -300 | J106: =IFERROR('cash flow data'!L31,0) -> -619 | ... L106: =IFERROR('cash flow data'!N31,0) -> -1000
B107: Dividends paid | C107: =IFERROR('cash flow data'!E32,0) -> -4 | D107: =IFERROR('cash flow data'!F32,0) -> -277 | E107: =IFERROR('cash flow data'!G32,0) -> -397 | F107: =IFERROR('cash flow data'!H32,0) -> -536 | G107: =IFERROR('cash flow data'!I32,0) -> -355 | H107: =IFERROR('cash flow data'!J32,0) -> -355 | I107: =IFERROR('cash flow data'!K32,0) -> -666 | J107: =IFERROR('cash flow data'!L32,0) -> -888 | ... L107: =IFERROR('cash flow data'!N32,0) -> -976
B108: Financial liabilities | C108: =IFERROR('cash flow data'!E33,0) -> 0 | D108: =IFERROR('cash flow data'!F33,0) -> 0 | E108: =IFERROR('cash flow data'!G33,0) -> 0 | F108: =IFERROR('cash flow data'!H33,0) -> 0 | G108: =IFERROR('cash flow data'!I33,0) -> 0 | H108: =IFERROR('cash flow data'!J33,0) -> -172 | I108: =IFERROR('cash flow data'!K33,0) -> -254 | J108: =IFERROR('cash flow data'!L33,0) -> -318 | ... L108: =IFERROR('cash flow data'!N33,0) -> -865
B109: Other financing items | C109: =IFERROR('cash flow data'!E34,0) -> -124 | D109: =IFERROR('cash flow data'!F34,0) -> 79 | E109: =IFERROR('cash flow data'!G34,0) -> 0 | F109: =IFERROR('cash flow data'!H34,0) -> 0 | G109: =IFERROR('cash flow data'!I34,0) -> 0 | H109: =IFERROR('cash flow data'!J34,0) -> 0 | I109: =IFERROR('cash flow data'!K34,0) -> 0 | J109: =IFERROR('cash flow data'!L34,0) -> -5133 | ... L109: =IFERROR('cash flow data'!N34,0) -> 0
B110: Cash from Financing activities | C110: =SUM(C101:C109) -> -166 | D110: =SUM(D101:D109) -> -252 | E110: =SUM(E101:E109) -> -489 | F110: =SUM(F101:F109) -> -242 | G110: =SUM(G101:G109) -> -1234 | H110: =SUM(H101:H109) -> -403 | I110: =SUM(I101:I109) -> 457 | J110: =SUM(J101:J109) -> -1329 | ... L110: =SUM(L101:L109) -> -2159
B112: Net Cash Flow | C112: =IFERROR(C83+C98+C110,0) -> 746 | D112: =IFERROR(D83+D98+D110,0) -> -1170 | E112: =IFERROR(E83+E98+E110,0) -> -1088 | F112: =IFERROR(F83+F98+F110,0) -> -1859 | G112: =IFERROR(G83+G98+G110,0) -> 102 | H112: =IFERROR(H83+H98+H110,0) -> -4370 | I112: =IFERROR(I83+I98+I110,0) -> -2301 | J112: =IFERROR(J83+J98+J110,0) -> -2401 | ... L112: =IFERROR(L83+L98+L110,0) -> -7958

Sheet Ratio Analysis
B2: ="Ratio Analysis - "&'Data Sheet'!B2 -> Ratio Analysis - TITAN COMPANY LTD
B3: Years | C3: ='Data Sheet'!B17 -> 42825 | D3: ='Data Sheet'!C17 -> 43190 | E3: ='Data Sheet'!D17 -> 43555 | F3: ='Data Sheet'!E17 -> 43921 | G3: ='Data Sheet'!F17 -> 44286 | H3: ='Data Sheet'!G17 -> 44651 | I3: ='Data Sheet'!H17 -> 45016 | J3: ='Data Sheet'!I17 -> 45382 | ... L3: ='Data Sheet'!K17 -> 46112 | M3: Trend | N3: Mean | O3: Median
B5: SalesGrowth | D5: =IFERROR(HistoricalFS!D7,0) -> 0.21559284 | E5: =IFERROR(HistoricalFS!E7,0) -> 0.22697284 | F5: =IFERROR(HistoricalFS!F7,0) -> 0.064387022 | G5: =IFERROR(HistoricalFS!G7,0) -> 0.028120844 | H5: =IFERROR(HistoricalFS!H7,0) -> 0.3305766 | I5: =IFERROR(HistoricalFS!I7,0) -> 0.40890309 | J5: =IFERROR(HistoricalFS!J7,0) -> 0.25900185 | K5: =IFERROR(HistoricalFS!K7,0) -> 0.18346253 | L5: =IFERROR(HistoricalFS!L7,0) -> 0.44872304 | N5: =IFERROR(AVERAGE(D5:L5),0) -> 0.24063785 | O5: =IFERROR(MEDIAN(C5:L5),0) -> 0.22697284
B6: EBITDA Growth | D6: =IFERROR((HistoricalFS!D18/HistoricalFS!C18)-1,0) -> 0.41266432 | E6: =IFERROR((HistoricalFS!E18/HistoricalFS!D18)-1,0) -> 0.21262012 | F6: =IFERROR((HistoricalFS!F18/HistoricalFS!E18)-1,0) -> 0.23533572 | G6: =IFERROR((HistoricalFS!G18/HistoricalFS!F18)-1,0) -> -0.29963459 | H6: =IFERROR((HistoricalFS!H18/HistoricalFS!G18)-1,0) -> 0.93855072 | I6: =IFERROR((HistoricalFS!I18/HistoricalFS!H18)-1,0) -> 0.45992823 | J6: =IFERROR((HistoricalFS!J18/HistoricalFS!I18)-1,0) -> 0.083981975 | K6: =IFERROR((HistoricalFS!K18/HistoricalFS!J18)-1,0) -> 0.075963719 | L6: =IFERROR((HistoricalFS!L18/HistoricalFS!K18)-1,0) -> 0.46768528 | N6: =IFERROR(AVERAGE(D6:L6),0) -> 0.28745505 | O6: =IFERROR(MEDIAN(C6:L6),0) -> 0.23533572
B7: EBT Growth | D7: =IFERROR((HistoricalFS!D33/HistoricalFS!C33)-1,0) -> 0.57182635 | E7: =IFERROR((HistoricalFS!E33/HistoricalFS!D33)-1,0) -> 0.27919701 | F7: =IFERROR((HistoricalFS!F33/HistoricalFS!E33)-1,0) -> 0.074153376 | G7: =IFERROR((HistoricalFS!G33/HistoricalFS!F33)-1,0) -> -0.36869648 | H7: =IFERROR((HistoricalFS!H33/HistoricalFS!G33)-1,0) -> 1.1883949 | I7: =IFERROR((HistoricalFS!I33/HistoricalFS!H33)-1,0) -> 0.53133609 | J7: =IFERROR((HistoricalFS!J33/HistoricalFS!I33)-1,0) -> 0.039577243 | K7: =IFERROR((HistoricalFS!K33/HistoricalFS!J33)-1,0) -> -0.019035258 | L7: =IFERROR((HistoricalFS!L33/HistoricalFS!K33)-1,0) -> 0.49966924 | N7: =IFERROR(AVERAGE(D7:L7),0) -> 0.31071361 | O7: =IFERROR(MEDIAN(C7:L7),0) -> 0.27919701
B8: Net Profit Growth | D8: =IFERROR((HistoricalFS!D39/HistoricalFS!C39)-1,0) -> 0.58029773 | E8: =IFERROR((HistoricalFS!E39/HistoricalFS!D39)-1,0) -> 0.26022089 | F8: =IFERROR((HistoricalFS!F39/HistoricalFS!E39)-1,0) -> 0.075144925 | G8: =IFERROR((HistoricalFS!G39/HistoricalFS!F39)-1,0) -> -0.34762224 | H8: =IFERROR((HistoricalFS!H39/HistoricalFS!G39)-1,0) -> 1.2566735 | I8: =IFERROR((HistoricalFS!I39/HistoricalFS!H39)-1,0) -> 0.48953594 | J8: =IFERROR((HistoricalFS!J39/HistoricalFS!I39)-1,0) -> 0.067806964 | K8: =IFERROR((HistoricalFS!K39/HistoricalFS!J39)-1,0) -> -0.045480549 | L8: =IFERROR((HistoricalFS!L39/HistoricalFS!K39)-1,0) -> 0.52022775 | N8: =IFERROR(AVERAGE(D8:L8),0) -> 0.31742277 | O8: =IFERROR(MEDIAN(C8:L8),0) -> 0.26022089
B9: Dividend per share Growth | D9: =IFERROR((HistoricalFS!D48/HistoricalFS!C48)-1,0) -> 0.44227353 | E9: =IFERROR((HistoricalFS!E48/HistoricalFS!D48)-1,0) -> 0.33335336 | F9: =IFERROR((HistoricalFS!F48/HistoricalFS!E48)-1,0) -> -0.19801757 | G9: =IFERROR((HistoricalFS!G48/HistoricalFS!F48)-1,0) -> 0 | H9: =IFERROR((HistoricalFS!H48/HistoricalFS!G48)-1,0) -> 0.875 | I9: =IFERROR((HistoricalFS!I48/HistoricalFS!H48)-1,0) -> 0.33333333 | J9: =IFERROR((HistoricalFS!J48/HistoricalFS!I48)-1,0) -> 0.1 | K9: =IFERROR((HistoricalFS!K48/HistoricalFS!J48)-1,0) -> 0 | L9: =IFERROR((HistoricalFS!L48/HistoricalFS!K48)-1,0) -> 0.36363636 | N9: =IFERROR(AVERAGE(D9:L9),0) -> 0.24995322 | O9: =IFERROR(MEDIAN(C9:L9),0) -> 0.33333333
B11: Gross Margin | C11: =IFERROR(HistoricalFS!C13,0) -> 0.20020014 | D11: =IFERROR(HistoricalFS!D13,0) -> 0.20826228 | E11: =IFERROR(HistoricalFS!E13,0) -> 0.20820769 | F11: =IFERROR(HistoricalFS!F13,0) -> 0.21024131 | G11: =IFERROR(HistoricalFS!G13,0) -> 0.18402329 | H11: =IFERROR(HistoricalFS!H13,0) -> 0.19354839 | I11: =IFERROR(HistoricalFS!I13,0) -> 0.20406654 | J11: =IFERROR(HistoricalFS!J13,0) -> 0.18440216 | ... L11: =IFERROR(HistoricalFS!L13,0) -> 0.16125091 | N11: =IFERROR(AVERAGE(C11:L11),0) -> 0.1926758 | O11: =IFERROR(MEDIAN(C11:L11),0) -> 0.19687426
B12: EBITDA Margin | C12: =IFERROR(HistoricalFS!C19,0) -> 0.08776977 | D12: =IFERROR(HistoricalFS!D19,0) -> 0.10199897 | E12: =IFERROR(HistoricalFS!E19,0) -> 0.10080582 | F12: =IFERROR(HistoricalFS!F19,0) -> 0.11699601 | G12: =IFERROR(HistoricalFS!G19,0) -> 0.079698762 | H12: =IFERROR(HistoricalFS!H19,0) -> 0.11611514 | I12: =IFERROR(HistoricalFS!I19,0) -> 0.12032039 | J12: =IFERROR(HistoricalFS!J19,0) -> 0.10359408 | ... L12: =IFERROR(HistoricalFS!L19,0) -> 0.095416971 | N12: =IFERROR(AVERAGE(C12:L12),0) -> 0.10169001 | O12: =IFERROR(MEDIAN(C12:L12),0) -> 0.1014024
B13: EBIT Margin | C13: =IFERROR(((HistoricalFS!C18-HistoricalFS!C24)/HistoricalFS!C6),0) -> 0.079434696 | D13: =IFERROR(((HistoricalFS!D18-HistoricalFS!D24)/HistoricalFS!D6),0) -> 0.093845632 | E13: =IFERROR(((HistoricalFS!E18-HistoricalFS!E24)/HistoricalFS!E6),0) -> 0.09257265 | F13: =IFERROR(((HistoricalFS!F18-HistoricalFS!F24)/HistoricalFS!F6),0) -> 0.10046551 | G13: =IFERROR(((HistoricalFS!G18-HistoricalFS!G24)/HistoricalFS!G6),0) -> 0.062372944 | H13: =IFERROR(((HistoricalFS!H18-HistoricalFS!H24)/HistoricalFS!H6),0) -> 0.1022605 | I13: =IFERROR(((HistoricalFS!I18-HistoricalFS!I24)/HistoricalFS!I6),0) -> 0.10945163 | J13: =IFERROR(((HistoricalFS!J18-HistoricalFS!J24)/HistoricalFS!J6),0) -> 0.092161929 | ... L13: =IFERROR(((HistoricalFS!L18-HistoricalFS!L24)/HistoricalFS!L6),0) -> 0.085986025 | N13: =IFERROR(AVERAGE(C13:L13),0) -> 0.090127284 | O13: =IFERROR(MEDIAN(C13:L13),0) -> 0.092367289
B14: EBT Margin | C14: =IFERROR(HistoricalFS!C34,0) -> 0.073392842 | D14: =IFERROR(HistoricalFS!D34,0) -> 0.094900858 | E14: =IFERROR(HistoricalFS!E34,0) -> 0.098940163 | F14: =IFERROR(HistoricalFS!F34,0) -> 0.099847995 | G14: =IFERROR(HistoricalFS!G34,0) -> 0.061310294 | H14: =IFERROR(HistoricalFS!H34,0) -> 0.10083683 | I14: =IFERROR(HistoricalFS!I34,0) -> 0.10959951 | J14: =IFERROR(HistoricalFS!J34,0) -> 0.090498003 | ... L14: =IFERROR(HistoricalFS!L34,0) -> 0.077651169 | N14: =IFERROR(AVERAGE(C14:L14),0) -> 0.08819909 | O14: =IFERROR(MEDIAN(C14:L14),0) -> 0.092699431
B15: Net Profit Margin | C15: =IFERROR(HistoricalFS!C40,0) -> 0.052581927 | D15: =IFERROR(HistoricalFS!D40,0) -> 0.068357675 | E15: =IFERROR(HistoricalFS!E40,0) -> 0.070210006 | F15: =IFERROR(HistoricalFS!F40,0) -> 0.070919628 | G15: =IFERROR(HistoricalFS!G40,0) -> 0.045000924 | H15: =IFERROR(HistoricalFS!H40,0) -> 0.076322095 | I15: =IFERROR(HistoricalFS!I40,0) -> 0.08069008 | J15: =IFERROR(HistoricalFS!J40,0) -> 0.068436301 | ... L15: =IFERROR(HistoricalFS!L40,0) -> 0.057921538 | N15: =IFERROR(AVERAGE(C15:L15),0) -> 0.064563734 | O15: =IFERROR(MEDIAN(C15:L15),0) -> 0.068396988
B17: SalesExpenses%Sales | C17: =IFERROR(HistoricalFS!C16,0) -> 0.11243037 | D17: =IFERROR(HistoricalFS!D16,0) -> 0.1062633 | E17: =IFERROR(HistoricalFS!E16,0) -> 0.10740187 | F17: =IFERROR(HistoricalFS!F16,0) -> 0.093245297 | G17: =IFERROR(HistoricalFS!G16,0) -> 0.10432452 | H17: =IFERROR(HistoricalFS!H16,0) -> 0.077433244 | I17: =IFERROR(HistoricalFS!I16,0) -> 0.083746149 | J17: =IFERROR(HistoricalFS!J16,0) -> 0.080808081 | ... L17: =IFERROR(HistoricalFS!L16,0) -> 0.065833942 | N17: =IFERROR(AVERAGE(C17:L17),0) -> 0.090985782 | O17: =IFERROR(MEDIAN(C17:L17),0) -> 0.088495723
B18: Depreciation%Sales | C18: =IFERROR(HistoricalFS!C25,0) -> 0.008335074 | D18: =IFERROR(HistoricalFS!D25,0) -> 0.0081533421 | E18: =IFERROR(HistoricalFS!E25,0) -> 0.0082331742 | F18: =IFERROR(HistoricalFS!F25,0) -> 0.016530496 | G18: =IFERROR(HistoricalFS!G25,0) -> 0.017325818 | H18: =IFERROR(HistoricalFS!H25,0) -> 0.013854648 | I18: =IFERROR(HistoricalFS!I25,0) -> 0.010868762 | J18: =IFERROR(HistoricalFS!J25,0) -> 0.011432151 | ... L18: =IFERROR(HistoricalFS!L25,0) -> 0.0094309463 | N18: =IFERROR(AVERAGE(C18:L18),0) -> 0.011562729 | O18: =IFERROR(MEDIAN(C18:L18),0) -> 0.011150456
B19: OperatingIncome%Sales | C19: =C13 -> 0.079434696 | D19: =D13 -> 0.093845632 | E19: =E13 -> 0.09257265 | F19: =F13 -> 0.10046551 | G19: =G13 -> 0.062372944 | H19: =H13 -> 0.1022605 | I19: =I13 -> 0.10945163 | J19: =J13 -> 0.092161929 | ... L19: =L13 -> 0.085986025 | N19: =IFERROR(AVERAGE(C19:L19),0) -> 0.090127284 | O19: =IFERROR(MEDIAN(C19:L19),0) -> 0.092367289
B21: Return on Capital Employed | C21: =IFERROR((HistoricalFS!C18-HistoricalFS!C24)/(SUM(HistoricalFS!C54:C56)),0) -> 0.17226537 | D21: =IFERROR((HistoricalFS!D18-HistoricalFS!D24)/(SUM(HistoricalFS!D54:D56)),0) -> 0.22309313 | E21: =IFERROR((HistoricalFS!E18-HistoricalFS!E24)/(SUM(HistoricalFS!E54:E56)),0) -> 0.21634431 | F21: =IFERROR((HistoricalFS!F18-HistoricalFS!F24)/(SUM(HistoricalFS!F54:F56)),0) -> 0.20672466 | G21: =IFERROR((HistoricalFS!G18-HistoricalFS!G24)/(SUM(HistoricalFS!G54:G56)),0) -> 0.10277884 | H21: =IFERROR((HistoricalFS!H18-HistoricalFS!H24)/(SUM(HistoricalFS!H54:H56)),0) -> 0.17764507 | I21: =IFERROR((HistoricalFS!I18-HistoricalFS!I24)/(SUM(HistoricalFS!I54:I56)),0) -> 0.20930342 | J21: =IFERROR((HistoricalFS!J18-HistoricalFS!J24)/(SUM(HistoricalFS!J54:J56)),0) -> 0.18891698 | ... L21: =IFERROR((HistoricalFS!L18-HistoricalFS!L24)/(SUM(HistoricalFS!L54:L56)),0) -> 0.16257232 | N21: =IFERROR(AVERAGE(C21:L21),0) -> 0.18139912 | O21: =IFERROR(MEDIAN(C21:L21),0) -> 0.18328102
B22: Retained Earnings% | C22: =IFERROR(HistoricalFS!C51,0) -> 0.66895652 | D22: =IFERROR(HistoricalFS!D51,0) -> 0.69787006 | E22: =IFERROR(HistoricalFS!E51,0) -> 0.68033702 | F22: =IFERROR(HistoricalFS!F51,0) -> 0.76155392 | G22: =IFERROR(HistoricalFS!G51,0) -> 0.63449692 | H22: =IFERROR(HistoricalFS!H51,0) -> 0.69631483 | I22: =IFERROR(HistoricalFS!I51,0) -> 0.72816127 | J22: =IFERROR(HistoricalFS!J51,0) -> 0.71996568 | ... L22: =IFERROR(HistoricalFS!L51,0) -> 0.73684211 | N22: =IFERROR(AVERAGE(C22:L22),0) -> 0.7031121 | O22: =IFERROR(MEDIAN(C22:L22),0) -> 0.70224639
B23: Return on Equity% | C23: =IFERROR(HistoricalFS!C39/SUM(HistoricalFS!C54:C55),0) -> 0.16474891 | D23: =IFERROR(HistoricalFS!D39/SUM(HistoricalFS!D54:D55),0) -> 0.21649037 | E23: =IFERROR(HistoricalFS!E39/SUM(HistoricalFS!E54:E55),0) -> 0.228767 | F23: =IFERROR(HistoricalFS!F39/SUM(HistoricalFS!F54:F55),0) -> 0.22387164 | G23: =IFERROR(HistoricalFS!G39/SUM(HistoricalFS!G54:G55),0) -> 0.12991863 | H23: =IFERROR(HistoricalFS!H39/SUM(HistoricalFS!H54:H55),0) -> 0.23626787 | I23: =IFERROR(HistoricalFS!I39/SUM(HistoricalFS!I54:I55),0) -> 0.27626361 | J23: =IFERROR(HistoricalFS!J39/SUM(HistoricalFS!J54:J55),0) -> 0.37219206 | ... L23: =IFERROR(HistoricalFS!L39/SUM(HistoricalFS!L54:L55),0) -> 0.32305929 | N23: =IFERROR(AVERAGE(C23:L23),0) -> 0.24586578 | O23: =IFERROR(MEDIAN(C23:L23),0) -> 0.23251743
B24: Self Sustained Growth Rate | C24: =IFERROR(C22*C23,0) -> 0.11020986 | D24: =IFERROR(D22*D23,0) -> 0.15108215 | E24: =IFERROR(E22*E23,0) -> 0.15563866 | F24: =IFERROR(F22*F23,0) -> 0.17049033 | G24: =IFERROR(G22*G23,0) -> 0.082432973 | H24: =IFERROR(H22*H23,0) -> 0.16451682 | I24: =IFERROR(I22*I23,0) -> 0.20116446 | J24: =IFERROR(J22*J23,0) -> 0.26796551 | ... L24: =IFERROR(L22*L23,0) -> 0.23804369 | N24: =IFERROR(AVERAGE(C24:L24),0) -> 0.17444006 | O24: =IFERROR(MEDIAN(C24:L24),0) -> 0.16750358
B25: Interest Coverage Ratio | C25: =IFERROR((HistoricalFS!C18-HistoricalFS!C24)/HistoricalFS!C21,0) -> 27.911235 | D25: =IFERROR((HistoricalFS!D18-HistoricalFS!D24)/HistoricalFS!D21,0) -> 28.585979 | E25: =IFERROR((HistoricalFS!E18-HistoricalFS!E24)/HistoricalFS!E21,0) -> 34.848687 | F25: =IFERROR((HistoricalFS!F18-HistoricalFS!F24)/HistoricalFS!F21,0) -> 12.740964 | G25: =IFERROR((HistoricalFS!G18-HistoricalFS!G24)/HistoricalFS!G21,0) -> 6.6502463 | H25: =IFERROR((HistoricalFS!H18-HistoricalFS!H24)/HistoricalFS!H21,0) -> 13.509174 | I25: =IFERROR((HistoricalFS!I18-HistoricalFS!I24)/HistoricalFS!I21,0) -> 14.803333 | J25: =IFERROR((HistoricalFS!J18-HistoricalFS!J24)/HistoricalFS!J21,0) -> 7.6058158 | ... L25: =IFERROR((HistoricalFS!L18-HistoricalFS!L24)/HistoricalFS!L21,0) -> 6.3822034 | N25: =IFERROR(AVERAGE(C25:L25),0) -> 15.828528 | O25: =IFERROR(MEDIAN(C25:L25),0) -> 13.125069
B27: Price to Earnings | C27: =IFERROR('Data Sheet'!B92/HistoricalFS!C44,0) -> 58.918863 | D27: =IFERROR('Data Sheet'!C92/HistoricalFS!D44,0) -> 75.920351 | E27: =IFERROR('Data Sheet'!D92/HistoricalFS!E44,0) -> 73.001435 | F27: =IFERROR('Data Sheet'!E92/HistoricalFS!F44,0) -> 55.521692 | G27: =IFERROR('Data Sheet'!F92/HistoricalFS!G44,0) -> 142.0161 | H27: =IFERROR('Data Sheet'!G92/HistoricalFS!H44,0) -> 102.43831 | I27: =IFERROR('Data Sheet'!H92/HistoricalFS!I44,0) -> 68.195731 | J27: =IFERROR('Data Sheet'!I92/HistoricalFS!J44,0) -> 96.545711 | ... L27: =IFERROR('Data Sheet'!K92/HistoricalFS!L44,0) -> 69.151447 | N27: =IFERROR(AVERAGE(C27:L27),0) -> 82.320925 | O27: =IFERROR(MEDIAN(C27:L27),0) -> 74.460893
B28: EV/EBITDA | C28: ='Data Sheet'!B99/HistoricalFS!C18 -> 36.245764 | D28: ='Data Sheet'!C99/HistoricalFS!D18 -> 51.532961 | E28: ='Data Sheet'!D99/HistoricalFS!E18 -> 51.50991 | F28: ='Data Sheet'!E99/HistoricalFS!F18 -> 34.947173 | G28: ='Data Sheet'!F99/HistoricalFS!G18 -> 83.131408 | H28: ='Data Sheet'!G99/HistoricalFS!H18 -> 69.037499 | I28: ='Data Sheet'!H99/HistoricalFS!I18 -> 47.377473 | J28: ='Data Sheet'!I99/HistoricalFS!J18 -> 66.425889 | ... L28: ='Data Sheet'!K99/HistoricalFS!L18 -> 45.412145 | N28: =IFERROR(AVERAGE(C28:L28),0) -> 53.675426 | O28: =IFERROR(MEDIAN(C28:L28),0) -> 51.321974
B29: EV/Sales | C29: ='Data Sheet'!B99/HistoricalFS!C6 -> 3.1812824 | D29: ='Data Sheet'!C99/HistoricalFS!D6 -> 5.2563091 | E29: ='Data Sheet'!D99/HistoricalFS!E6 -> 5.1924989 | F29: ='Data Sheet'!E99/HistoricalFS!F6 -> 4.0886797 | G29: ='Data Sheet'!F99/HistoricalFS!G6 -> 6.6254703 | H29: ='Data Sheet'!G99/HistoricalFS!H6 -> 8.0162991 | I29: ='Data Sheet'!H99/HistoricalFS!I6 -> 5.7004762 | J29: ='Data Sheet'!I99/HistoricalFS!J6 -> 6.8813289 | ... L29: ='Data Sheet'!K99/HistoricalFS!L6 -> 4.3330893 | N29: =IFERROR(AVERAGE(C29:L29),0) -> 5.4091452 | O29: =IFERROR(MEDIAN(C29:L29),0) -> 5.224404
B30: Price to Book Value | C30: ='Data Sheet'!B98/'Data Sheet'!B100 -> 9.7068186 | D30: ='Data Sheet'!C98/'Data Sheet'!C100 -> 16.436025 | E30: ='Data Sheet'!D98/'Data Sheet'!D100 -> 16.700319 | F30: ='Data Sheet'!E98/'Data Sheet'!E100 -> 12.429732 | G30: ='Data Sheet'!F98/'Data Sheet'!F100 -> 18.450537 | H30: ='Data Sheet'!G98/'Data Sheet'!G100 -> 24.20288 | I30: ='Data Sheet'!H98/'Data Sheet'!H100 -> 18.839998 | J30: ='Data Sheet'!I98/'Data Sheet'!I100 -> 35.933547 | ... L30: ='Data Sheet'!K98/'Data Sheet'!K100 -> 22.340017 | N30: =IFERROR(AVERAGE(C30:L30),0) -> 19.843666 | O30: =IFERROR(MEDIAN(C30:L30),0) -> 18.645268
B32: Debtor Turnover Ratio | C32: =IFERROR(HistoricalFS!C6/HistoricalFS!C66,0) -> 63.87683 | D32: =IFERROR(HistoricalFS!D6/HistoricalFS!D66,0) -> 54.515777 | E32: =IFERROR(HistoricalFS!E6/HistoricalFS!E66,0) -> 47.041313 | F32: =IFERROR(HistoricalFS!F6/HistoricalFS!F66,0) -> 67.474359 | G32: =IFERROR(HistoricalFS!G6/HistoricalFS!G66,0) -> 59.136612 | H32: =IFERROR(HistoricalFS!H6/HistoricalFS!H66,0) -> 50.971681 | I32: =IFERROR(HistoricalFS!I6/HistoricalFS!I66,0) -> 60.200297 | J32: =IFERROR(HistoricalFS!J6/HistoricalFS!J66,0) -> 50.180747 | ... L32: =IFERROR(HistoricalFS!L6/HistoricalFS!L66,0) -> 95.615721 | N32: =IFERROR(AVERAGE(C32:L32),0) -> 60.562008 | O32: =IFERROR(MEDIAN(C32:L32),0) -> 57.871677
B33: Creditor Turnover Ratio | C33: =IFERROR(HistoricalFS!C6/'Data Sheet'!B62,0) -> 16.935926 | D33: =IFERROR(HistoricalFS!D6/'Data Sheet'!C62,0) -> 18.359647 | E33: =IFERROR(HistoricalFS!E6/'Data Sheet'!D62,0) -> 21.830596 | F33: =IFERROR(HistoricalFS!F6/'Data Sheet'!E62,0) -> 35.322148 | G33: =IFERROR(HistoricalFS!G6/'Data Sheet'!F62,0) -> 27.432193 | H33: =IFERROR(HistoricalFS!H6/'Data Sheet'!G62,0) -> 22.255796 | I33: =IFERROR(HistoricalFS!I6/'Data Sheet'!H62,0) -> 33.42257 | J33: =IFERROR(HistoricalFS!J6/'Data Sheet'!I62,0) -> 36.229787 | ... L33: =IFERROR(HistoricalFS!L6/'Data Sheet'!K62,0) -> 30.581006 | N33: =IFERROR(AVERAGE(C33:L33),0) -> 27.316743 | O33: =IFERROR(MEDIAN(C33:L33),0) -> 29.006599
B34: Inventory Turnover | C34: =IFERROR(HistoricalFS!C9/HistoricalFS!C67,0) -> 2.153181 | D34: =IFERROR(HistoricalFS!D9/HistoricalFS!D67,0) -> 2.1540885 | E34: =IFERROR(HistoricalFS!E9/HistoricalFS!E67,0) -> 2.2248729 | F34: =IFERROR(HistoricalFS!F9/HistoricalFS!F67,0) -> 2.0518327 | G34: =IFERROR(HistoricalFS!G9/HistoricalFS!G67,0) -> 2.1004995 | H34: =IFERROR(HistoricalFS!H9/HistoricalFS!H67,0) -> 1.7065912 | I34: =IFERROR(HistoricalFS!I9/HistoricalFS!I67,0) -> 1.9473589 | J34: =IFERROR(HistoricalFS!J9/HistoricalFS!J67,0) -> 2.1869718 | ... L34: =IFERROR(HistoricalFS!L9/HistoricalFS!L67,0) -> 1.7186674 | N34: =IFERROR(AVERAGE(C34:L34),0) -> 2.0018972 | O34: =IFERROR(MEDIAN(C34:L34),0) -> 2.0761661
B35: Fixed Asset Turnover | C35: =IFERROR(HistoricalFS!C6/HistoricalFS!C60,0) -> 11.155554 | D35: =IFERROR(HistoricalFS!D6/HistoricalFS!D60,0) -> 10.937482 | E35: =IFERROR(HistoricalFS!E6/HistoricalFS!E60,0) -> 12.624883 | F35: =IFERROR(HistoricalFS!F6/HistoricalFS!F60,0) -> 7.9954425 | G35: =IFERROR(HistoricalFS!G6/HistoricalFS!G60,0) -> 8.5786762 | H35: =IFERROR(HistoricalFS!H6/HistoricalFS!H60,0) -> 11.320362 | I35: =IFERROR(HistoricalFS!I6/HistoricalFS!I60,0) -> 13.534023 | J35: =IFERROR(HistoricalFS!J6/HistoricalFS!J60,0) -> 13.772985 | ... L35: =IFERROR(HistoricalFS!L6/HistoricalFS!L60,0) -> 12.733934 | N35: =IFERROR(AVERAGE(C35:L35),0) -> 11.753665 | O35: =IFERROR(MEDIAN(C35:L35),0) -> 11.972622
B36: Capital Turnover Ratio | C36: =IFERROR(HistoricalFS!C6/(SUM(HistoricalFS!C54:C55)),0) -> 3.1331851 | D36: =IFERROR(HistoricalFS!D6/(SUM(HistoricalFS!D54:D55)),0) -> 3.1670236 | E36: =IFERROR(HistoricalFS!E6/(SUM(HistoricalFS!E54:E55)),0) -> 3.2583248 | F36: =IFERROR(HistoricalFS!F6/(SUM(HistoricalFS!F54:F55)),0) -> 3.1566952 | G36: =IFERROR(HistoricalFS!G6/(SUM(HistoricalFS!G54:G55)),0) -> 2.8870215 | H36: =IFERROR(HistoricalFS!H6/(SUM(HistoricalFS!H54:H55)),0) -> 3.0956681 | I36: =IFERROR(HistoricalFS!I6/(SUM(HistoricalFS!I54:I55)),0) -> 3.4237617 | J36: =IFERROR(HistoricalFS!J6/(SUM(HistoricalFS!J54:J55)),0) -> 5.438518 | ... L36: =IFERROR(HistoricalFS!L6/(SUM(HistoricalFS!L54:L55)),0) -> 5.577533 | N36: =IFERROR(AVERAGE(C36:L36),0) -> 3.8338694 | O36: =IFERROR(MEDIAN(C36:L36),0) -> 3.2126742
B38: (in days)
B39: Debtor Days | C39: =IFERROR(365/C32,0) -> 5.714122 | D39: =IFERROR(365/D32,0) -> 6.6953095 | E39: =IFERROR(365/E32,0) -> 7.7591372 | F39: =IFERROR(365/F32,0) -> 5.4094623 | G39: =IFERROR(365/G32,0) -> 6.1721493 | H39: =IFERROR(365/H32,0) -> 7.1608389 | I39: =IFERROR(365/I32,0) -> 6.063093 | J39: =IFERROR(365/J32,0) -> 7.2737061 | ... L39: =IFERROR(365/L32,0) -> 3.8173639 | N39: =IFERROR(AVERAGE(C39:L39),0) -> 6.2513177 | O39: =IFERROR(MEDIAN(C39:L39),0) -> 6.3100723
B40: Payable Days | C40: =IFERROR(365/C33,0) -> 21.551818 | D40: =IFERROR(365/D33,0) -> 19.880557 | E40: =IFERROR(365/E33,0) -> 16.719653 | F40: =IFERROR(365/F33,0) -> 10.33346 | G40: =IFERROR(365/G33,0) -> 13.305535 | H40: =IFERROR(365/H33,0) -> 16.400222 | I40: =IFERROR(365/I33,0) -> 10.920764 | J40: =IFERROR(365/J33,0) -> 10.074583 | ... L40: =IFERROR(365/L33,0) -> 11.935513 | N40: =IFERROR(AVERAGE(C40:L40),0) -> 14.297362 | O40: =IFERROR(MEDIAN(C40:L40),0) -> 12.620524
B41: Inventory Days | C41: =IFERROR(365/C34,0) -> 169.51663 | D41: =IFERROR(365/D34,0) -> 169.44522 | E41: =IFERROR(365/E34,0) -> 164.05431 | F41: =IFERROR(365/F34,0) -> 177.88975 | G41: =IFERROR(365/G34,0) -> 173.76819 | H41: =IFERROR(365/H34,0) -> 213.87664 | I41: =IFERROR(365/I34,0) -> 187.43335 | J41: =IFERROR(365/J34,0) -> 166.89744 | ... L41: =IFERROR(365/L34,0) -> 212.37384 | N41: =IFERROR(AVERAGE(C41:L41),0) -> 184.08999 | O41: =IFERROR(MEDIAN(C41:L41),0) -> 175.82897
B42: Cash Conversion Cycle (in days) | C42: =IFERROR(SUM(C39,C41)-C40,0) -> 153.67894 | D42: =IFERROR(SUM(D39,D41)-D40,0) -> 156.25997 | E42: =IFERROR(SUM(E39,E41)-E40,0) -> 155.0938 | F42: =IFERROR(SUM(F39,F41)-F40,0) -> 172.96575 | G42: =IFERROR(SUM(G39,G41)-G40,0) -> 166.6348 | H42: =IFERROR(SUM(H39,H41)-H40,0) -> 204.63726 | I42: =IFERROR(SUM(I39,I41)-I40,0) -> 182.57568 | J42: =IFERROR(SUM(J39,J41)-J40,0) -> 164.09656 | ... L42: =IFERROR(SUM(L39,L41)-L40,0) -> 204.2557 | N42: =IFERROR(AVERAGE(C42:L42),0) -> 176.04394 | O42: =IFERROR(MEDIAN(C42:L42),0) -> 169.80028
B44: CFO/Sales | C44: =IFERROR(HistoricalFS!C83/HistoricalFS!C6,0) -> 0.14063976 | D44: =IFERROR(HistoricalFS!D83/HistoricalFS!D6,0) -> -0.06309023 | E44: =IFERROR(HistoricalFS!E83/HistoricalFS!E6,0) -> 0.01001086 | F44: =IFERROR(HistoricalFS!F83/HistoricalFS!F6,0) -> -0.087972639 | G44: =IFERROR(HistoricalFS!G83/HistoricalFS!G6,0) -> 0.19104602 | H44: =IFERROR(HistoricalFS!H83/HistoricalFS!H6,0) -> -0.17820063 | I44: =IFERROR(HistoricalFS!I83/HistoricalFS!I6,0) -> -0.023265558 | J44: =IFERROR(HistoricalFS!J83/HistoricalFS!J6,0) -> -0.017285256 | ... L44: =IFERROR(HistoricalFS!L83/HistoricalFS!L6,0) -> -0.032357508 | N44: =IFERROR(AVERAGE(C44:L44),0) -> -0.019668995 | O44: =IFERROR(MEDIAN(C44:L44),0) -> -0.027811533
B45: CFO/Total Assets | C45: =IFERROR(HistoricalFS!C83/HistoricalFS!C71,0) -> 0.2218239 | D45: =IFERROR(HistoricalFS!D83/HistoricalFS!D71,0) -> -0.10681606 | E45: =IFERROR(HistoricalFS!E83/HistoricalFS!E71,0) -> 0.016908856 | F45: =IFERROR(HistoricalFS!F83/HistoricalFS!F71,0) -> -0.13673952 | G45: =IFERROR(HistoricalFS!G83/HistoricalFS!G71,0) -> 0.2514595 | H45: =IFERROR(HistoricalFS!H83/HistoricalFS!H71,0) -> -0.24221257 | I45: =IFERROR(HistoricalFS!I83/HistoricalFS!I71,0) -> -0.034937084 | J45: =IFERROR(HistoricalFS!J83/HistoricalFS!J71,0) -> -0.027989983 | ... L45: =IFERROR(HistoricalFS!L83/HistoricalFS!L71,0) -> -0.046795793 | N45: =IFERROR(AVERAGE(C45:L45),0) -> -0.03079067 | O45: =IFERROR(MEDIAN(C45:L45),0) -> -0.040866438
B46: CFO/Total Debt | C46: =IFERROR(HistoricalFS!C83/HistoricalFS!C56,0) -> 0.99074069 | D46: =IFERROR(HistoricalFS!D83/HistoricalFS!D56,0) -> -0.60141572 | E46: =IFERROR(HistoricalFS!E83/HistoricalFS!E56,0) -> 0.08274202 | F46: =IFERROR(HistoricalFS!F83/HistoricalFS!F56,0) -> -0.51993262 | G46: =IFERROR(HistoricalFS!G83/HistoricalFS!G56,0) -> 0.73341611 | H46: =IFERROR(HistoricalFS!H83/HistoricalFS!H56,0) -> -0.70542955 | I46: =IFERROR(HistoricalFS!I83/HistoricalFS!I56,0) -> -0.10077933 | J46: =IFERROR(HistoricalFS!J83/HistoricalFS!J56,0) -> -0.056865018 | ... L46: =IFERROR(HistoricalFS!L83/HistoricalFS!L56,0) -> -0.092550864 | N46: =IFERROR(AVERAGE(C46:L46),0) -> -0.066642603 | O46: =IFERROR(MEDIAN(C46:L46),0) -> -0.096665098

Sheet Common Size Statement
B3: ="Common Size Income Statement - "&'Data Sheet'!$B$2 -> Common Size Income Statement - TITAN COMPANY LTD
B5: Particulars | C5: ='Data Sheet'!B$17 -> 42825 | D5: ='Data Sheet'!C$17 -> 43190 | E5: ='Data Sheet'!D$17 -> 43555 | F5: ='Data Sheet'!E$17 -> 43921 | G5: ='Data Sheet'!F$17 -> 44286 | H5: ='Data Sheet'!G$17 -> 44651 | I5: ='Data Sheet'!H$17 -> 45016 | J5: ='Data Sheet'!I$17 -> 45382 | ... L5: ='Data Sheet'!K$17 -> 46112
B7: ='Data Sheet'!A18 -> Sales | C7: ='Data Sheet'!B18/'Data Sheet'!B$18 -> 1 | D7: ='Data Sheet'!C18/'Data Sheet'!C$18 -> 1 | E7: ='Data Sheet'!D18/'Data Sheet'!D$18 -> 1 | F7: ='Data Sheet'!E18/'Data Sheet'!E$18 -> 1 | G7: ='Data Sheet'!F18/'Data Sheet'!F$18 -> 1 | H7: ='Data Sheet'!G18/'Data Sheet'!G$18 -> 1 | I7: ='Data Sheet'!H18/'Data Sheet'!H$18 -> 1 | J7: ='Data Sheet'!I18/'Data Sheet'!I$18 -> 1 | ... L7: ='Data Sheet'!K18/'Data Sheet'!K$18 -> 1
B8: ='Data Sheet'!A19 -> Raw Material Cost | C8: ='Data Sheet'!B19/'Data Sheet'!B$18 -> 0.74061277 | D8: ='Data Sheet'!C19/'Data Sheet'!C$18 -> 0.78567064 | E8: ='Data Sheet'!D19/'Data Sheet'!D$18 -> 0.76702706 | F8: ='Data Sheet'!E19/'Data Sheet'!E$18 -> 0.76159035 | G8: ='Data Sheet'!F19/'Data Sheet'!F$18 -> 0.75272593 | H8: ='Data Sheet'!G19/'Data Sheet'!G$18 -> 0.91794854 | I8: ='Data Sheet'!H19/'Data Sheet'!H$18 -> 0.8031793 | J8: ='Data Sheet'!I19/'Data Sheet'!I$18 -> 0.82419153 | ... L8: ='Data Sheet'!K19/'Data Sheet'!K$18 -> 0.91618332
B9: ='Data Sheet'!A20 -> Change in Inventory | C9: ='Data Sheet'!B20/'Data Sheet'!B$18 -> 0.02365689 | D9: ='Data Sheet'!C20/'Data Sheet'!C$18 -> 0.060708683 | E9: ='Data Sheet'!D20/'Data Sheet'!D$18 -> 0.039255212 | F9: ='Data Sheet'!E20/'Data Sheet'!E$18 -> 0.041706251 | G9: ='Data Sheet'!F20/'Data Sheet'!F$18 -> -0.0056366661 | H9: ='Data Sheet'!G20/'Data Sheet'!G$18 -> 0.16649884 | I9: ='Data Sheet'!H20/'Data Sheet'!H$18 -> 0.055058534 | J9: ='Data Sheet'!I20/'Data Sheet'!I$18 -> 0.05228643 | ... L9: ='Data Sheet'!K20/'Data Sheet'!K$18 -> 0.11344538
B10: ='Data Sheet'!A21 -> Power and Fuel | C10: ='Data Sheet'!B21/'Data Sheet'!B$18 -> 0.0033059771 | D10: ='Data Sheet'!C21/'Data Sheet'!C$18 -> 0.0028114545 | E10: ='Data Sheet'!D21/'Data Sheet'!D$18 -> 0.0024526608 | F10: ='Data Sheet'!E21/'Data Sheet'!E$18 -> 0.0024700741 | G10: ='Data Sheet'!F21/'Data Sheet'!F$18 -> 0.0017094807 | H10: ='Data Sheet'!G21/'Data Sheet'!G$18 -> 0.0015625543 | I10: ='Data Sheet'!H21/'Data Sheet'!H$18 -> 0.0014540974 | J10: ='Data Sheet'!I21/'Data Sheet'!I$18 -> 0.0013898677 | ... L10: ='Data Sheet'!K21/'Data Sheet'!K$18 -> 0.00099333212
B11: ='Data Sheet'!A22 -> Other Mfr. Exp | C11: ='Data Sheet'!B22/'Data Sheet'!B$18 -> 0.012097282 | D11: ='Data Sheet'!C22/'Data Sheet'!C$18 -> 0.007743907 | E11: ='Data Sheet'!D22/'Data Sheet'!D$18 -> 0.0097722175 | F11: ='Data Sheet'!E22/'Data Sheet'!E$18 -> 0.010212806 | G11: ='Data Sheet'!F22/'Data Sheet'!F$18 -> 0.0065145075 | H11: ='Data Sheet'!G22/'Data Sheet'!G$18 -> 0.0063543873 | I11: ='Data Sheet'!H22/'Data Sheet'!H$18 -> 0.0055452865 | J11: ='Data Sheet'!I22/'Data Sheet'!I$18 -> 0.0055986219 | ... L11: ='Data Sheet'!K22/'Data Sheet'!K$18 -> 0.0042816039
B12: ='Data Sheet'!A23 -> Employee Cost | C12: ='Data Sheet'!B23/'Data Sheet'!B$18 -> 0.067440726 | D12: ='Data Sheet'!C23/'Data Sheet'!C$18 -> 0.056220405 | E12: ='Data Sheet'!D23/'Data Sheet'!D$18 -> 0.051795584 | F12: ='Data Sheet'!E23/'Data Sheet'!E$18 -> 0.057191716 | G12: ='Data Sheet'!F23/'Data Sheet'!F$18 -> 0.049390131 | H12: ='Data Sheet'!G23/'Data Sheet'!G$18 -> 0.047084968 | I12: ='Data Sheet'!H23/'Data Sheet'!H$18 -> 0.040813309 | J12: ='Data Sheet'!I23/'Data Sheet'!I$18 -> 0.036704252 | ... L12: ='Data Sheet'!K23/'Data Sheet'!K$18 -> 0.030736208
B13: ='Data Sheet'!A24 -> Selling and admin | C13: ='Data Sheet'!B24/'Data Sheet'!B$18 -> 0.09133365 | D13: ='Data Sheet'!C24/'Data Sheet'!C$18 -> 0.079269741 | E13: ='Data Sheet'!D24/'Data Sheet'!D$18 -> 0.073530274 | F13: ='Data Sheet'!E24/'Data Sheet'!E$18 -> 0.069827095 | G13: ='Data Sheet'!F24/'Data Sheet'!F$18 -> 0.047542044 | H13: ='Data Sheet'!G24/'Data Sheet'!G$18 -> 0.058925657 | I13: ='Data Sheet'!H24/'Data Sheet'!H$18 -> 0.066913124 | J13: ='Data Sheet'!I24/'Data Sheet'!I$18 -> 0.063601128 | ... L13: ='Data Sheet'!K24/'Data Sheet'!K$18 -> 0.0477827
B14: ='Data Sheet'!A25 -> Other Expenses | C14: ='Data Sheet'!B25/'Data Sheet'!B$18 -> 0.021096719 | D14: ='Data Sheet'!C25/'Data Sheet'!C$18 -> 0.026993561 | E14: ='Data Sheet'!D25/'Data Sheet'!D$18 -> 0.033871594 | F14: ='Data Sheet'!E25/'Data Sheet'!E$18 -> 0.023418203 | G14: ='Data Sheet'!F25/'Data Sheet'!F$18 -> 0.05678248 | H14: ='Data Sheet'!G25/'Data Sheet'!G$18 -> 0.018507587 | I14: ='Data Sheet'!H25/'Data Sheet'!H$18 -> 0.016833025 | J14: ='Data Sheet'!I25/'Data Sheet'!I$18 -> 0.017206953 | ... L14: ='Data Sheet'!K25/'Data Sheet'!K$18 -> 0.018051242
B15: ='Data Sheet'!A26 -> Other Income | C15: ='Data Sheet'!B26/'Data Sheet'!B$18 -> -0.0031958784 | D15: ='Data Sheet'!C26/'Data Sheet'!C$18 -> 0.0043381512 | E15: ='Data Sheet'!D26/'Data Sheet'!D$18 -> 0.009023931 | F15: ='Data Sheet'!E26/'Data Sheet'!E$18 -> 0.007267718 | G15: ='Data Sheet'!F26/'Data Sheet'!F$18 -> 0.0083163925 | H15: ='Data Sheet'!G26/'Data Sheet'!G$18 -> 0.0061460467 | I15: ='Data Sheet'!H26/'Data Sheet'!H$18 -> 0.0075415896 | J15: ='Data Sheet'!I26/'Data Sheet'!I$18 -> 0.010453371 | ... L15: ='Data Sheet'!K26/'Data Sheet'!K$18 -> 0.0051379247
B16: ='Data Sheet'!A27 -> Depreciation | C16: ='Data Sheet'!B27/'Data Sheet'!B$18 -> 0.008335074 | D16: ='Data Sheet'!C27/'Data Sheet'!C$18 -> 0.0081533421 | E16: ='Data Sheet'!D27/'Data Sheet'!D$18 -> 0.0082331742 | F16: ='Data Sheet'!E27/'Data Sheet'!E$18 -> 0.016530496 | G16: ='Data Sheet'!F27/'Data Sheet'!F$18 -> 0.017325818 | H16: ='Data Sheet'!G27/'Data Sheet'!G$18 -> 0.013854648 | I16: ='Data Sheet'!H27/'Data Sheet'!H$18 -> 0.010868762 | J16: ='Data Sheet'!I27/'Data Sheet'!I$18 -> 0.011432151 | ... L16: ='Data Sheet'!K27/'Data Sheet'!K$18 -> 0.0094309463
B17: ='Data Sheet'!A28 -> Interest | C17: ='Data Sheet'!B28/'Data Sheet'!B$18 -> 0.0028459757 | D17: ='Data Sheet'!C28/'Data Sheet'!C$18 -> 0.0032829253 | E17: ='Data Sheet'!D28/'Data Sheet'!D$18 -> 0.0026564172 | F17: ='Data Sheet'!E28/'Data Sheet'!E$18 -> 0.0078852366 | G17: ='Data Sheet'!F28/'Data Sheet'!F$18 -> 0.0093790427 | H17: ='Data Sheet'!G28/'Data Sheet'!G$18 -> 0.0075697073 | I17: ='Data Sheet'!H28/'Data Sheet'!H$18 -> 0.0073937153 | J17: ='Data Sheet'!I28/'Data Sheet'!I$18 -> 0.012117297 | ... L17: ='Data Sheet'!K28/'Data Sheet'!K$18 -> 0.01347278
B18: ='Data Sheet'!A29 -> Profit before tax | C18: ='Data Sheet'!B29/'Data Sheet'!B$18 -> 0.073392842 | D18: ='Data Sheet'!C29/'Data Sheet'!C$18 -> 0.094900858 | E18: ='Data Sheet'!D29/'Data Sheet'!D$18 -> 0.098940163 | F18: ='Data Sheet'!E29/'Data Sheet'!E$18 -> 0.099847995 | G18: ='Data Sheet'!F29/'Data Sheet'!F$18 -> 0.061310294 | H18: ='Data Sheet'!G29/'Data Sheet'!G$18 -> 0.10083683 | I18: ='Data Sheet'!H29/'Data Sheet'!H$18 -> 0.10959951 | J18: ='Data Sheet'!I29/'Data Sheet'!I$18 -> 0.090498003 | ... L18: ='Data Sheet'!K29/'Data Sheet'!K$18 -> 0.077651169
... B21: ='Data Sheet'!A32 -> Dividend Amount | C21: ='Data Sheet'!B32/'Data Sheet'!B$18 -> 0.017406904 | D21: ='Data Sheet'!C32/'Data Sheet'!C$18 -> 0.0206529 | E21: ='Data Sheet'!D32/'Data Sheet'!D$18 -> 0.02244354 | F21: ='Data Sheet'!E32/'Data Sheet'!E$18 -> 0.016910507 | G21: ='Data Sheet'!F32/'Data Sheet'!F$18 -> 0.016447976 | H21: ='Data Sheet'!G32/'Data Sheet'!G$18 -> 0.023177888 | I21: ='Data Sheet'!H32/'Data Sheet'!H$18 -> 0.021934689 | J21: ='Data Sheet'!I32/'Data Sheet'!I$18 -> 0.019164513 | ... L21: ='Data Sheet'!K32/'Data Sheet'!K$18 -> 0.01524251
B22: ='Data Sheet'!A35 -> EBITDA | C22: ='Data Sheet'!B35/'Data Sheet'!B$18 -> 0.08776977 | D22: ='Data Sheet'!C35/'Data Sheet'!C$18 -> 0.10199897 | E22: ='Data Sheet'!D35/'Data Sheet'!D$18 -> 0.10080582 | F22: ='Data Sheet'!E35/'Data Sheet'!E$18 -> 0.11699601 | G22: ='Data Sheet'!F35/'Data Sheet'!F$18 -> 0.079698762 | H22: ='Data Sheet'!G35/'Data Sheet'!G$18 -> 0.11611514 | I22: ='Data Sheet'!H35/'Data Sheet'!H$18 -> 0.12032039 | J22: ='Data Sheet'!I35/'Data Sheet'!I$18 -> 0.10359408 | ... L22: ='Data Sheet'!K35/'Data Sheet'!K$18 -> 0.095416971
B24: ="Common Size Balance Sheet - "&'Data Sheet'!$B$2 -> Common Size Balance Sheet - TITAN COMPANY LTD
B26: Particulars | C26: ='Data Sheet'!B$17 -> 42825 | D26: ='Data Sheet'!C$17 -> 43190 | E26: ='Data Sheet'!D$17 -> 43555 | F26: ='Data Sheet'!E$17 -> 43921 | G26: ='Data Sheet'!F$17 -> 44286 | H26: ='Data Sheet'!G$17 -> 44651 | I26: ='Data Sheet'!H$17 -> 45016 | J26: ='Data Sheet'!I$17 -> 45382 | ... L26: ='Data Sheet'!K$17 -> 46112
B28: Total Liabilities | C28: ='Data Sheet'!B63/'Data Sheet'!B$63 -> 1 | D28: ='Data Sheet'!C63/'Data Sheet'!C$63 -> 1 | E28: ='Data Sheet'!D63/'Data Sheet'!D$63 -> 1 | F28: ='Data Sheet'!E63/'Data Sheet'!E$63 -> 1 | G28: ='Data Sheet'!F63/'Data Sheet'!F$63 -> 1 | H28: ='Data Sheet'!G63/'Data Sheet'!G$63 -> 1 | I28: ='Data Sheet'!H63/'Data Sheet'!H$63 -> 1 | J28: ='Data Sheet'!I63/'Data Sheet'!I$63 -> 1 | ... L28: ='Data Sheet'!K63/'Data Sheet'!K$63 -> 1
B29: ='Data Sheet'!A58 -> Equity Share Capital | C29: ='Data Sheet'!B58/'Data Sheet'!B$63 -> 0.010559531 | D29: ='Data Sheet'!C58/'Data Sheet'!C$63 -> 0.0093246116 | E29: ='Data Sheet'!D58/'Data Sheet'!D$63 -> 0.0075816578 | F29: ='Data Sheet'!E58/'Data Sheet'!E$63 -> 0.0065711754 | G29: ='Data Sheet'!F58/'Data Sheet'!F$63 -> 0.0054123084 | H29: ='Data Sheet'!G58/'Data Sheet'!G$63 -> 0.0042004908 | I29: ='Data Sheet'!H58/'Data Sheet'!H$63 -> 0.0032938564 | J29: ='Data Sheet'!I58/'Data Sheet'!I$63 -> 0.0028211874 | ... L29: ='Data Sheet'!K58/'Data Sheet'!K$63 -> 0.0014695926
B30: ='Data Sheet'!A59 -> Reserves | C30: ='Data Sheet'!B59/'Data Sheet'!B$63 -> 0.49284157 | D30: ='Data Sheet'!C59/'Data Sheet'!C$63 -> 0.52526825 | E30: ='Data Sheet'!D59/'Data Sheet'!D$63 -> 0.51079861 | F30: ='Data Sheet'!E59/'Data Sheet'!E$63 -> 0.48582398 | G30: ='Data Sheet'!F59/'Data Sheet'!F$63 -> 0.45049866 | H30: ='Data Sheet'!G59/'Data Sheet'!G$63 -> 0.43486879 | I30: ='Data Sheet'!H59/'Data Sheet'!H$63 -> 0.43530718 | J30: ='Data Sheet'!I59/'Data Sheet'!I$63 -> 0.29492503 | ... L30: ='Data Sheet'!K59/'Data Sheet'!K$63 -> 0.25782269
B31: ='Data Sheet'!A60 -> Borrowings | C31: ='Data Sheet'!B60/'Data Sheet'!B$63 -> 0.22389704 | D31: ='Data Sheet'!C60/'Data Sheet'!C$63 -> 0.1776077 | E31: ='Data Sheet'!D60/'Data Sheet'!D$63 -> 0.20435634 | F31: ='Data Sheet'!E60/'Data Sheet'!E$63 -> 0.26299468 | G31: ='Data Sheet'!F60/'Data Sheet'!F$63 -> 0.34286062 | H31: ='Data Sheet'!G60/'Data Sheet'!G$63 -> 0.34335473 | I31: ='Data Sheet'!H60/'Data Sheet'!H$63 -> 0.34666913 | J31: ='Data Sheet'!I60/'Data Sheet'!I$63 -> 0.49221796 | ... L31: ='Data Sheet'!K60/'Data Sheet'!K$63 -> 0.50562243
B32: ='Data Sheet'!A61 -> Other Liabilities | C32: ='Data Sheet'!B61/'Data Sheet'!B$63 -> 0.27270186 | D32: ='Data Sheet'!C61/'Data Sheet'!C$63 -> 0.28779944 | E32: ='Data Sheet'!D61/'Data Sheet'!D$63 -> 0.2772634 | F32: ='Data Sheet'!E61/'Data Sheet'!E$63 -> 0.24461016 | G32: ='Data Sheet'!F61/'Data Sheet'!F$63 -> 0.20122841 | H32: ='Data Sheet'!G61/'Data Sheet'!G$63 -> 0.21757599 | I32: ='Data Sheet'!H61/'Data Sheet'!H$63 -> 0.21472983 | J32: ='Data Sheet'!I61/'Data Sheet'!I$63 -> 0.21003582 | ... L32: ='Data Sheet'!K61/'Data Sheet'!K$63 -> 0.23508529
B34: Total Assets | C34: =HistoricalFS!C71/HistoricalFS!C$71 -> 1 | D34: =HistoricalFS!D71/HistoricalFS!D$71 -> 1 | E34: =HistoricalFS!E71/HistoricalFS!E$71 -> 1 | F34: =HistoricalFS!F71/HistoricalFS!F$71 -> 1 | G34: =HistoricalFS!G71/HistoricalFS!G$71 -> 1 | H34: =HistoricalFS!H71/HistoricalFS!H$71 -> 1 | I34: =HistoricalFS!I71/HistoricalFS!I$71 -> 1 | J34: =HistoricalFS!J71/HistoricalFS!J$71 -> 1 | ... L34: =HistoricalFS!L71/HistoricalFS!L$71 -> 1
B35: ='Data Sheet'!A64 -> Net Block | C35: =HistoricalFS!C60/HistoricalFS!C$71 -> 0.14138687 | D35: =HistoricalFS!D60/HistoricalFS!D$71 -> 0.15479506 | E35: =HistoricalFS!E60/HistoricalFS!E$71 -> 0.13378748 | F35: =HistoricalFS!F60/HistoricalFS!F$71 -> 0.19440343 | G35: =HistoricalFS!G60/HistoricalFS!G$71 -> 0.15342982 | H35: =HistoricalFS!H60/HistoricalFS!H$71 -> 0.12006796 | I35: =HistoricalFS!I60/HistoricalFS!I$71 -> 0.11095485 | J35: =HistoricalFS!J60/HistoricalFS!J$71 -> 0.11757061 | ... L35: =HistoricalFS!L60/HistoricalFS!L$71 -> 0.11357144
B36: ='Data Sheet'!A65 -> Capital Work in Progress | C36: =HistoricalFS!C61/HistoricalFS!C$71 -> 0.018087271 | D36: =HistoricalFS!D61/HistoricalFS!D$71 -> 0.0045551746 | E36: =HistoricalFS!E61/HistoricalFS!E$71 -> 0.0027131028 | F36: =HistoricalFS!F61/HistoricalFS!F$71 -> 0.0013290018 | G36: =HistoricalFS!G61/HistoricalFS!G$71 -> 0.0019459985 | H36: =HistoricalFS!H61/HistoricalFS!H$71 -> 0.0040117047 | I36: =HistoricalFS!I61/HistoricalFS!I$71 -> 0.0053293856 | J36: =HistoricalFS!J61/HistoricalFS!J$71 -> 0.0030747773 | ... L36: =HistoricalFS!L61/HistoricalFS!L$71 -> 0.0026915011
B37: ='Data Sheet'!A66 -> Investments | C37: =HistoricalFS!C62/HistoricalFS!C$71 -> 0.051231212 | D37: =HistoricalFS!D62/HistoricalFS!D$71 -> 0.0037800492 | E37: =HistoricalFS!E62/HistoricalFS!E$71 -> 0.0092588797 | F37: =HistoricalFS!F62/HistoricalFS!F$71 -> 0.011665682 | G37: =HistoricalFS!G62/HistoricalFS!G$71 -> 0.17173437 | H37: =HistoricalFS!H62/HistoricalFS!H$71 -> 0.013875779 | I37: =HistoricalFS!I62/HistoricalFS!I$71 -> 0.093079201 | J37: =HistoricalFS!J62/HistoricalFS!J$71 -> 0.074333534 | ... L37: =HistoricalFS!L62/HistoricalFS!L$71 -> 0.057892043
B38: ='Data Sheet'!A67 -> Other Assets | C38: =HistoricalFS!C63/HistoricalFS!C$71 -> 0.086086705 | D38: =HistoricalFS!D63/HistoricalFS!D$71 -> 0.11862465 | E38: =HistoricalFS!E63/HistoricalFS!E$71 -> 0.12615629 | F38: =HistoricalFS!F63/HistoricalFS!F$71 -> 0.14316302 | G38: =HistoricalFS!G63/HistoricalFS!G$71 -> 0.10526636 | H38: =HistoricalFS!H63/HistoricalFS!H$71 -> 0.11884085 | I38: =HistoricalFS!I63/HistoricalFS!I$71 -> 0.10222058 | J38: =HistoricalFS!J63/HistoricalFS!J$71 -> 0.12048689 | ... L38: =HistoricalFS!L63/HistoricalFS!L$71 -> 0.073281485
B39: ='Data Sheet'!A69 -> Receivables | C39: =HistoricalFS!C66/HistoricalFS!C$71 -> 0.024692033 | D39: =HistoricalFS!D66/HistoricalFS!D$71 -> 0.031056481 | E39: =HistoricalFS!E66/HistoricalFS!E$71 -> 0.0359057 | F39: =HistoricalFS!F66/HistoricalFS!F$71 -> 0.023036031 | G39: =HistoricalFS!G66/HistoricalFS!G$71 -> 0.022257358 | H39: =HistoricalFS!H66/HistoricalFS!H$71 -> 0.026666037 | I39: =HistoricalFS!I66/HistoricalFS!I$71 -> 0.024944486 | J39: =HistoricalFS!J66/HistoricalFS!J$71 -> 0.032269312 | ... L39: =HistoricalFS!L66/HistoricalFS!L$71 -> 0.015125246
B40: ='Data Sheet'!A70 -> Inventory | C40: =HistoricalFS!C67/HistoricalFS!C$71 -> 0.58586964 | D40: =HistoricalFS!D67/HistoricalFS!D$71 -> 0.62228916 | E40: =HistoricalFS!E67/HistoricalFS!E$71 -> 0.601103 | F40: =HistoricalFS!F67/HistoricalFS!F$71 -> 0.5982723 | G40: =HistoricalFS!G67/HistoricalFS!G$71 -> 0.51131112 | H40: =HistoricalFS!H67/HistoricalFS!H$71 -> 0.64229753 | I40: =HistoricalFS!I67/HistoricalFS!I$71 -> 0.61376758 | J40: =HistoricalFS!J67/HistoricalFS!J$71 -> 0.6038926 | ... L40: =HistoricalFS!L67/HistoricalFS!L$71 -> 0.70578425
B41: ='Data Sheet'!A71 -> Cash & Bank | C41: =HistoricalFS!C68/HistoricalFS!C$71 -> 0.09264627 | D41: =HistoricalFS!D68/HistoricalFS!D$71 -> 0.064899423 | E41: =HistoricalFS!E68/HistoricalFS!E$71 -> 0.09107554 | F41: =HistoricalFS!F68/HistoricalFS!F$71 -> 0.028130538 | G41: =HistoricalFS!G68/HistoricalFS!G$71 -> 0.034054974 | H41: =HistoricalFS!H68/HistoricalFS!H$71 -> 0.074240136 | I41: =HistoricalFS!I68/HistoricalFS!I$71 -> 0.049703923 | J41: =HistoricalFS!J68/HistoricalFS!J$71 -> 0.04837227 | ... L41: =HistoricalFS!L68/HistoricalFS!L$71 -> 0.031654035

Sheet Dupont Analysis
B2: ='Data Sheet'!B2&" - Dupont Analysis" -> TITAN COMPANY LTD - Dupont Analysis
D4: =HistoricalFS!H3 -> 44651 | E4: =HistoricalFS!I3 -> 45016 | F4: =HistoricalFS!J3 -> 45382 | G4: =HistoricalFS!K3 -> 45747 | H4: =HistoricalFS!L3 -> 46112
B6: Financial Summary
A26: # | B26: Return on Equity (ROE)
B27: Net Profit | D27: =HistoricalFS!H39 -> 2198 | E27: =HistoricalFS!I39 -> 3274 | F27: =HistoricalFS!J39 -> 3496 | G27: =HistoricalFS!K39 -> 3337 | H27: =HistoricalFS!L39 -> 5073
B28: Average Shareholder Equity | D28: =(SUM(HistoricalFS!H54:H55)+SUM(HistoricalFS!G54:G55))/2 -> 8400 | E28: =(SUM(HistoricalFS!I54:I55)+SUM(HistoricalFS!H54:H55))/2 -> 10577 | F28: =(SUM(HistoricalFS!J54:J55)+SUM(HistoricalFS!I54:I55))/2 -> 10622 | G28: =(SUM(HistoricalFS!K54:K55)+SUM(HistoricalFS!J54:J55))/2 -> 10508.5 | H28: =(SUM(HistoricalFS!L54:L55)+SUM(HistoricalFS!K54:K55))/2 -> 13663.5
B29: Return on Equity (ROE) | D29: =D27/D28 -> 0.26166667 | E29: =E27/E28 -> 0.30953957 | F29: =F27/F28 -> 0.32912822 | G29: =G27/G28 -> 0.31755246 | H29: =H27/H28 -> 0.37128115
A31: # | B31: Return on Equity (ROE) - Dupont Equation
B32: =B27 -> Net Profit | D32: =D27 -> 2198 | E32: =E27 -> 3274 | F32: =F27 -> 3496 | G32: =G27 -> 3337 | H32: =H27 -> 5073
B33: Revenue | D33: =HistoricalFS!H6 -> 28799 | E33: =HistoricalFS!I6 -> 40575 | F33: =HistoricalFS!J6 -> 51084 | G33: =HistoricalFS!K6 -> 60456 | H33: =HistoricalFS!L6 -> 87584
B34: Net Profit Margin (A) | D34: =D32/D33 -> 0.076322095 | E34: =E32/E33 -> 0.08069008 | F34: =F32/F33 -> 0.068436301 | G34: =G32/G33 -> 0.055197168 | H34: =H32/H33 -> 0.057921538
B36: Revenue | D36: =D33 -> 28799 | E36: =E33 -> 40575 | F36: =F33 -> 51084 | G36: =G33 -> 60456 | H36: =H33 -> 87584
B37: Average Total Assets | D37: =(HistoricalFS!H71+HistoricalFS!G71)/2 -> 18816 | E37: =(HistoricalFS!I71+HistoricalFS!H71)/2 -> 24104 | F37: =(HistoricalFS!J71+HistoricalFS!I71)/2 -> 29283.5 | G37: =(HistoricalFS!K71+HistoricalFS!J71)/2 -> 36096 | H37: =(HistoricalFS!L71+HistoricalFS!K71)/2 -> 50603
B38: Asset Turnover Ratio (B) | D38: =D36/D37 -> 1.5305591 | E38: =E36/E37 -> 1.6833306 | F38: =F36/F37 -> 1.7444636 | G38: =G36/G37 -> 1.674867 | H38: =H36/H37 -> 1.7308065
B40: =B37 -> Average Total Assets | D40: =D37 -> 18816 | E40: =E37 -> 24104 | F40: =F37 -> 29283.5 | G40: =G37 -> 36096 | H40: =H37 -> 50603
B41: =B28 -> Average Shareholder Equity | D41: =D28 -> 8400 | E41: =E28 -> 10577 | F41: =F28 -> 10622 | G41: =G28 -> 10508.5 | H41: =H28 -> 13663.5
B42: Financial Leverage Ratio (C) | D42: =D40/D41 -> 2.24 | E42: =E40/E41 -> 2.2789071 | F42: =F40/F41 -> 2.7568725 | G42: =G40/G41 -> 3.4349336 | H42: =H40/H41 -> 3.7035167
B44: Return on Equity (A*B*C) | D44: =D34*D38*D42 -> 0.26166667 | E44: =E34*E38*E42 -> 0.30953957 | F44: =F34*F38*F42 -> 0.32912822 | G44: =G34*G38*G42 -> 0.31755246 | H44: =H34*H38*H42 -> 0.37128115
A46: # | B46: Return on Assets (ROA)
B48: =B32 -> Net Profit | D48: =D32 -> 2198 | E48: =E32 -> 3274 | F48: =F32 -> 3496 | G48: =G32 -> 3337 | H48: =H32 -> 5073
B49: =B37 -> Average Total Assets | D49: =D37 -> 18816 | E49: =E37 -> 24104 | F49: =F37 -> 29283.5 | G49: =G37 -> 36096 | H49: =H37 -> 50603
B50: Return on Assets | D50: =D48/D49 -> 0.11681548 | E50: =E48/E49 -> 0.13582808 | F50: =F48/F49 -> 0.11938464 | G50: =G48/G49 -> 0.092447917 | H50: =H48/H49 -> 0.10025097
A52: # | B52: Return on Assets (ROA) - Dupont Equation
B53: =B32 -> Net Profit | D53: =D32 -> 2198 | E53: =E32 -> 3274 | F53: =F32 -> 3496 | G53: =G32 -> 3337 | H53: =H32 -> 5073
B54: =B33 -> Revenue | D54: =D33 -> 28799 | E54: =E33 -> 40575 | F54: =F33 -> 51084 | G54: =G33 -> 60456 | H54: =H33 -> 87584
B55: =B34 -> Net Profit Margin (A) | D55: =D34 -> 0.076322095 | E55: =E34 -> 0.08069008 | F55: =F34 -> 0.068436301 | G55: =G34 -> 0.055197168 | H55: =H34 -> 0.057921538
B57: =B36 -> Revenue | D57: =D36 -> 28799 | E57: =E36 -> 40575 | F57: =F36 -> 51084 | G57: =G36 -> 60456 | H57: =H36 -> 87584
B58: =B37 -> Average Total Assets | D58: =D37 -> 18816 | E58: =E37 -> 24104 | F58: =F37 -> 29283.5 | G58: =G37 -> 36096 | H58: =H37 -> 50603
B59: =B38 -> Asset Turnover Ratio (B) | D59: =D38 -> 1.5305591 | E59: =E38 -> 1.6833306 | F59: =F38 -> 1.7444636 | G59: =G38 -> 1.674867 | H59: =H38 -> 1.7308065
B61: Return on Assets (A*B) | D61: =D55*D59 -> 0.11681548 | E61: =E55*E59 -> 0.13582808 | F61: =F55*F59 -> 0.11938464 | G61: =G55*G59 -> 0.092447917 | H61: =H55*H59 -> 0.10025097

Sheet Segment Analysis
B2: SEGMENT ANALYSIS
C3: =HistoricalFS!H3 -> 44651 | D3: =HistoricalFS!I3 -> 45016 | E3: =HistoricalFS!J3 -> 45382 | F3: =HistoricalFS!K3 -> 45747 | G3: =HistoricalFS!L3 -> 46112
B37: Revenue | H37: CAGR
B38: ='Segment Data'!B5 -> Watches | C38: ='Segment Data'!C5 -> 2309 | D38: ='Segment Data'!D5 -> 3296 | E38: ='Segment Data'!E5 -> 3904 | F38: ='Segment Data'!F5 -> 4576 | G38: ='Segment Data'!G5 -> 5233 | H38: =(G38/C38)^(1/4)-1 -> 0.22696366
B39: ='Segment Data'!B6 -> Jewellery | C39: ='Segment Data'!C6 -> 24313 | D39: ='Segment Data'!D6 -> 34105 | E39: ='Segment Data'!E6 -> 42292 | F39: ='Segment Data'!F6 -> 49227 | G39: ='Segment Data'!G6 -> 71108 | H39: =(G39/C39)^(1/4)-1 -> 0.3077357
B40: ='Segment Data'!B7 -> EyeCare | C40: ='Segment Data'!C7 -> 517 | D40: ='Segment Data'!D7 -> 689 | E40: ='Segment Data'!E7 -> 724 | F40: ='Segment Data'!F7 -> 796 | G40: ='Segment Data'!G7 -> 907 | H40: =(G40/C40)^(1/4)-1 -> 0.15087773
B41: ='Segment Data'!B8 -> Others | C41: ='Segment Data'!C8 -> 154 | D41: ='Segment Data'!D8 -> 295 | E41: ='Segment Data'!E8 -> 378 | F41: ='Segment Data'!F8 -> 406 | G41: ='Segment Data'!G8 -> 508 | H41: =(G41/C41)^(1/4)-1 -> 0.34767679
B42: ='Segment Data'!B9 -> Corporate (Unallocated) | C42: ='Segment Data'!C9 -> 163 | D42: ='Segment Data'!D9 -> 184 | E42: ='Segment Data'!E9 -> 326 | F42: ='Segment Data'!F9 -> 330 | G42: ='Segment Data'!G9 -> 333 | H42: =(G42/C42)^(1/4)-1 -> 0.19554013
B43: ='Segment Data'!B10 -> Segment Total | C43: ='Segment Data'!C10 -> 27456 | D43: ='Segment Data'!D10 -> 38569 | E43: ='Segment Data'!E10 -> 47624 | F43: ='Segment Data'!F10 -> 55335 | G43: ='Segment Data'!G10 -> 78089 | H43: =(G43/C43)^(1/4)-1 -> 0.29863813
B44: ='Segment Data'!B11 -> Caratlane & other subs | C44: ='Segment Data'!C11 -> 1343 | D44: ='Segment Data'!D11 -> 2006 | E44: ='Segment Data'!E11 -> 3460 | F44: ='Segment Data'!F11 -> 5121 | G44: ='Segment Data'!G11 -> 9495 | H44: =(G44/C44)^(1/4)-1 -> 0.63062741
B45: ='Segment Data'!B12 -> Consolidated Total | C45: ='Segment Data'!C12 -> 28799 | D45: ='Segment Data'!D12 -> 40575 | E45: ='Segment Data'!E12 -> 51084 | F45: ='Segment Data'!F12 -> 60456 | G45: ='Segment Data'!G12 -> 87584 | H45: =(G45/C45)^(1/4)-1 -> 0.32057126
B47: Jewellery revenue as % of total | C47: =C39/C43 -> 0.88552593 | D47: =D39/D43 -> 0.88425938 | E47: =E39/E43 -> 0.88803964 | F47: =F39/F43 -> 0.88961778 | G47: =G39/G43 -> 0.91060201
B48: Watches revenue as % of total | C48: =C38/C43 -> 0.084098193 | D48: =D38/D43 -> 0.085457232 | E48: =E38/E43 -> 0.081975475 | F48: =F38/F43 -> 0.082696304 | G48: =G38/G43 -> 0.06701328
B50: EBIT
B51: ='Segment Data'!B15 -> Watches | C51: ='Segment Data'!C15 -> 108 | D51: ='Segment Data'!D15 -> 413 | E51: ='Segment Data'!E15 -> 397 | F51: ='Segment Data'!F15 -> 553 | G51: ='Segment Data'!G15 -> 842
B52: ='Segment Data'!B16 -> Jewellery | C52: ='Segment Data'!C16 -> 3027 | D52: ='Segment Data'!D16 -> 4363 | E52: ='Segment Data'!E16 -> 4726 | F52: ='Segment Data'!F16 -> 4764 | G52: ='Segment Data'!G16 -> 6601
B53: ='Segment Data'!B17 -> EyeCare | C53: ='Segment Data'!C17 -> 50 | D53: ='Segment Data'!D17 -> 98 | E53: ='Segment Data'!E17 -> 85 | F53: ='Segment Data'!F17 -> 85 | G53: ='Segment Data'!G17 -> 84
B54: ='Segment Data'!B18 -> Others | C54: ='Segment Data'!C18 -> -36 | D54: ='Segment Data'!D18 -> -78 | E54: ='Segment Data'!E18 -> -93 | F54: ='Segment Data'!F18 -> -124 | G54: ='Segment Data'!G18 -> -114
B55: ='Segment Data'!B19 -> Total | C55: ='Segment Data'!C19 -> 3149 | D55: ='Segment Data'!D19 -> 4796 | E55: ='Segment Data'!E19 -> 5115 | F55: ='Segment Data'!F19 -> 5278 | G55: ='Segment Data'!G19 -> 7413
B56: ='Segment Data'!B20 -> Caratlane & other subs | C56: ='Segment Data'!C20 -> -182 | D56: ='Segment Data'!D20 -> -264 | E56: ='Segment Data'!E20 -> -379 | F56: ='Segment Data'!F20 -> -247 | G56: ='Segment Data'!G20 -> 289
B57: ='Segment Data'!B21 -> Corporate (unallocated) | C57: ='Segment Data'!C21 -> -22 | D57: ='Segment Data'!D21 -> -91 | E57: ='Segment Data'!E21 -> -28 | F57: ='Segment Data'!F21 -> -30 | G57: ='Segment Data'!G21 -> -171
B58: ='Segment Data'!B22 -> Consolidated EBIT | C58: ='Segment Data'!C22 -> 2945 | D58: ='Segment Data'!D22 -> 4441 | E58: ='Segment Data'!E22 -> 4708 | F58: ='Segment Data'!F22 -> 5001 | G58: ='Segment Data'!G22 -> 7531
B60: Net Assets
B61: ='Segment Data'!B25 -> Watches | C61: ='Segment Data'!C25 -> 1351 | D61: ='Segment Data'!D25 -> 1764 | E61: ='Segment Data'!E25 -> 2605 | F61: ='Segment Data'!F25 -> 2865 | G61: ='Segment Data'!G25 -> 3132
B62: ='Segment Data'!B26 -> Jewellery | C62: ='Segment Data'!C26 -> 4998 | D62: ='Segment Data'!D26 -> 6376 | E62: ='Segment Data'!E26 -> 7632 | F62: ='Segment Data'!F26 -> 11488 | G62: ='Segment Data'!G26 -> 11653
B63: ='Segment Data'!B27 -> EyeCare | C63: ='Segment Data'!C27 -> 194 | D63: ='Segment Data'!D27 -> 256 | E63: ='Segment Data'!E27 -> 261 | F63: ='Segment Data'!F27 -> 256 | G63: ='Segment Data'!G27 -> 265
B64: ='Segment Data'!B28 -> Others | C64: ='Segment Data'!C28 -> 117 | D64: ='Segment Data'!D28 -> 168 | E64: ='Segment Data'!E28 -> 245 | F64: ='Segment Data'!F28 -> 262 | G64: ='Segment Data'!G28 -> 270
B65: ='Segment Data'!B29 -> Corporate (unallocated) | C65: ='Segment Data'!C29 -> 2713 | D65: ='Segment Data'!D29 -> 3430 | E65: ='Segment Data'!E29 -> 3714 | F65: ='Segment Data'!F29 -> 1940 | G65: ='Segment Data'!G29 -> 5167
B66: ='Segment Data'!B30 -> Total | C66: ='Segment Data'!C30 -> 9373 | D66: ='Segment Data'!D30 -> 11994 | E66: ='Segment Data'!E30 -> 14457 | F66: ='Segment Data'!F30 -> 16811 | G66: ='Segment Data'!G30 -> 20487
B68: EBIT Margins
B69: =B38 -> Watches | C69: =C51/C38 -> 0.046773495 | D69: =D51/D38 -> 0.1253034 | E69: =E51/E38 -> 0.10169057 | F69: =F51/F38 -> 0.1208479 | G69: =G51/G38 -> 0.16090197
B70: =B39 -> Jewellery | C70: =C52/C39 -> 0.1245013 | D70: =D52/D39 -> 0.12792846 | E70: =E52/E39 -> 0.1117469 | F70: =F52/F39 -> 0.096776159 | G70: =G52/G39 -> 0.092830624
B71: =B40 -> EyeCare | C71: =C53/C40 -> 0.096711799 | D71: =D53/D40 -> 0.14223512 | E71: =E53/E40 -> 0.11740331 | F71: =F53/F40 -> 0.10678392 | G71: =G53/G40 -> 0.09261301
B72: =B41 -> Others | C72: =C54/C41 -> -0.23376623 | D72: =D54/D41 -> -0.26440678 | E72: =E54/E41 -> -0.24603175 | F72: =F54/F41 -> -0.30541872 | G72: =G54/G41 -> -0.22440945
B73: =B44 -> Caratlane & other subs | C73: =C56/C44 -> -0.1355175 | D73: =D56/D44 -> -0.13160518 | E73: =E56/E44 -> -0.10953757 | F73: =F56/F44 -> -0.048232767 | G73: =G56/G44 -> 0.030437072
B75: Return on Capital Employed
B76: =B61 -> Watches | C76: =C51/C61 -> 0.079940785 | D76: =D51/D61 -> 0.23412698 | E76: =E51/E61 -> 0.15239923 | F76: =F51/F61 -> 0.1930192 | G76: =G51/G61 -> 0.2688378
B77: =B62 -> Jewellery | C77: =C52/C62 -> 0.60564226 | D77: =D52/D62 -> 0.68428482 | E77: =E52/E62 -> 0.6192348 | F77: =F52/F62 -> 0.41469359 | G77: =G52/G62 -> 0.56646357
B78: =B63 -> EyeCare | C78: =C53/C63 -> 0.25773196 | D78: =D53/D63 -> 0.3828125 | E78: =E53/E63 -> 0.3256705 | F78: =F53/F63 -> 0.33203125 | G78: =G53/G63 -> 0.31698113
B79: =B64 -> Others | C79: =C54/C64 -> -0.30769231 | D79: =D54/D64 -> -0.46428571 | E79: =E54/E64 -> -0.37959184 | F79: =F54/F64 -> -0.47328244 | G79: =G54/G64 -> -0.42222222
B80: =B56 -> Caratlane & other subs | C80: =C56/(C44/4) -> -0.54206999 | D80: =D56/(D44/4) -> -0.52642074 | E80: =E56/(E44/4) -> -0.43815029 | F80: =F56/(F44/4) -> -0.19293107 | G80: =G56/(G44/4) -> 0.12174829
B82: Jewellery Business Growth: Value vs Volume | H82: CAGR
B83: Revenue - Jewellery | C83: =C39 -> 24313 | D83: =D39 -> 34105 | E83: =E39 -> 42292 | F83: =F39 -> 49227 | G83: =G39 -> 71108 | H83: =(G83/C83)^(1/4)-1 -> 0.3077357
B84: Revenue Growth | D84: =(D83/C83)-1 -> 0.4027475 | E84: =(E83/D83)-1 -> 0.24005278 | F84: =(F83/E83)-1 -> 0.163979 | G84: =(G83/F83)-1 -> 0.44449184
B85: ='Segment Data'!B33 -> Gold Sold (Tonnes) | C85: ='Segment Data'!C33 -> 36.8 | D85: ='Segment Data'!D33 -> 44.4 | E85: ='Segment Data'!E33 -> 47.1 | F85: ='Segment Data'!F33 -> 44.4 | G85: ='Segment Data'!G33 -> 48.9 | H85: =(G85/C85)^(1/4)-1 -> 0.073656259
B86: Volume Growth | D86: =D85/C85-1 -> 0.20652174 | E86: =E85/D85-1 -> 0.060810811 | F86: =F85/E85-1 -> -0.057324841 | G86: =G85/F85-1 -> 0.10135135
B87: ='Segment Data'!B34 -> Average Price per gm | C87: ='Segment Data'!C34 -> 4534 | D87: ='Segment Data'!D34 -> 5142 | E87: ='Segment Data'!E34 -> 5785 | F87: ='Segment Data'!F34 -> 6680 | G87: ='Segment Data'!G34 -> 7450 | H87: =(G87/C87)^(1/4)-1 -> 0.13218837
B88: Gold Price Growth | D88: =D87/C87-1 -> 0.13409793 | E88: =E87/D87-1 -> 0.12504862 | F88: =F87/E87-1 -> 0.15471046 | G88: =G87/F87-1 -> 0.11526946

Sheet Valuation>

Sheet WACC
B3: WEIGHTED AVERAGE COST OF CAPITAL
B5: All figures are in INR unless stated otherwise
B7: Peer comparision
G8: Debt / | H8: Debt / | I8: Levered | J8: Unlevered
B9: Name | C9: Country | D9: Total Debt | E9: Total Equity | F9: Tax Rate1 | G9: Equity | H9: Capital | I9: Beta2 | J9: Beta3
B11: Titan Company | C11: India | D11: ='Beta - comps'!F4 -> 30621 | E11: ='Beta - comps'!E4 -> 448931.97 | F11: 0.2517 | G11: =D11/E11 -> 0.068208553 | H11: =D11/(D11+E11) -> 0.063853217 | I11: ='Beta - regression'!J7 -> 0.97667835 | J11: =I11/(1+(1-F11)*G11) -> 0.92924905
B12: Kalyan Jewellers | C12: India | D12: ='Beta - comps'!F5 -> 6117.33 | E12: ='Beta - comps'!E5 -> 63311.81 | F12: 0.2517 | G12: =D12/E12 -> 0.096622257 | H12: =D12/(D12+E12) -> 0.08810897 | I12: ='Beta - regression'!AD7 -> 1.5734218 | J12: =I12/(1+(1-F12)*G12) -> 1.4673303
B13: Thangamayil Jew. | C13: India | D13: ='Beta - comps'!F6 -> 913.21 | E13: ='Beta - comps'!E6 -> 16398.54 | F13: 0.2517 | G13: =D13/E13 -> 0.055688494 | H13: =D13/(D13+E13) -> 0.052750877 | I13: ='Beta - regression'!AN7 -> 0.56835062 | J13: =I13/(1+(1-F13)*G13) -> 0.54561396
B14: Bluestone Jewel | C14: India | D14: ='Beta - comps'!F7 -> 1699.09 | E14: ='Beta - comps'!E7 -> 13388.55 | F14: 0.2517 | G14: =D14/E14 -> 0.1269062 | H14: =D14/(D14+E14) -> 0.1126147 | I14: ='Beta - regression'!BH7 -> 0.27185751 | J14: =I14/(1+(1-F14)*G14) -> 0.24827988
B15: Sky Gold & Diam. | C15: India | D15: ='Beta - comps'!F8 -> 869.11 | E15: ='Beta - comps'!E8 -> 11993.66 | F15: 0.2517 | G15: =D15/E15 -> 0.072464119 | H15: =D15/(D15+E15) -> 0.067567872 | I15: ='Beta - regression'!AX7 -> 1.2305792 | J15: =I15/(1+(1-F15)*G15) -> 1.1672834
E17: Peer Average | F17: =AVERAGE(F12:F15) -> 0.2517 | G17: =AVERAGE(G12:G15) -> 0.087920267 | H17: =AVERAGE(H12:H15) -> 0.080260604 | I17: =AVERAGE(I12:I15) -> 0.91105229 | J17: =AVERAGE(J12:J15) -> 0.85712687
E18: Peer Median | F18: =MEDIAN(F12:F15) -> 0.2517 | G18: =MEDIAN(G12:G15) -> 0.084543188 | H18: =MEDIAN(H12:H15) -> 0.077838421 | I18: =MEDIAN(I12:I15) -> 0.89946491 | J18: =MEDIAN(J12:J15) -> 0.85644867
B21: Cost of Debt | G21: Cost of Equity
B23: Pre-Tax Cost of Debt | E23: 0.072 | G23: Risk Free Rate | J23: 0.06758
B24: Tax Rate | E24: =F11 -> 0.2517 | G24: Equity Risk Premium | J24: ='Market Return'!F7-WACC!J23 -> 0.074682827
B25: Post Tax Cost of Debt | E25: =E23*(1-E24) -> 0.0538776 | G25: Levered Beta4 | J25: =J34 -> 0.91054454
G26: Cost of Equity | J26: =J23+(J24*J25) -> 0.13558204
B29: Capital Structure | G29: Levered Beta
D31: Current | E31: Target | G31: Peer Median Unlevered Beta | J31: =J18 -> 0.85644867
B32: Total Debt | C32: =D11 -> 30621 | D32: =C32/$C$34 -> 0.063853217 | E32: =H18 -> 0.077838421 | G32: Target Debt / Equity | J32: =E36 -> 0.084408658
B33: Market Capitalization | C33: =E11 -> 448931.97 | D33: =C33/$C$34 -> 0.93614678 | E33: =E34-E32 -> 0.92216158 | G33: Tax Rate | J33: =E24 -> 0.2517
B34: Total Capital | C34: =SUM(C32:C33) -> 479552.97 | D34: =SUM(D32:D33) -> 1 | E34: =D34 -> 1 | G34: Levered Beta | J34: =J31*(1+(1-J33)*J32) -> 0.91054454
B36: Debt / Equity | D36: =D32/D33 -> 0.068208553 | E36: =E32/E33 -> 0.084408658
G37: Weighted Average Cost of Capital
I39: Total Cost | J39: Total Weight
G40: Debt | I40: =E25 -> 0.0538776 | J40: =E32 -> 0.077838421
G41: Equity | I41: =J26 -> 0.13558204 | J41: =E33 -> 0.92216158
G42: Weighted Average Cost of Capital | J42: =SUMPRODUCT(I40:I41,J40:J41) -> 0.1292223
B44: Notes:
B45: 1. Tax Rate considered as Marginal Tax Rate for the country
B46: 2. Levered Beta is based on 5 year monthly data
B47: 3. Unlevered Beta = Levered Beta/(1+(1-Tax Rate) x Debt/Equity)
B48: 4. Levered Beta = Unlevered Beta*(1+(1-Tax Rate) x Debt/Equity)
B49: 5. Historical beta calculated using 2 years of weekly price data where available; Bluestone uses 1 year due to IPO in 2025
B50: 6. Pre-tax cost of debt is set at 7.20% based on Titan's implied interest statement yields and current credit facility borrowing rates.

Sheet Intrinsic Growth
B2: Calculation of ROIC | G2: ='Data Sheet'!G$57 -> 44651 | H2: ='Data Sheet'!H$57 -> 45016 | I2: ='Data Sheet'!I$57 -> 45382 | J2: ='Data Sheet'!J$57 -> 45747 | K2: ='Data Sheet'!K$57 -> 46112
B4: Current Assets
B5: ='Raw FS'!B36 -> Inventories | G5: ='Raw FS'!J36 -> 13609 | H5: ='Raw FS'!K36 -> 16584 | I5: ='Raw FS'!L36 -> 19051 | J5: ='Raw FS'!M36 -> 28184 | K5: ='Raw FS'!N36 -> 42743
B6: ='Raw FS'!B37 -> Trade receivables | G6: ='Raw FS'!J37 -> 565 | H6: ='Raw FS'!K37 -> 674 | I6: ='Raw FS'!L37 -> 1018 | J6: ='Raw FS'!M37 -> 1068 | K6: ='Raw FS'!N37 -> 916
B7: ='Raw FS'!B39 -> Loans n Advances | G7: ='Raw FS'!J39 -> 29 | H7: ='Raw FS'!K39 -> 167 | I7: ='Raw FS'!L39 -> 151 | J7: ='Raw FS'!M39 -> 324 | K7: ='Raw FS'!N39 -> 399
B8: ='Raw FS'!B40 -> Other asset items | G8: ='Raw FS'!J40 -> 2489 | H8: ='Raw FS'!K40 -> 2595 | I8: ='Raw FS'!L40 -> 3650 | J8: ='Raw FS'!M40 -> 3330 | K8: ='Raw FS'!N40 -> 4039
B9: Total Current Assets | G9: =SUM(G5:G8) -> 16692 | H9: =SUM(H5:H8) -> 20020 | I9: =SUM(I5:I8) -> 23870 | J9: =SUM(J5:J8) -> 32906 | K9: =SUM(K5:K8) -> 48097
B11: Current Liabilities
B12: ='Raw FS'!B13 -> Trade Payables | G12: ='Raw FS'!J13 -> 1294 | H12: ='Raw FS'!K13 -> 1214 | I12: ='Raw FS'!L13 -> 1410 | J12: ='Raw FS'!M13 -> 1963 | K12: ='Raw FS'!N13 -> 2864
B13: ='Raw FS'!B14 -> Advance from Customers | G13: ='Raw FS'!J14 -> 532 | H13: ='Raw FS'!K14 -> 718 | I13: ='Raw FS'!L14 -> 1085 | J13: ='Raw FS'!M14 -> 2140 | K13: ='Raw FS'!N14 -> 4745
B14: ='Raw FS'!B15 -> Other liability items | G14: ='Raw FS'!J15 -> 2754 | H14: ='Raw FS'!K15 -> 3817 | I14: ='Raw FS'!L15 -> 4131 | J14: ='Raw FS'!M15 -> 4141 | K14: ='Raw FS'!N15 -> 6628
B15: Total Current Liabilties | G15: =SUM(G12:G14) -> 4580 | H15: =SUM(H12:H14) -> 5749 | I15: =SUM(I12:I14) -> 6626 | J15: =SUM(J12:J14) -> 8244 | K15: =SUM(K12:K14) -> 14237
A17: # | B17: Net Working Capital | G17: =G9-G15 -> 12112 | H17: =H9-H15 -> 14271 | I17: =I9-I15 -> 17244 | J17: =J9-J15 -> 24662 | K17: =K9-K15 -> 33860
B19: Non Current Assets
B20: ='Raw FS'!B19 -> Land | G20: ='Raw FS'!J19 -> 136 | H20: ='Raw FS'!K19 -> 144 | I20: ='Raw FS'!L19 -> 163 | J20: ='Raw FS'!M19 -> 163 | K20: ='Raw FS'!N19 -> 440
B21: ='Raw FS'!B20 -> Building | G21: ='Raw FS'!J20 -> 1853 | H21: ='Raw FS'!K20 -> 2403 | I21: ='Raw FS'!L20 -> 3546 | J21: ='Raw FS'!M20 -> 4177 | K21: ='Raw FS'!N20 -> 5239
B22: ='Raw FS'!B21 -> Plant Machinery | G22: ='Raw FS'!J21 -> 768 | H22: ='Raw FS'!K21 -> 838 | I22: ='Raw FS'!L21 -> 899 | J22: ='Raw FS'!M21 -> 1012 | K22: ='Raw FS'!N21 -> 1197
B23: ='Raw FS'!B22 -> Equipments | G23: ='Raw FS'!J22 -> 96 | H23: ='Raw FS'!K22 -> 130 | I23: ='Raw FS'!L22 -> 110 | J23: ='Raw FS'!M22 -> 127 | K23: ='Raw FS'!N22 -> 176
B24: ='Raw FS'!B23 -> Computers | G24: ='Raw FS'!J23 -> 159 | H24: ='Raw FS'!K23 -> 204 | I24: ='Raw FS'!L23 -> 212 | J24: ='Raw FS'!M23 -> 228 | K24: ='Raw FS'!N23 -> 264
B25: ='Raw FS'!B24 -> Furniture n fittings | G25: ='Raw FS'!J24 -> 321 | H25: ='Raw FS'!K24 -> 376 | I25: ='Raw FS'!L24 -> 173 | J25: ='Raw FS'!M24 -> 193 | K25: ='Raw FS'!N24 -> 379
B26: ='Raw FS'!B25 -> Vehicles | G26: ='Raw FS'!J25 -> 38 | H26: ='Raw FS'!K25 -> 40 | I26: ='Raw FS'!L25 -> 50 | J26: ='Raw FS'!M25 -> 57 | K26: ='Raw FS'!N25 -> 68
B27: ='Raw FS'!B26 -> Intangible Assets | G27: ='Raw FS'!J26 -> 320 | H27: ='Raw FS'!K26 -> 320 | I27: ='Raw FS'!L26 -> 320 | J27: ='Raw FS'!M26 -> 320 | K27: ='Raw FS'!N26 -> 1782
B28: ='Raw FS'!B27 -> Other fixed assets | G28: ='Raw FS'!J27 -> 157 | H28: ='Raw FS'!K27 -> 205 | I28: ='Raw FS'!L27 -> 305 | J28: ='Raw FS'!M27 -> 369 | K28: ='Raw FS'!N27 -> 540
B29: Gross Block | G29: =SUM(G20:G28) -> 3848 | H29: =SUM(H20:H28) -> 4660 | I29: =SUM(I20:I28) -> 5778 | J29: =SUM(J20:J28) -> 6646 | K29: =SUM(K20:K28) -> 10085
B30: ='Raw FS'!B29 -> Accumulated Depreciation | G30: =-'Raw FS'!J29 -> -1304 | H30: =-'Raw FS'!K29 -> -1662 | I30: =-'Raw FS'!L29 -> -2069 | J30: =-'Raw FS'!M29 -> -2584 | K30: =-'Raw FS'!N29 -> -3207
A31: # | B31: Net Non current Assets | G31: =SUM(G29:G30) -> 2544 | H31: =SUM(H29:H30) -> 2998 | I31: =SUM(I29:I30) -> 3709 | J31: =SUM(J29:J30) -> 4062 | K31: =SUM(K29:K30) -> 6878
A33: # | B33: Invested Capital | G33: =G31+G17 -> 14656 | H33: =H31+H17 -> 17269 | I33: =I31+I17 -> 20953 | J33: =J31+J17 -> 28724 | K33: =K31+K17 -> 40738
B34: EBIT | G34: =HistoricalFS!H33+HistoricalFS!H21 -> 3122 | H34: =HistoricalFS!I33+HistoricalFS!I21 -> 4747 | I34: =HistoricalFS!J33+HistoricalFS!J21 -> 5242 | J34: =HistoricalFS!K33+HistoricalFS!K21 -> 5488 | K34: =HistoricalFS!L33+HistoricalFS!L21 -> 7981
A36: # | B36: ROIC | G36: =G34/G33 -> 0.21301856 | H36: =H34/H33 -> 0.27488563 | I36: =I34/I33 -> 0.25017897 | J36: =J34/J33 -> 0.19105974 | K36: =K34/K33 -> 0.19591045
B38: Calculation of Reinvestment Rate | G38: ='Data Sheet'!G$57 -> 44651 | H38: ='Data Sheet'!H$57 -> 45016 | I38: ='Data Sheet'!I$57 -> 45382 | J38: ='Data Sheet'!J$57 -> 45747 | K38: ='Data Sheet'!K$57 -> 46112
B40: Gross Capex | G40: =-SUM('cash flow data'!J13:J14) -> 216 | H40: =-SUM('cash flow data'!K13:K14) -> 420 | I40: =-SUM('cash flow data'!L13:L14) -> 671 | J40: =-SUM('cash flow data'!M13:M14) -> 470 | K40: =-SUM('cash flow data'!N13:N14) -> 877
B41: Depreciation | G41: ='Data Sheet'!G27 -> 399 | H41: ='Data Sheet'!H27 -> 441 | I41: ='Data Sheet'!I27 -> 584 | J41: ='Data Sheet'!J27 -> 693 | K41: ='Data Sheet'!K27 -> 826
B42: Net Capex | G42: =G40-G41 -> -183 | H42: =H40-H41 -> -21 | I42: =I40-I41 -> 87 | J42: =J40-J41 -> -223 | K42: =K40-K41 -> 51
B43: Change in Working Capital | H43: =H17-G17 -> 2159 | I43: =I17-H17 -> 2973 | J43: =J17-I17 -> 7418 | K43: =K17-J17 -> 9198
B45: EBIT | G45: =G34 -> 3122 | H45: =H34 -> 4747 | I45: =I34 -> 5242 | J45: =J34 -> 5488 | K45: =K34 -> 7981
B46: Marginal Tax Rate | G46: =WACC!$E$24 -> 0.2517 | H46: =WACC!$E$24 -> 0.2517 | I46: =WACC!$E$24 -> 0.2517 | J46: =WACC!$E$24 -> 0.2517 | K46: =WACC!$E$24 -> 0.2517
B47: NOPAT | G47: =G45*(1-G46) -> 2336.1926 | H47: =H45*(1-H46) -> 3552.1801 | I47: =I45*(1-I46) -> 3922.5886 | J47: =J45*(1-J46) -> 4106.6704 | K47: =K45*(1-K46) -> 5972.1823
B49: Reinvestment | H49: =SUM(H42:H43) -> 2138 | I49: =SUM(I42:I43) -> 3060 | J49: =SUM(J42:J43) -> 7195 | K49: =SUM(K42:K43) -> 9249
A51: # | B51: Reinvestment Rate | H51: =H49/H47 -> 0.6018839 | I51: =I49/I47 -> 0.7800971 | J51: =J49/J47 -> 1.7520276 | K51: =K49/K47 -> 1.5486801
J53: 4 year Average | K53: =AVERAGE(H51:K51) -> 1.1706722
J54: 4 year Median | K54: =MEDIAN(H51:K51) -> 1.1643886
B56: Calculation of Growth Rate | G56: ='Data Sheet'!G$57 -> 44651 | H56: ='Data Sheet'!H$57 -> 45016 | I56: ='Data Sheet'!I$57 -> 45382 | J56: ='Data Sheet'!J$57 -> 45747 | K56: ='Data Sheet'!K$57 -> 46112
B58: =B51 -> Reinvestment Rate | H58: =H51 -> 0.6018839 | I58: =I51 -> 0.7800971 | J58: =J51 -> 1.7520276 | K58: =K51 -> 1.5486801
B59: =B36 -> ROIC | H59: =H36 -> 0.27488563 | I59: =I36 -> 0.25017897 | J59: =J36 -> 0.19105974 | K59: =K36 -> 0.19591045
A61: # | B61: Intrinsic Growth Rate | H61: =H59*H58 -> 0.16544924 | I61: =I59*I58 -> 0.19516389 | J61: =J59*J58 -> 0.33474194 | K61: =K59*K58 -> 0.30340262
J63: 4 year Average | K63: =AVERAGE(H61:K61) -> 0.24968942
J64: 4 year Median | K64: =MEDIAN(H61:K61) -> 0.24928326

Sheet P E Valuation
B2: Forecast Assumptions | E2: Current Market Price | H2: =B28 -> Implied Target Price | I2: =B30 -> Implied Downside % | J2: Target Period
B4: Sales Growth Rate | C4: 0.15 | E4: =Teaser!B11 -> 5169 | F4: =Teaser!C11 -> (28th August, 2026 - close price) | H4: =F28 -> 5088.2674 | I4: =F30 -> -0.015618619 | J4: 12 months
B5: EBITDA Margin | C5: 0.1
B6: Net Profit Margin | C6: 0.06
B7: Forward P/E Multiple | C7: 65
B10: ="5 Year Forecast - "&'Data Sheet'!B2 -> 5 Year Forecast - TITAN COMPANY LTD
D11: ='Intrinsic Growth'!K2 -> 46112 | E11: =D11+365 -> 46477 | F11: =E11+365 -> 46842 | G11: =F11+365 -> 47207 | H11: =G11+365 -> 47572 | I11: =H11+365 -> 47937
B13: Sales | D13: =HistoricalFS!L6 -> 87584 | E13: =D13*(1+E14) -> 100721.6 | F13: =E13*(1+F14) -> 115829.84 | G13: =F13*(1+G14) -> 133204.32 | H13: =G13*(1+H14) -> 153184.96 | I13: =H13*(1+I14) -> 176162.71
B14: Growth Rate | E14: =$C$4 -> 0.15 | F14: =$C$4 -> 0.15 | G14: =$C$4 -> 0.15 | H14: =$C$4 -> 0.15 | I14: =$C$4 -> 0.15
B16: EBITDA | D16: =HistoricalFS!L18 -> 8357 | E16: =E13*E17 -> 10072.16 | F16: =F13*F17 -> 11582.984 | G16: =G13*G17 -> 13320.432 | H16: =H13*H17 -> 15318.496 | I16: =I13*I17 -> 17616.271
B17: EBITDA Margin | D17: =HistoricalFS!L19 -> 0.095416971 | E17: =$C$5 -> 0.1 | F17: =$C$5 -> 0.1 | G17: =$C$5 -> 0.1 | H17: =$C$5 -> 0.1 | I17: =$C$5 -> 0.1
B19: Net Profit | D19: =HistoricalFS!L39 -> 5073 | E19: =E13*E20 -> 6043.296 | F19: =F13*F20 -> 6949.7904 | G19: =G13*G20 -> 7992.259 | H19: =H13*H20 -> 9191.0978 | I19: =I13*I20 -> 10569.762
B20: Net Profit Margin | D20: =HistoricalFS!L40 -> 0.057921538 | E20: =$C$6 -> 0.06 | F20: =$C$6 -> 0.06 | G20: =$C$6 -> 0.06 | H20: =$C$6 -> 0.06 | I20: =$C$6 -> 0.06
B22: =HistoricalFS!B42 -> Equity shares outstanding | D22: =HistoricalFS!L42 -> 88.78 | E22: =$D$22 -> 88.78 | F22: =$D$22 -> 88.78 | G22: =$D$22 -> 88.78 | H22: =$D$22 -> 88.78 | I22: =$D$22 -> 88.78
B24: EPS | D24: =HistoricalFS!L44 -> 57.141248 | E24: =E19/E22 -> 68.070466 | F24: =F19/F22 -> 78.281036 | G24: =G19/G22 -> 90.023192 | H24: =H19/H22 -> 103.52667 | I24: =I19/I22 -> 119.05567
B26: Target P/E Multiple | E26: =$C$7 -> 65 | F26: =$C$7 -> 65 | G26: =$C$7 -> 65 | H26: =$C$7 -> 65 | I26: =$C$7 -> 65
B28: Implied Target Price | E28: =E24*E26 -> 4424.5803 | F28: =F24*F26 -> 5088.2674 | G28: =G24*G26 -> 5851.5075 | H28: =H24*H26 -> 6729.2336 | I28: =I24*I26 -> 7738.6186
B30: =IF(F30<0, "Implied Downside %", "Implied Upside %") -> Implied Downside % | F30: =(F28/E4)-1 -> -0.015618619
B33: Sensitivity Analysis
D34: Net Profit Margin
D35: =C6-0.04 -> 0.02 | E35: =C6-0.02 -> 0.04 | F35: =C6 -> 0.06 | G35: =C6+0.02 -> 0.08 | H35: =C6+0.04 -> 0.1
B36: Implied Target Price | C36: =C7-10 -> 55 | D36: =($F$13*D$35/$F$22)*$C36 -> 1435.1523 | E36: =($F$13*E$35/$F$22)*$C36 -> 2870.3047 | F36: =($F$13*F$35/$F$22)*$C36 -> 4305.457 | G36: =($F$13*G$35/$F$22)*$C36 -> 5740.6093 | H36: =($F$13*H$35/$F$22)*$C36 -> 7175.7617
C37: =C7-5 -> 60 | D37: =($F$13*D$35/$F$22)*$C37 -> 1565.6207 | E37: =($F$13*E$35/$F$22)*$C37 -> 3131.2415 | F37: =($F$13*F$35/$F$22)*$C37 -> 4696.8622 | G37: =($F$13*G$35/$F$22)*$C37 -> 6262.4829 | H37: =($F$13*H$35/$F$22)*$C37 -> 7828.1036
C38: =C7 -> 65 | D38: =($F$13*D$35/$F$22)*$C38 -> 1696.0891 | E38: =($F$13*E$35/$F$22)*$C38 -> 3392.1782 | F38: =($F$13*F$35/$F$22)*$C38 -> 5088.2674 | G38: =($F$13*G$35/$F$22)*$C38 -> 6784.3565 | H38: =($F$13*H$35/$F$22)*$C38 -> 8480.4456
C39: =C7+5 -> 70 | D39: =($F$13*D$35/$F$22)*$C39 -> 1826.5575 | E39: =($F$13*E$35/$F$22)*$C39 -> 3653.115 | F39: =($F$13*F$35/$F$22)*$C39 -> 5479.6725 | G39: =($F$13*G$35/$F$22)*$C39 -> 7306.2301 | H39: =($F$13*H$35/$F$22)*$C39 -> 9132.7876
C40: =C7+10 -> 75 | D40: =($F$13*D$35/$F$22)*$C40 -> 1957.0259 | E40: =($F$13*E$35/$F$22)*$C40 -> 3914.0518 | F40: =($F$13*F$35/$F$22)*$C40 -> 5871.0777 | G40: =($F$13*G$35/$F$22)*$C40 -> 7828.1036 | H40: =($F$13*H$35/$F$22)*$C40 -> 9785.1295

Sheet Scenario Analysis
B3: Scenario Analysis
B5: Forecast Assumptions | C5: Bear | D5: Base | E5: Bull | H5: Current Market Price | L5: Summary
B6: Sales Growth Rate | C6: =D6-0.04 -> 0.11 | D6: ='P E Valuation'!C4 -> 0.15 | E6: =D6+0.04 -> 0.19 | H6: ='P E Valuation'!E4 -> 5169 | I6: ='P E Valuation'!F4 -> (28th August, 2026 - close price) | L6: Prob weighted Target Price | N6: =(F32*C10)+(J32*D10)+(N32*E10) -> 5141.0627
B7: EBITDA Margin | C7: =D7-0.02 -> 0.08 | D7: ='P E Valuation'!C5 -> 0.1 | E7: =D7+0.02 -> 0.12 | L7: Expected Return Vector | N7: =N6/H6-1 -> -0.0054047856
B8: Net Profit Margin | C8: =D8-0.03 -> 0.03 | D8: ='P E Valuation'!C6 -> 0.06 | E8: =D8+0.02 -> 0.08 | L8: Risk/Reward Ratio | N8: =(N32-H6)/(H6-F32) -> 1.0157159
B9: Forward P/E Multiple | C9: =D9-10 -> 55 | D9: ='P E Valuation'!C7 -> 65 | E9: =D9+10 -> 75
B10: Assigned Probability | C10: =D10-0.25 -> 0.25 | D10: 0.5 | E10: =D10-0.25 -> 0.25
B12: ="Scenario Matrix - "&'Data Sheet'!B2 -> Scenario Matrix - TITAN COMPANY LTD
D13: Bear | H13: Base | L13: Bull
D15: ='P E Valuation'!D11 -> 46112 | E15: ='P E Valuation'!E11 -> 46477 | F15: ='P E Valuation'!F11 -> 46842 | H15: =D15 -> 46112 | I15: =E15 -> 46477 | J15: =F15 -> 46842 | L15: =H15 -> 46112 | M15: =I15 -> 46477 | N15: =J15 -> 46842
B17: Sales | D17: =HistoricalFS!$L$6 -> 87584 | E17: =D17*(1+E18) -> 97218.24 | F17: =E17*(1+F18) -> 107912.25 | H17: =HistoricalFS!$L$6 -> 87584 | I17: =H17*(1+I18) -> 100721.6 | J17: =I17*(1+J18) -> 115829.84 | L17: =HistoricalFS!$L$6 -> 87584 | M17: =L17*(1+M18) -> 104224.96 | N17: =M17*(1+N18) -> 124027.7
B18: Growth Rate | D18: =HistoricalFS!$L$7 -> 0.44872304 | E18: =$C$6 -> 0.11 | F18: =$C$6 -> 0.11 | H18: =HistoricalFS!$L$7 -> 0.44872304 | I18: =$D$6 -> 0.15 | J18: =$D$6 -> 0.15 | L18: =HistoricalFS!$L$7 -> 0.44872304 | M18: =$E$6 -> 0.19 | N18: =$E$6 -> 0.19
B20: EBITDA | D20: =HistoricalFS!$L$18 -> 8357 | E20: =E17*E21 -> 7777.4592 | F20: =F17*F21 -> 8632.9797 | H20: =HistoricalFS!$L$18 -> 8357 | I20: =I17*I21 -> 10072.16 | J20: =J17*J21 -> 11582.984 | L20: =HistoricalFS!$L$18 -> 8357 | M20: =M17*M21 -> 12506.995 | N20: =N17*N21 -> 14883.324
B21: EBITDA Margin | D21: =HistoricalFS!$L$19 -> 0.095416971 | E21: =$C$7 -> 0.08 | F21: =$C$7 -> 0.08 | H21: =HistoricalFS!$L$19 -> 0.095416971 | I21: =$D$7 -> 0.1 | J21: =$D$7 -> 0.1 | L21: =HistoricalFS!$L$19 -> 0.095416971 | M21: =$E$7 -> 0.12 | N21: =$E$7 -> 0.12
B23: Net Profit | D23: =HistoricalFS!$L$39 -> 5073 | E23: =E17*E24 -> 2916.5472 | F23: =F17*F24 -> 3237.3674 | H23: =HistoricalFS!$L$39 -> 5073 | I23: =I17*I24 -> 6043.296 | J23: =J17*J24 -> 6949.7904 | L23: =HistoricalFS!$L$39 -> 5073 | M23: =M17*M24 -> 8337.9968 | N23: =N17*N24 -> 9922.2162
B24: Net Profit Margin | D24: =HistoricalFS!$L$40 -> 0.057921538 | E24: =$C$8 -> 0.03 | F24: =$C$8 -> 0.03 | H24: =HistoricalFS!$L$40 -> 0.057921538 | I24: =$D$8 -> 0.06 | J24: =$D$8 -> 0.06 | L24: =HistoricalFS!$L$40 -> 0.057921538 | M24: =$E$8 -> 0.08 | N24: =$E$8 -> 0.08
B26: ='P E Valuation'!B22 -> Equity shares outstanding | D26: ='P E Valuation'!$D$22 -> 88.78 | E26: ='P E Valuation'!$D$22 -> 88.78 | F26: ='P E Valuation'!$D$22 -> 88.78 | H26: ='P E Valuation'!$D$22 -> 88.78 | I26: ='P E Valuation'!$D$22 -> 88.78 | J26: ='P E Valuation'!$D$22 -> 88.78 | L26: ='P E Valuation'!$D$22 -> 88.78 | M26: ='P E Valuation'!$D$22 -> 88.78 | N26: ='P E Valuation'!$D$22 -> 88.78
B28: EPS | D28: =D23/D26 -> 57.141248 | E28: =E23/E26 -> 32.851399 | F28: =F23/F26 -> 36.465053 | H28: =H23/H26 -> 57.141248 | I28: =I23/I26 -> 68.070466 | J28: =J23/J26 -> 78.281036 | L28: =L23/L26 -> 57.141248 | M28: =M23/M26 -> 93.917513 | N28: =N23/N26 -> 111.76184
B30: Target P/E Multiple | D30: =$C$9 -> 55 | E30: =$C$9 -> 55 | F30: =$C$9 -> 55 | H30: =$D$9 -> 65 | I30: =$D$9 -> 65 | J30: =$D$9 -> 65 | L30: =$E$9 -> 75 | M30: =$E$9 -> 75 | N30: =$E$9 -> 75
B32: Implied Target Price | F32: =F28*F30 -> 2005.5779 | J32: =J28*J30 -> 5088.2674 | N32: =N28*N30 -> 8382.138
B34: Implied Downside/Upside % | F34: =(F32/$H$6)-1 -> -0.61199886 | J34: =(J32/$H$6)-1 -> -0.015618619 | N34: =(N32/$H$6)-1 -> 0.62161695

Sheet DCF - Exit Multiple
B2: Calculation of PV OF FCFF | D2: ='Intrinsic Growth'!K2 -> 46112 | E2: =D2+365 -> 46477 | F2: =E2+365 -> 46842 | G2: =F2+365 -> 47207 | H2: =G2+365 -> 47572 | I2: =H2+365 -> 47937
B4: EBIT | D4: ='Intrinsic Growth'!K34 -> 7981 | E4: =D4*(1+$C$20) -> 9178.15 | F4: =E4*(1+$C$20) -> 10554.872 | G4: =F4*(1+$C$20) -> 12138.103 | H4: =G4*(1+$C$20) -> 13958.819 | I4: =H4*(1+$C$20) -> 16052.642
B5: Tax Rate | D5: ='Intrinsic Growth'!$K$46 -> 0.2517 | E5: ='Intrinsic Growth'!$K$46 -> 0.2517 | F5: ='Intrinsic Growth'!$K$46 -> 0.2517 | G5: ='Intrinsic Growth'!$K$46 -> 0.2517 | H5: ='Intrinsic Growth'!$K$46 -> 0.2517 | I5: ='Intrinsic Growth'!$K$46 -> 0.2517
B6: NOPAT | D6: =D4*(1-D5) -> 5972.1823 | E6: =E4*(1-E5) -> 6868.0096 | F6: =F4*(1-F5) -> 7898.2111 | G6: =G4*(1-G5) -> 9082.9428 | H6: =H4*(1-H5) -> 10445.384 | I6: =I4*(1-I5) -> 12012.192
B7: Less: Reinvestment rate | D7: 0.75 | E7: 0.7 | F7: 0.65 | G7: 0.6 | H7: 0.55 | I7: 0.5
B8: FCFF | D8: =D6*(1-D7) -> 1493.0456 | E8: =E6*(1-E7) -> 2060.4029 | F8: =F6*(1-F7) -> 2764.3739 | G8: =G6*(1-G7) -> 3633.1771 | H8: =H6*(1-H7) -> 4700.4229 | I8: =I6*(1-I7) -> 6006.0959
B9: Mid Year Convention | E9: 0.5 | F9: =E9+1 -> 1.5 | G9: =F9+1 -> 2.5 | H9: =G9+1 -> 3.5 | I9: =H9+1 -> 4.5
B10: Discounting Factor | E10: =1/(1+$C$22)^E9 -> 0.94104475 | F10: =1/(1+$C$22)^F9 -> 0.83335651 | G10: =1/(1+$C$22)^G9 -> 0.73799155 | H10: =1/(1+$C$22)^H9 -> 0.65353966 | I10: =1/(1+$C$22)^I9 -> 0.57875199
B11: PV of FCFF | E11: =E8*E10 -> 1938.9313 | F11: =F8*F10 -> 2303.709 | G11: =G8*G10 -> 2681.254 | H11: =H8*H10 -> 3071.9127 | I11: =I8*I10 -> 3476.04
B13: Calculation of PV OF Terminal Enterprise Value | D13: =D2 -> 46112 | E13: =E2 -> 46477 | F13: =F2 -> 46842 | G13: =G2 -> 47207 | H13: =H2 -> 47572 | I13: =I2 -> 47937
B15: EBITDA | D15: =HistoricalFS!L18 -> 8357 | E15: =D15*(1+$C$20) -> 9610.55 | F15: =E15*(1+$C$20) -> 11052.132 | G15: =F15*(1+$C$20) -> 12709.952 | H15: =G15*(1+$C$20) -> 14616.445 | I15: =H15*(1+$C$20) -> 16808.912
B16: Terminal EV/EBITDA Multiple | I16: 40
B17: Terminal Enterprise Value | I17: =I15*I16 -> 672356.48
B18: PV of Terminal Enterprise Value | I18: =I17*I10 -> 389127.65
B20: Expected Growth | C20: 0.15
B21: Terminal Growth | C21: 0.045
B22: WACC | C22: =WACC!J42 -> 0.1292223
B24: Calculation of Equity Value per Share | E24: Sensitivity Analysis
G25: Terminal EV/EBITDA Multiple
B26: PV of FCFF | C26: =SUM(E11:I11) -> 13471.847 | F26: =C34 -> 4211.4835 | G26: =I16-10 -> 30 | H26: =I16-5 -> 35 | I26: =I16 -> 40 | J26: =I16+5 -> 45 | K26: =I16+10 -> 50
B27: PV of Terminal Value | C27: =I18 -> 389127.65 | E27: WACC | F27: =C22-0.02 -> 0.1092223 | G27: =(($E$8/(1+$F27)^0.5)+($F$8/(1+$F27)^1.5)+($G$8/(1+$F27)^2.5)+($H$8/(1+$F27)^3.5)+($I$8/(1+$F27)^4.5)+($I$15*G$26/(1+$F27)^4.5)+$C$30-$C$31)/$C$33 -> 3398.7797 | H27: =(($E$8/(1+$F27)^0.5)+($F$8/(1+$F27)^1.5)+($G$8/(1+$F27)^2.5)+($H$8/(1+$F27)^3.5)+($I$8/(1+$F27)^4.5)+($I$15*H$26/(1+$F27)^4.5)+$C$30-$C$31)/$C$33 -> 3992.5395 | I27: =(($E$8/(1+$F27)^0.5)+($F$8/(1+$F27)^1.5)+($G$8/(1+$F27)^2.5)+($H$8/(1+$F27)^3.5)+($I$8/(1+$F27)^4.5)+($I$15*I$26/(1+$F27)^4.5)+$C$30-$C$31)/$C$33 -> 4586.2994 | J27: =(($E$8/(1+$F27)^0.5)+($F$8/(1+$F27)^1.5)+($G$8/(1+$F27)^2.5)+($H$8/(1+$F27)^3.5)+($I$8/(1+$F27)^4.5)+($I$15*J$26/(1+$F27)^4.5)+$C$30-$C$31)/$C$33 -> 5180.0592 | K27: =(($E$8/(1+$F27)^0.5)+($F$8/(1+$F27)^1.5)+($G$8/(1+$F27)^2.5)+($H$8/(1+$F27)^3.5)+($I$8/(1+$F27)^4.5)+($I$15*K$26/(1+$F27)^4.5)+$C$30-$C$31)/$C$33 -> 5773.819
B28: Value of Operating Assets | C28: =SUM(C26:C27) -> 402599.5 | F28: =C22-0.01 -> 0.1192223 | G28: =(($E$8/(1+$F28)^0.5)+($F$8/(1+$F28)^1.5)+($G$8/(1+$F28)^2.5)+($H$8/(1+$F28)^3.5)+($I$8/(1+$F28)^4.5)+($I$15*G$26/(1+$F28)^4.5)+$C$30-$C$31)/$C$33 -> 3253.7903 | H28: =(($E$8/(1+$F28)^0.5)+($F$8/(1+$F28)^1.5)+($G$8/(1+$F28)^2.5)+($H$8/(1+$F28)^3.5)+($I$8/(1+$F28)^4.5)+($I$15*H$26/(1+$F28)^4.5)+$C$30-$C$31)/$C$33 -> 3824.0477 | I28: =(($E$8/(1+$F28)^0.5)+($F$8/(1+$F28)^1.5)+($G$8/(1+$F28)^2.5)+($H$8/(1+$F28)^3.5)+($I$8/(1+$F28)^4.5)+($I$15*I$26/(1+$F28)^4.5)+$C$30-$C$31)/$C$33 -> 4394.305 | J28: =(($E$8/(1+$F28)^0.5)+($F$8/(1+$F28)^1.5)+($G$8/(1+$F28)^2.5)+($H$8/(1+$F28)^3.5)+($I$8/(1+$F28)^4.5)+($I$15*J$26/(1+$F28)^4.5)+$C$30-$C$31)/$C$33 -> 4964.5623 | K28: =(($E$8/(1+$F28)^0.5)+($F$8/(1+$F28)^1.5)+($G$8/(1+$F28)^2.5)+($H$8/(1+$F28)^3.5)+($I$8/(1+$F28)^4.5)+($I$15*K$26/(1+$F28)^4.5)+$C$30-$C$31)/$C$33 -> 5534.8197
F29: =C22 -> 0.1292223 | G29: =(($E$8/(1+$F29)^0.5)+($F$8/(1+$F29)^1.5)+($G$8/(1+$F29)^2.5)+($H$8/(1+$F29)^3.5)+($I$8/(1+$F29)^4.5)+($I$15*G$26/(1+$F29)^4.5)+$C$30-$C$31)/$C$33 -> 3115.7196 | H29: =(($E$8/(1+$F29)^0.5)+($F$8/(1+$F29)^1.5)+($G$8/(1+$F29)^2.5)+($H$8/(1+$F29)^3.5)+($I$8/(1+$F29)^4.5)+($I$15*H$26/(1+$F29)^4.5)+$C$30-$C$31)/$C$33 -> 3663.6015 | I29: =(($E$8/(1+$F29)^0.5)+($F$8/(1+$F29)^1.5)+($G$8/(1+$F29)^2.5)+($H$8/(1+$F29)^3.5)+($I$8/(1+$F29)^4.5)+($I$15*I$26/(1+$F29)^4.5)+$C$30-$C$31)/$C$33 -> 4211.4835 | J29: =(($E$8/(1+$F29)^0.5)+($F$8/(1+$F29)^1.5)+($G$8/(1+$F29)^2.5)+($H$8/(1+$F29)^3.5)+($I$8/(1+$F29)^4.5)+($I$15*J$26/(1+$F29)^4.5)+$C$30-$C$31)/$C$33 -> 4759.3654 | K29: =(($E$8/(1+$F29)^0.5)+($F$8/(1+$F29)^1.5)+($G$8/(1+$F29)^2.5)+($H$8/(1+$F29)^3.5)+($I$8/(1+$F29)^4.5)+($I$15*K$26/(1+$F29)^4.5)+$C$30-$C$31)/$C$33 -> 5307.2473
B30: Add: Cash | C30: ='Data Sheet'!K71 -> 1917 | F30: =C22+0.01 -> 0.1392223 | G30: =(($E$8/(1+$F30)^0.5)+($F$8/(1+$F30)^1.5)+($G$8/(1+$F30)^2.5)+($H$8/(1+$F30)^3.5)+($I$8/(1+$F30)^4.5)+($I$15*G$26/(1+$F30)^4.5)+$C$30-$C$31)/$C$33 -> 2984.1798 | H30: =(($E$8/(1+$F30)^0.5)+($F$8/(1+$F30)^1.5)+($G$8/(1+$F30)^2.5)+($H$8/(1+$F30)^3.5)+($I$8/(1+$F30)^4.5)+($I$15*H$26/(1+$F30)^4.5)+$C$30-$C$31)/$C$33 -> 3510.7501 | I30: =(($E$8/(1+$F30)^0.5)+($F$8/(1+$F30)^1.5)+($G$8/(1+$F30)^2.5)+($H$8/(1+$F30)^3.5)+($I$8/(1+$F30)^4.5)+($I$15*I$26/(1+$F30)^4.5)+$C$30-$C$31)/$C$33 -> 4037.3204 | J30: =(($E$8/(1+$F30)^0.5)+($F$8/(1+$F30)^1.5)+($G$8/(1+$F30)^2.5)+($H$8/(1+$F30)^3.5)+($I$8/(1+$F30)^4.5)+($I$15*J$26/(1+$F30)^4.5)+$C$30-$C$31)/$C$33 -> 4563.8906 | K30: =(($E$8/(1+$F30)^0.5)+($F$8/(1+$F30)^1.5)+($G$8/(1+$F30)^2.5)+($H$8/(1+$F30)^3.5)+($I$8/(1+$F30)^4.5)+($I$15*K$26/(1+$F30)^4.5)+$C$30-$C$31)/$C$33 -> 5090.4609
B31: Less: Debt | C31: =SUM('Raw FS'!N7:N9) -> 30621 | F31: =C22+0.02 -> 0.1492223 | G31: =(($E$8/(1+$F31)^0.5)+($F$8/(1+$F31)^1.5)+($G$8/(1+$F31)^2.5)+($H$8/(1+$F31)^3.5)+($I$8/(1+$F31)^4.5)+($I$15*G$26/(1+$F31)^4.5)+$C$30-$C$31)/$C$33 -> 2858.8082 | H31: =(($E$8/(1+$F31)^0.5)+($F$8/(1+$F31)^1.5)+($G$8/(1+$F31)^2.5)+($H$8/(1+$F31)^3.5)+($I$8/(1+$F31)^4.5)+($I$15*H$26/(1+$F31)^4.5)+$C$30-$C$31)/$C$33 -> 3365.0713 | I31: =(($E$8/(1+$F31)^0.5)+($F$8/(1+$F31)^1.5)+($G$8/(1+$F31)^2.5)+($H$8/(1+$F31)^3.5)+($I$8/(1+$F31)^4.5)+($I$15*I$26/(1+$F31)^4.5)+$C$30-$C$31)/$C$33 -> 3871.3344 | J31: =(($E$8/(1+$F31)^0.5)+($F$8/(1+$F31)^1.5)+($G$8/(1+$F31)^2.5)+($H$8/(1+$F31)^3.5)+($I$8/(1+$F31)^4.5)+($I$15*J$26/(1+$F31)^4.5)+$C$30-$C$31)/$C$33 -> 4377.5975 | K31: =(($E$8/(1+$F31)^0.5)+($F$8/(1+$F31)^1.5)+($G$8/(1+$F31)^2.5)+($H$8/(1+$F31)^3.5)+($I$8/(1+$F31)^4.5)+($I$15*K$26/(1+$F31)^4.5)+$C$30-$C$31)/$C$33 -> 4883.8606
B32: Value of Equity | C32: =C28+C30-C31 -> 373895.5
B33: No of shares | C33: ='Data Sheet'!B7 -> 88.78
B34: Equity Value per share | C34: =C32/C33 -> 4211.4835
B36: Share price | C36: =Teaser!B11 -> 5169 | D36: =Teaser!C11 -> (28th August, 2026 - close price)
B37: =IF(C36>C34,"Premium","Discount") -> Premium | C37: =C36/C34 -> 1.2273585
B40: Notes:
B41: The reinvestment rate utilizes a decaying glide path from 75% down to 55% by FY31, bridging historical working capital intensity with normalized steady-state efficiency.
B42: 15% used as the base-case expected growth rate, supported by Titan's stated medium-term 15–20% growth objective and current analyst estimates around 15–16%
B43: A 40x multiple reflects Titan's dominant pricing power

Sheet DCF - Perpetual Growth
B2: Calculation of PV OF FCFF | D2: ='Intrinsic Growth'!K2 -> 46112 | E2: =D2+365 -> 46477 | F2: =E2+365 -> 46842 | G2: =F2+365 -> 47207 | H2: =G2+365 -> 47572 | I2: =H2+365 -> 47937
B4: EBIT | D4: ='Intrinsic Growth'!K34 -> 7981 | E4: =D4*(1+$C$13) -> 9178.15 | F4: =E4*(1+$C$13) -> 10554.872 | G4: =F4*(1+$C$13) -> 12138.103 | H4: =G4*(1+$C$13) -> 13958.819 | I4: =H4*(1+$C$13) -> 16052.642
B5: Tax Rate | D5: ='Intrinsic Growth'!$K$46 -> 0.2517 | E5: ='Intrinsic Growth'!$K$46 -> 0.2517 | F5: ='Intrinsic Growth'!$K$46 -> 0.2517 | G5: ='Intrinsic Growth'!$K$46 -> 0.2517 | H5: ='Intrinsic Growth'!$K$46 -> 0.2517 | I5: ='Intrinsic Growth'!$K$46 -> 0.2517
B6: NOPAT | D6: =D4*(1-D5) -> 5972.1823 | E6: =E4*(1-E5) -> 6868.0096 | F6: =F4*(1-F5) -> 7898.2111 | G6: =G4*(1-G5) -> 9082.9428 | H6: =H4*(1-H5) -> 10445.384 | I6: =I4*(1-I5) -> 12012.192
B7: Less: Reinvestment rate | D7: 0.75 | E7: 0.7 | F7: 0.65 | G7: 0.6 | H7: 0.55 | I7: 0.5
B8: FCFF | D8: =D6*(1-D7) -> 1493.0456 | E8: =E6*(1-E7) -> 2060.4029 | F8: =F6*(1-F7) -> 2764.3739 | G8: =G6*(1-G7) -> 3633.1771 | H8: =H6*(1-H7) -> 4700.4229 | I8: =I6*(1-I7) -> 6006.0959
B9: Mid Year Convention | E9: 0.5 | F9: =E9+1 -> 1.5 | G9: =F9+1 -> 2.5 | H9: =G9+1 -> 3.5 | I9: =H9+1 -> 4.5
B10: Discounting Factor | E10: =1/(1+$C$15)^E9 -> 0.94104475 | F10: =1/(1+$C$15)^F9 -> 0.83335651 | G10: =1/(1+$C$15)^G9 -> 0.73799155 | H10: =1/(1+$C$15)^H9 -> 0.65353966 | I10: =1/(1+$C$15)^I9 -> 0.57875199
B11: PV of FCFF | E11: =E8*E10 -> 1938.9313 | F11: =F8*F10 -> 2303.709 | G11: =G8*G10 -> 2681.254 | H11: =H8*H10 -> 3071.9127 | I11: =I8*I10 -> 3476.04
B13: Expected Growth | C13: 0.15
B14: Terminal Growth | C14: 0.045
B15: WACC | C15: =WACC!J42 -> 0.1292223
B17: Calculation of Terminal Value | E17: Sensitivity Analysis
E18: =C35 -> 363.04218 | F18: 0.13 | G18: 0.14 | H18: 0.15 | I18: 0.16 | J18: 0.17
B19: FCFF(n+1) | C19: =I8*(1+C13) -> 6907.0103 | E19: 0.035 | F19: 250.09955 | G19: 277.62457 | H19: 306.30252 | I19: 336.17282 | J19: 367.27588
B20: WACC | C20: =C15 -> 0.1292223 | E20: 0.04 | F20: 274.20382 | G20: 303.03736 | H20: 333.08251 | I20: 364.38075 | J20: 396.97466
B21: Terminal Growth Rate | C21: =C14 -> 0.045 | E21: 0.045 | F21: 301.17007 | G21: 331.46751 | H21: 363.04218 | I21: 395.93791 | J21: 430.19967
E22: 0.05 | F22: 331.5402 | G22: 363.48631 | H22: 396.78357 | I22: 431.47844 | J22: 467.61857
B23: Terminal Value | C23: =C19/(C20-C21) -> 82009.285 | E23: 0.055 | F23: 366.0021 | G23: 399.81901 | H23: 435.07095 | I23: 471.80735 | J23: 510.07894
B25: Calculation of Equity Value per Share
B27: PV of FCFF | C27: =SUM(E11:I11) -> 13471.847
B28: PV of Terminal Value | C28: =C23*I10 -> 47463.037
B29: Value of Operating Assets | C29: =SUM(C27:C28) -> 60934.884
B31: Add: Cash | C31: ='Data Sheet'!K71 -> 1917
B32: Less: Debt | C32: =SUM('Raw FS'!N7:N9) -> 30621
B33: Value of Equity | C33: =C29+C31-C32 -> 32230.884
B34: No of shares | C34: ='Data Sheet'!B7 -> 88.78
B35: Equity Value per share | C35: =C33/C34 -> 363.04218
B37: Share price | C37: =Teaser!B11 -> 5169 | D37: =Teaser!C11 -> (28th August, 2026 - close price)
B38: =IF(C37>C35,"Premium","Discount") -> Premium | C38: =C37/C35 -> 14.238015
B41: Notes:
B42: The reinvestment rate utilizes a decaying glide path from 75% down to 55% by FY31, bridging historical working capital intensity with normalized steady-state efficiency.
B43: 15% used as the base-case expected growth rate, supported by Titan's stated medium-term 15–20% growth objective and current analyst estimates around 15–16%

Sheet Relative Valuation>

Sheet Comps_Val
B3: Amount in crores
B4: Comparable Company Valuation
D6: Market Data | K6: Financials | O6: Valuation
B7: Company | C7: Ticker | D7: Share price | E7: Shares outstanding | F7: Equity Value | G7: Net Debt | H7: Enterprise Value | K7: Revenue | L7: EBITDA | M7: Net Income | O7: EV/Revenue | P7: EV/EBITDA | Q7: P/E
B9: =Comps_Data!C3 -> Titan Company | C9: =Comps_Data!D3 -> TITAN | D9: =Comps_Data!E3 -> 5169 | E9: =Comps_Data!F3 -> 88.78 | F9: =E9*D9 -> 458903.82 | G9: =Comps_Data!J3 -> 29037 | H9: =F9+G9 -> 487940.82 | K9: =Comps_Data!L3 -> 92417 | L9: =Comps_Data!M3 -> 10012.509 | M9: =Comps_Data!N3 -> 5760 | O9: =$H9/$K9 -> 5.2797734 | P9: =$H9/$L9 -> 48.733121 | Q9: =F9/M9 -> 79.670802
B10: =Comps_Data!C4 -> Kalyan Jewellers | C10: =Comps_Data!D4 -> KALYANKJIL | D10: =Comps_Data!E4 -> 615.8 | E10: =Comps_Data!F4 -> 103.28 | F10: =E10*D10 -> 63599.824 | G10: =Comps_Data!J4 -> 5086.26 | H10: =F10+G10 -> 68686.084 | K10: =Comps_Data!L4 -> 39063.32 | L10: =Comps_Data!M4 -> 2833.0189 | M10: =Comps_Data!N4 -> 1434.98 | O10: =$H10/$K10 -> 1.7583268 | P10: =$H10/$L10 -> 24.244838 | Q10: =F10/M10 -> 44.321053
B11: =Comps_Data!C5 -> Thangamayil Jew. | C11: =Comps_Data!D5 -> THANGAMAYL | D11: =Comps_Data!E5 -> 5440.5 | E11: =Comps_Data!F5 -> 3.11 | F11: =E11*D11 -> 16919.955 | G11: =Comps_Data!J5 -> 671.42 | H11: =F11+G11 -> 17591.375 | K11: =Comps_Data!L5 -> 9622.28 | L11: =Comps_Data!M5 -> 636.8824 | M11: =Comps_Data!N5 -> 391.04 | O11: =$H11/$K11 -> 1.828192 | P11: =$H11/$L11 -> 27.621073 | Q11: =F11/M11 -> 43.269116
B12: =Comps_Data!C6 -> Bluestone Jewel | C12: =Comps_Data!D6 -> BLUESTONE | D12: =Comps_Data!E6 -> 794.7 | E12: =Comps_Data!F6 -> 15.27 | F12: =E12*D12 -> 12135.069 | G12: =Comps_Data!J6 -> 1797 | H12: =F12+G12 -> 13932.069 | K12: =Comps_Data!L6 -> 2680.6 | L12: =Comps_Data!M6 -> 488.41514 | M12: =Comps_Data!N6 -> 53.89 | O12: =$H12/$K12 -> 5.1973696 | P12: =$H12/$L12 -> 28.525056 | Q12: =F12/M12 -> 225.1822
B13: =Comps_Data!C7 -> Sky Gold & Diam. | C13: =Comps_Data!D7 -> SKYGOLD | D13: =Comps_Data!E7 -> 811.4 | E13: =Comps_Data!F7 -> 15.49 | F13: =E13*D13 -> 12568.586 | G13: =Comps_Data!J7 -> 693.98 | H13: =F13+G13 -> 13262.566 | K13: =Comps_Data!L7 -> 7176.44 | L13: =Comps_Data!M7 -> 559.68862 | M13: =Comps_Data!N7 -> 343.15 | O13: =$H13/$K13 -> 1.8480704 | P13: =$H13/$L13 -> 23.696329 | Q13: =F13/M13 -> 36.62709
B14: =Comps_Data!C8 -> PC Jeweller | C14: =Comps_Data!D8 -> PCJEWELLER | D14: =Comps_Data!E8 -> 10.94 | E14: =Comps_Data!F8 -> 975.21 | F14: =E14*D14 -> 10668.797 | G14: =Comps_Data!J8 -> 1102.78 | H14: =F14+G14 -> 11771.577 | K14: =Comps_Data!L8 -> 3505.01 | L14: =Comps_Data!M8 -> 901.39836 | M14: =Comps_Data!N8 -> 774.41 | O14: =$H14/$K14 -> 3.3585004 | P14: =$H14/$L14 -> 13.05924 | Q14: =F14/M14 -> 13.776678
B15: =Comps_Data!C9 -> P N Gadgil Jewe. | C15: =Comps_Data!D9 -> PNGJL | D15: =Comps_Data!E9 -> 598 | E15: =Comps_Data!F9 -> 14.72 | F15: =E15*D15 -> 8802.56 | G15: =Comps_Data!J9 -> 1208.4 | H15: =F15+G15 -> 10010.96 | K15: =Comps_Data!L9 -> 11437.52 | L15: =Comps_Data!M9 -> 773.28104 | M15: =Comps_Data!N9 -> 445.82 | O15: =$H15/$K15 -> 0.87527366 | P15: =$H15/$L15 -> 12.946082 | Q15: =F15/M15 -> 19.74465
B16: =Comps_Data!C12 -> Senco Gold | C16: =Comps_Data!D12 -> SENCO | D16: =Comps_Data!E12 -> 354.85 | E16: =Comps_Data!F12 -> 16.39 | F16: =E16*D16 -> 5815.9915 | G16: =Comps_Data!J12 -> 2108.26 | H16: =F16+G16 -> 7924.2515 | K16: =Comps_Data!L12 -> 9659.79 | L16: =Comps_Data!M12 -> 1075.6049 | M16: =Comps_Data!N12 -> 570.8 | O16: =$H16/$K16 -> 0.82033372 | P16: =$H16/$L16 -> 7.3672509 | Q16: =F16/M16 -> 10.189193
B19: High | O19: =MAX(O10:O16) -> 5.1973696 | P19: =MAX(P10:P16) -> 28.525056 | Q19: =MAX(Q10:Q16) -> 225.1822
B20: 75th percentile | O20: =_xlfn.QUARTILE.EXC(O10:O16,3) -> 3.3585004 | P20: =_xlfn.QUARTILE.EXC(P10:P16,3) -> 27.621073 | Q20: =_xlfn.QUARTILE.EXC(Q10:Q16,3) -> 44.321053
B21: Average | O21: =AVERAGE(O10:O16) -> 2.2408666 | P21: =AVERAGE(P10:P16) -> 19.637124 | Q21: =AVERAGE(Q10:Q16) -> 56.158569
B22: Median | O22: =MEDIAN(O10:O16) -> 1.828192 | P22: =MEDIAN(P10:P16) -> 23.696329 | Q22: =MEDIAN(Q10:Q16) -> 36.62709
B23: 25th percentile | O23: =_xlfn.QUARTILE.EXC(O10:O16,1) -> 0.87527366 | P23: =_xlfn.QUARTILE.EXC(P10:P16,1) -> 12.946082 | Q23: =_xlfn.QUARTILE.EXC(Q10:Q16,1) -> 13.776678
B24: Low | O24: =MIN(O10:O16) -> 0.82033372 | P24: =MIN(P10:P16) -> 7.3672509 | Q24: =MIN(Q10:Q16) -> 10.189193
B27: ="Comparable Valuation - "&'Data Sheet'!B2 -> Comparable Valuation - TITAN COMPANY LTD | O27: =O7 -> EV/Revenue | P27: =P7 -> EV/EBITDA | Q27: =Q7 -> P/E
B29: Implied Enterprise Value | O29: =O22*K9 -> 168956.02 | P29: =P22*L9 -> 237259.71 | Q29: =+Q30+Q31 -> 240009.04
B30: Net Debt | O30: =$G$9 -> 29037 | P30: =$G$9 -> 29037 | Q30: =$G$9 -> 29037
B31: Implied Market Value | O31: =O29-O30 -> 139919.02 | P31: =P29-P30 -> 208222.71 | Q31: =Q22*M9 -> 210972.04
B32: Shares Outstanding | O32: =$E$9 -> 88.78 | P32: =$E$9 -> 88.78 | Q32: =$E$9 -> 88.78
B34: Implied Value per Share | O34: =O31/O32 -> 1576.0196 | P34: =P31/P32 -> 2345.3786 | Q34: =Q31/Q32 -> 2376.3465
O36: =IF(O34>$D$9,"Trading at discount","Trading at premium") -> Trading at premium | P36: =IF(P34>$D$9,"Trading at discount","Trading at premium") -> Trading at premium | Q36: =IF(Q34>$D$9,"Trading at discount","Trading at premium") -> Trading at premium
B40: Peer multiples based on market prices as of 28 Aug 2026 and latest TTM financials (June 2026)

Sheet Data>

Sheet Data Sheet
A1: SOURCE: SCREENER
A2: COMPANY NAME | B2: TITAN COMPANY LTD
A3: LATEST VERSION | B3: 2.1 | E3: PLEASE DO NOT MAKE ANY CHANGES TO THIS SHEET
A4: CURRENT VERSION | B4: 2.1
A6: META
A7: Number of shares | B7: 88.78
A8: Face Value | B8: 1
A9: Current Price | B9: =Teaser!B11 -> 5169 | C9: =Teaser!C11 -> (28th August, 2026 - close price)
A10: Market Capitalization | B10: =B9*B7 -> 458903.82
A16: PROFIT & LOSS | B16: 32432.08 | K16: 29129.19
A17: Report Date | B17: 42825 | C17: 43190 | D17: 43555 | E17: 43921 | F17: 44286 | G17: 44651 | H17: 45016 | I17: 45382 | J17: 45747 | K17: 46112
A18: Sales | B18: 13260.83 | C18: 16119.77 | D18: 19778.52 | E18: 21052 | F18: 21644 | G18: 28799 | H18: 40575 | I18: 51084 | J18: 60456 | K18: 87584
A19: Raw Material Cost | B19: 9821.14 | C19: 12664.83 | D19: 15170.66 | E19: 16033 | F19: 16292 | G19: 26436 | H19: 32589 | I19: 42103 | J19: 55271 | K19: 80243
A20: Change in Inventory | B20: 313.71 | C20: 978.61 | D20: 776.41 | E20: 878 | F20: -122 | G20: 4795 | H20: 2234 | I20: 2671 | J20: 7815 | K20: 9936
A21: Power and Fuel | B21: 43.84 | C21: 45.32 | D21: 48.51 | E21: 52 | F21: 37 | G21: 45 | H21: 59 | I21: 71 | J21: 78 | K21: 87
A22: Other Mfr. Exp | B22: 160.42 | C22: 124.83 | D22: 193.28 | E22: 215 | F22: 141 | G22: 183 | H22: 225 | I22: 286 | J22: 326 | K22: 375
A23: Employee Cost | B23: 894.32 | C23: 906.26 | D23: 1024.44 | E23: 1204 | F23: 1069 | G23: 1356 | H23: 1656 | I23: 1875 | J23: 2164 | K23: 2692
A24: Selling and admin | B24: 1211.16 | C24: 1277.81 | D24: 1454.32 | E24: 1470 | F24: 1029 | G24: 1697 | H24: 2715 | I24: 3249 | J24: 3494 | K24: 4185
A25: Other Expenses | B25: 279.76 | C25: 435.13 | D25: 669.93 | E25: 493 | F25: 1229 | G25: 533 | H25: 683 | I25: 879 | J25: 1244 | K25: 1581
A26: Other Income | B26: -42.38 | C26: 69.93 | D26: 178.48 | E26: 153 | F26: 180 | G26: 177 | H26: 306 | I26: 534 | J26: 487 | K26: 450
A27: Depreciation | B27: 110.53 | C27: 131.43 | D27: 162.84 | E27: 348 | F27: 375 | G27: 399 | H27: 441 | I27: 584 | J27: 693 | K27: 826
A28: Interest | B28: 37.74 | C28: 52.92 | D28: 52.54 | E28: 166 | F28: 203 | G28: 218 | H28: 300 | I28: 619 | J28: 953 | K28: 1180
... A33: Effective Tax Rate | B33: 0.28 | C33: 0.25 | D33: 0.35 | E33: 0.21 | F33: 0.35 | G33: 0.39 | H33: 0.08 | I33: -0.04 | J33: -0.24 | K33: -0.6
A35: EBITDA | B35: =HistoricalFS!C18 -> 1163.9 | C35: =HistoricalFS!D18 -> 1644.2 | D35: =HistoricalFS!E18 -> 1993.79 | E35: =HistoricalFS!F18 -> 2463 | F35: =HistoricalFS!G18 -> 1725 | G35: =HistoricalFS!H18 -> 3344 | H35: =HistoricalFS!I18 -> 4882 | I35: =HistoricalFS!J18 -> 5292 | ... K35: =HistoricalFS!L18 -> 8357
A41: Quarters
A42: Report Date | B42: 45382 | C42: 45473 | D42: 45565 | E42: 45657 | F42: 45747 | G42: 45838 | H42: 45930 | I42: 46022 | J42: 46112 | K42: 46203
A43: Sales | B43: 12494 | C43: 13266 | D43: 14534 | E43: 17740 | F43: 14916 | G43: 16523 | H43: 18725 | I43: 25416 | J43: 26920 | K43: 21356
A44: Expenses | B44: 11303 | C44: 12019 | D44: 13298 | E44: 16066 | F44: 13379 | G44: 14693 | H44: 16850 | I44: 22703 | J44: 24982 | K44: 18466
A45: Other Income | B45: 159 | C45: 120 | D45: 123 | E45: 128 | F45: 116 | G45: 105 | H45: 113 | I45: -1 | J45: 235 | K45: 148
A46: Depreciation | B46: 158 | C46: 164 | D46: 171 | E46: 175 | F46: 183 | G46: 184 | H46: 189 | I46: 207 | J46: 246 | K46: 256
A47: Interest | B47: 201 | C47: 230 | D47: 240 | E47: 231 | F47: 252 | G47: 271 | H47: 277 | I47: 282 | J47: 350 | K47: 353
A48: Profit before tax | B48: 991 | C48: 973 | D48: 948 | E48: 1396 | F48: 1218 | G48: 1480 | H48: 1522 | I48: 2223 | J48: 1577 | K48: 2429
A49: Tax | B49: 220 | C49: 258 | D49: 244 | E49: 349 | F49: 347 | G49: 389 | H49: 402 | I49: 539 | J49: 398 | K49: 652
A50: Net profit | B50: 771 | C50: 715 | D50: 704 | E50: 1047 | F50: 871 | G50: 1091 | H50: 1120 | I50: 1684 | J50: 1179 | K50: 1777
A51: Operating Profit | B51: 1191 | C51: 1247 | D51: 1236 | E51: 1674 | F51: 1537 | G51: 1830 | H51: 1875 | I51: 2713 | J51: 1938 | K51: 2890
A52: EBITDA | B52: 1238.68 | C52: 6765.23 | D52: 12106.31 | E52: 624.13 | F52: 5696.47 | G52: 5014.11 | H52: 7688.78 | I52: 8538.01 | J52: 4774.12 | K52: 6982.91
A56: BALANCE SHEET
A57: Report Date | B57: 42825 | C57: 43190 | D57: 43555 | E57: 43921 | F57: 44286 | G57: 44651 | H57: 45016 | I57: 45382 | J57: 45747 | K57: 46112
A58: Equity Share Capital | B58: 88.78 | C58: 88.78 | D58: 88.78 | E58: 89 | F58: 89 | G58: 89 | H58: 89 | I58: 89 | J58: 89 | K58: 89
A59: Reserves | B59: 4143.6 | C59: 5001.1 | D59: 5981.37 | E59: 6580 | F59: 7408 | G59: 9214 | H59: 11762 | I59: 9304 | J59: 11535 | K59: 15614
A60: Borrowings | B60: 1882.43 | C60: 1691.01 | D60: 2392.98 | E60: 3562 | F60: 5638 | G60: 7275 | H60: 9367 | I60: 15528 | J60: 20777 | K60: 30621
A61: Other Liabilities | B61: 2292.76 | C61: 2740.15 | D61: 3246.71 | E61: 3313 | F61: 3309 | G61: 4610 | H61: 5802 | I61: 6626 | J61: 8244 | K61: 14237
A62: Trade Payables | B62: 783 | C62: 878 | D62: 906 | E62: 596 | F62: 789 | G62: 1294 | H62: 1214 | I62: 1410 | J62: 1963 | K62: 2864
A63: Total Liabilities | B63: 8407.57 | C63: 9521.04 | D63: 11709.84 | E63: 13544 | F63: 16444 | G63: 21188 | H63: 27020 | I63: 31547 | J63: 40645 | K63: 60561
A64: Net Block | B64: 1188.72 | C64: 1473.81 | D64: 1566.63 | E64: 2633 | F64: 2523 | G64: 2544 | H64: 2998 | I64: 3709 | J64: 4062 | K64: 6878
A65: Capital Work in Progress | B65: 152.07 | C65: 43.37 | D65: 31.77 | E65: 18 | F65: 32 | G65: 85 | H65: 144 | I65: 97 | J65: 105 | K65: 163
A66: Investments | B66: 430.73 | C66: 35.99 | D66: 108.42 | E66: 158 | F66: 2824 | G66: 294 | H66: 2515 | I66: 2345 | J66: 1988 | K66: 3506
A67: Other Assets | B67: 6636.05 | C67: 7967.87 | D67: 10003.02 | E67: 10735 | F67: 11065 | G67: 18265 | H67: 21363 | I67: 25396 | J67: 34490 | K67: 50014
A68: Total | B68: 8407.57 | C68: 9521.04 | D68: 11709.84 | E68: 13544 | F68: 16444 | G68: 21188 | H68: 27020 | I68: 31547 | J68: 40645 | K68: 60561
... A72: No. of Equity Shares | B72: 887786160 | C72: 887786160 | D72: 887786160 | E72: 887786160 | F72: 887786160 | G72: 887786160 | H72: 890000000 | I72: 890000000 | J72: 890000000 | K72: 890000000
A73: New Bonus Shares
A74: Face value | B74: 1 | C74: 1 | D74: 1 | E74: 1 | F74: 1 | G74: 1 | H74: 1 | I74: 1 | J74: 1 | K74: 1
H75: -4,101.26 | I75: 22,304.78 | J75: 17,441.51 | K75: 6,045.18
A76: Total Assets | B76: =SUM(B68:B71) -> 14319.84 | C76: =SUM(C68:C71) -> 16359.48 | D76: =SUM(D68:D71) -> 20235.59 | E76: =SUM(E68:E71) -> 22340 | F76: =SUM(F68:F71) -> 25778 | G76: =SUM(G68:G71) -> 36935 | H76: =SUM(H68:H71) -> 45621 | I76: =SUM(I68:I71) -> 53142 | ... K76: =SUM(K68:K71) -> 106137
A82: CASH FLOW:
A83: Report Date | B83: 42825 | C83: 43190 | D83: 43555 | E83: 43921 | F83: 44286 | G83: 44651 | H83: 45016 | I83: 45382 | J83: 45747 | K83: 46112
A84: Cash from Operating Activity | B84: 1712.3 | C84: -51.12 | D84: 1242.92 | E84: -348 | F84: 4139 | G84: -724 | H84: 1370 | I84: 1695 | J84: -541 | K84: 5590
A85: Cash from Investing Activity | B85: -953.15 | C85: 97.62 | D85: -796.61 | E85: 235 | F85: -2799 | G85: 1165 | H85: -1814 | I85: -189 | J85: 546 | K85: -2965
A86: Cash from Financing Activity | B86: -165.6 | C86: -252.45 | D86: -488.83 | E86: -242 | F86: -1234 | G86: -403 | H86: 457 | I86: -1329 | J86: -7 | K86: -2159
A87: Net Cash Flow | B87: 593.55 | C87: -205.95 | D87: -42.52 | E87: -355 | F87: 106 | G87: 38 | H87: 13 | I87: 177 | J87: -2 | K87: 466
A92: PRICE: | B92: 462.75 | C92: 942.3 | D92: 1141.85 | E92: 933.7 | F92: 1558.05 | G92: 2536.15 | H92: 2514.9 | I92: 3801.8 | J92: 3063.35 | K92: 3951.4
A95: DERIVED:
A96: Adjusted Equity Shares in Cr | B96: 88.78 | C96: 88.78 | D96: 88.78 | E96: 88.78 | F96: 88.78 | G96: 88.78 | H96: 88.78 | I96: 88.78 | J96: 88.78 | K96: 88.78
A98: Market cap in cr | B98: =B92*B96 -> 41082.945 | C98: =C92*C96 -> 83657.394 | D98: =D92*D96 -> 101373.44 | E98: =E92*E96 -> 82893.886 | F98: =F92*F96 -> 138323.68 | G98: =G92*G96 -> 225159.4 | H98: =H92*H96 -> 223272.82 | I98: =I92*I96 -> 337523.8 | ... K98: =K92*K96 -> 350805.29
A99: Enterprise value in cr | B99: =B98+B60-B71 -> 42186.445 | C99: =C98+C60-C71 -> 84730.494 | D99: =D98+D60-D71 -> 102699.94 | E99: =E98+E60-E71 -> 86074.886 | F99: =F98+F60-F71 -> 143401.68 | G99: =G98+G60-G71 -> 230861.4 | H99: =H98+H60-H71 -> 231296.82 | I99: =I98+I60-I71 -> 351525.8 | ... K99: =K98+K60-K71 -> 379509.29
A100: Book value in cr | B100: =B58+B59 -> 4232.38 | C100: =C58+C59 -> 5089.88 | D100: =D58+D59 -> 6070.15 | E100: =E58+E59 -> 6669 | F100: =F58+F59 -> 7497 | G100: =G58+G59 -> 9303 | H100: =H58+H59 -> 11851 | I100: =I58+I59 -> 9393 | ... K100: =K58+K59 -> 15703

Sheet cash flow data
A1: SOURCE: SCREENER | B1: TITAN
C2: 42064 | D2: 42430 | E2: 42795 | F2: 43160 | G2: 43525 | H2: 43891 | I2: 44256 | J2: 44621 | K2: 44986 | L2: 45352 | M2: 45717 | N2: 46082
B3: Cash from Operating Activity - | C3: 503 | D3: 576 | E3: 1712 | F3: -51 | G3: 1243 | H3: -348 | I3: 4139 | J3: -724 | K3: 1370 | L3: 1695 | M3: -541 | N3: 5590
B4: Profit from operations | C4: 1163 | D4: 942 | E4: 1073 | F4: 1642 | G4: 2183 | H4: 2481 | I4: 1789 | J4: 3298 | K4: 4937 | L4: 5404 | M4: 5774 | N4: 8447
B5: Receivables | C5: -39 | D5: 0 | E5: -12 | F5: -90 | G5: -139 | H5: 109 | I5: -59 | J5: -207 | K5: -112 | L5: -348 | M5: -95 | N5: 210
B6: Inventory | C6: -180 | D6: -398 | E6: -448 | F6: -996 | G6: -1120 | H6: -1057 | I6: -316 | J6: -5199 | K6: -2977 | L6: -2462 | M6: -9072 | N6: -11592
B7: Payables | C7: 1079 | D7: -245 | E7: 238 | F7: 95 | G7: 32 | H7: -310 | I7: 195 | J7: 504 | K7: -89 | L7: 196 | M7: 564 | N7: 472
B8: Loans Advances | C8: -71 | D8: -66 | E8: 0 | F8: 3 | G8: -24 | H8: -20 | I8: -8 | J8: -3 | K8: -18 | L8: -21 | M8: 4 | N8: -8
B9: Other WC items | C9: -1204 | D9: 545 | E9: 375 | F9: 22 | G9: 206 | H9: -226 | I9: 184 | J9: 497 | K9: 882 | L9: 57 | M9: 905 | N9: 2494
B10: Working capital changes | C10: -415 | D10: -163 | E10: 916 | F10: -1237 | G10: -304 | H10: -2272 | I10: 2621 | J10: -3220 | K10: -2413 | L10: -2536 | M10: -5226 | N10: -1120
B11: Direct taxes | C11: -245 | D11: -202 | E11: -277 | F11: -456 | G11: -636 | H11: -557 | I11: -271 | J11: -802 | K11: -1154 | L11: -1173 | M11: -1089 | N11: -1737
B12: Cash from Investing Activity - | C12: -118 | D12: -159 | E12: -953 | F12: 98 | G12: -797 | H12: 235 | I12: -2799 | J12: 1165 | K12: -1814 | L12: -189 | M12: 546 | N12: -2965
B13: Fixed assets purchased | C13: -209 | D13: -254 | E13: -256 | F13: -305 | G13: -265 | H13: -355 | I13: -146 | J13: -224 | K13: -432 | L13: -691 | M13: -494 | N13: -902
B14: Fixed assets sold | C14: 2 | D14: 2 | E14: 5 | F14: 6 | G14: 1 | H14: 10 | I14: 7 | J14: 8 | K14: 12 | L14: 20 | M14: 24 | N14: 25
... B35: Net Cash Flow | C35: -620 | D35: -88 | E35: 594 | F35: -206 | G35: -43 | H35: -355 | I35: 106 | J35: 38 | K35: 13 | L35: 177 | M35: -2 | N35: 466

Sheet Segment Data
B1: SOURCE: Titan annual reports
B4: SEGMENT REVENUE | C4: ='Data Sheet'!G17 -> 44651 | D4: ='Data Sheet'!H17 -> 45016 | E4: ='Data Sheet'!I17 -> 45382 | F4: ='Data Sheet'!J17 -> 45747 | G4: ='Data Sheet'!K17 -> 46112
B5: Watches | C5: 2309 | D5: 3296 | E5: 3904 | F5: 4576 | G5: 5233
B6: Jewellery | C6: 24313 | D6: 34105 | E6: 42292 | F6: 49227 | G6: 71108
B7: EyeCare | C7: 517 | D7: 689 | E7: 724 | F7: 796 | G7: 907
B8: Others | C8: 154 | D8: 295 | E8: 378 | F8: 406 | G8: 508
B9: Corporate (Unallocated) | C9: 163 | D9: 184 | E9: 326 | F9: 330 | G9: 333
B10: Segment Total | C10: 27456 | D10: 38569 | E10: 47624 | F10: 55335 | G10: 78089
B11: Caratlane & other subs | C11: =C12-C10 -> 1343 | D11: =D12-D10 -> 2006 | E11: =E12-E10 -> 3460 | F11: =F12-F10 -> 5121 | G11: =G12-G10 -> 9495
B12: Consolidated Total | C12: =HistoricalFS!H6 -> 28799 | D12: =HistoricalFS!I6 -> 40575 | E12: =HistoricalFS!J6 -> 51084 | F12: =HistoricalFS!K6 -> 60456 | G12: =HistoricalFS!L6 -> 87584
B14: SEGMENT EBIT | C14: =C4 -> 44651 | D14: =D4 -> 45016 | E14: =E4 -> 45382 | F14: =F4 -> 45747 | G14: =G4 -> 46112
B15: Watches | C15: 108 | D15: 413 | E15: 397 | F15: 553 | G15: 842
B16: Jewellery | C16: 3027 | D16: 4363 | E16: 4726 | F16: 4764 | G16: 6601
B17: EyeCare | C17: 50 | D17: 98 | E17: 85 | F17: 85 | G17: 84
B18: Others | C18: -36 | D18: -78 | E18: -93 | F18: -124 | G18: -114
B19: Total | C19: 3149 | D19: 4796 | E19: 5115 | F19: 5278 | G19: 7413
B20: Caratlane & other subs | C20: =C22-C19-C21 -> -182 | D20: =D22-D19-D21 -> -264 | E20: =E22-E19-E21 -> -379 | F20: =F22-F19-F21 -> -247 | G20: =G22-G19-G21 -> 289
B21: Corporate (unallocated) | C21: -22 | D21: -91 | E21: -28 | F21: -30 | G21: -171
B22: Consolidated EBIT | C22: =HistoricalFS!H27 -> 2945 | D22: =HistoricalFS!I27 -> 4441 | E22: =HistoricalFS!J27 -> 4708 | F22: =HistoricalFS!K27 -> 5001 | G22: =HistoricalFS!L27 -> 7531
B24: SEGMENT NET ASSETS | C24: =C14 -> 44651 | D24: =D14 -> 45016 | E24: =E14 -> 45382 | F24: =F14 -> 45747 | G24: =G14 -> 46112
B25: Watches | C25: 1351 | D25: 1764 | E25: 2605 | F25: 2865 | G25: 3132
B26: Jewellery | C26: 4998 | D26: 6376 | E26: 7632 | F26: 11488 | G26: 11653
B27: EyeCare | C27: 194 | D27: 256 | E27: 261 | F27: 256 | G27: 265
B28: Others | C28: 117 | D28: 168 | E28: 245 | F28: 262 | G28: 270
B29: Corporate (unallocated) | C29: 2713 | D29: 3430 | E29: 3714 | F29: 1940 | G29: 5167
B30: Total | C30: 9373 | D30: 11994 | E30: 14457 | F30: 16811 | G30: 20487
C32: =C24 -> 44651 | D32: =D24 -> 45016 | E32: =E24 -> 45382 | F32: =F24 -> 45747 | G32: =G24 -> 46112
B33: Gold Sold (Tonnes) | C33: 36.8 | D33: 44.4 | E33: 47.1 | F33: 44.4 | G33: 48.9
B34: Average Price per gm | C34: 4534 | D34: 5142 | E34: 5785 | F34: 6680 | G34: 7450

Sheet Beta - regression
B3: Regression Beta - 2 Years Weekly
B5: Titan Weekly Returns | F5: NIFTY Returns | I5: Beta Drifting | L5: Beta 1 | M5: =SLOPE(D9:D113,G9:G113) -> 0.97667835 | V5: Kalyan Jewellers Weekly Returns | Z5: NIFTY Returns | AC5: Beta Drifting | AF5: Thangamayil Jew. Weekly Returns | AJ5: NIFTY Returns | AM5: Beta Drifting | AP5: Sky Gold & Diam. Weekly Returns | AT5: NIFTY Returns | AW5: Beta Drifting | AZ5: Bluestone Weekly Returns | BD5: NIFTY Returns | BG5: Beta Drifting
L6: Beta 2 | M6: =_xlfn.COVARIANCE.S(D8:D113,G8:G113)/_xlfn.VAR.S(G8:G113) -> 0.97667835
B7: Date | C7: Closing price | D7: Return | F7: Closing price | G7: Return | I7: Levered Raw Beta | J7: =M8 -> 0.97667835 | V7: Date | W7: Closing price | X7: Return | Z7: Closing price | AA7: Return | AC7: Levered Raw Beta | AD7: =SLOPE(X9:X112,AA9:AA112) -> 1.5734218 | AF7: Date | AG7: Closing price | AH7: Return | AJ7: Closing price | AK7: Return | AM7: Levered Raw Beta | AN7: =SLOPE(AH9:AH112,AK9:AK112) -> 0.56835062 | AP7: Date | AQ7: Closing price | AR7: Return | AT7: Closing price | AU7: Return | AW7: Levered Raw Beta | AX7: =SLOPE(AR9:AR112,AU9:AU112) -> 1.2305792 | AZ7: Date | BA7: Closing price | BB7: Return | BD7: Closing price | BE7: Return | BG7: Levered Raw Beta | BH7: =SLOPE(BB9:BB59,BE9:BE59) -> 0.27185751
B8: 45516 | C8: 3423.18 | F8: 24541.15 | I8: Raw Beta Weight | J8: 0.75 | L8: Beta (through regression) | M8: =M29 -> 0.97667835 | V8: 45516 | W8: 571.28 | Z8: 24541.15 | AC8: Raw Beta Weight | AD8: 0.75 | AF8: 45516 | AG8: 1780.69 | AJ8: 24541.15 | AM8: Raw Beta Weight | AN8: 0.75 | AP8: 45516 | AQ8: 239.97 | AT8: 24541.15 | AW8: Raw Beta Weight | AX8: 0.75 | AZ8: 45887 | BA8: 546.35 | BD8: 24870.1 | BG8: Raw Beta Weight | BH8: 0.75
B9: 45523 | C9: 3547.65 | D9: =C9/C8-1 -> 0.036360928 | F9: 24823.15 | G9: =F9/F8-1 -> 0.011490904 | V9: 45523 | W9: 587.18 | X9: =W9/W8-1 -> 0.027832236 | Z9: 24823.15 | AA9: =Z9/Z8-1 -> 0.011490904 | AF9: 45523 | AG9: 1908.03 | AH9: =AG9/AG8-1 -> 0.071511605 | AJ9: 24823.15 | AK9: =AJ9/AJ8-1 -> 0.011490904 | AP9: 45523 | AQ9: 253.7 | AR9: =AQ9/AQ8-1 -> 0.057215485 | AT9: 24823.15 | AU9: =AT9/AT8-1 -> 0.011490904 | AZ9: 45894 | BA9: 534.8 | BB9: =BA9/BA8-1 -> -0.021140295 | BD9: 24426.85 | BE9: =BD9/BD8-1 -> -0.017822606
B10: 45530 | C10: 3542.83 | D10: =C10/C9-1 -> -0.0013586459 | F10: 25235.9 | G10: =F10/F9-1 -> 0.016627624 | I10: Market Beta | J10: 1 | V10: 45530 | W10: 613.41 | X10: =W10/W9-1 -> 0.04467114 | Z10: 25235.9 | AA10: =Z10/Z9-1 -> 0.016627624 | AC10: Market Beta | AD10: 1 | AF10: 45530 | AG10: 2016.8 | AH10: =AG10/AG9-1 -> 0.057006441 | AJ10: 25235.9 | AK10: =AJ10/AJ9-1 -> 0.016627624 | AM10: Market Beta | AN10: 1 | AP10: 45530 | AQ10: 260.68 | AR10: =AQ10/AQ9-1 -> 0.02751281 | AT10: 25235.9 | AU10: =AT10/AT9-1 -> 0.016627624 | AW10: Market Beta | AX10: 1 | AZ10: 45901 | BA10: 604.25 | BB10: =BA10/BA9-1 -> 0.12986163 | BD10: 24741 | BE10: =BD10/BD9-1 -> 0.012860848 | BG10: Market Beta | BH10: 1
B11: 45537 | C11: 3672.36 | D11: =C11/C10-1 -> 0.036561167 | F11: 24852.15 | G11: =F11/F10-1 -> -0.015206511 | I11: Market Beta Weight | J11: =1-J8 -> 0.25 | V11: 45537 | W11: 646.31 | X11: =W11/W10-1 -> 0.0536346 | Z11: 24852.15 | AA11: =Z11/Z10-1 -> -0.015206511 | AC11: Market Beta Weight | AD11: =1-AD8 -> 0.25 | AF11: 45537 | AG11: 2092.09 | AH11: =AG11/AG10-1 -> 0.037331416 | AJ11: 24852.15 | AK11: =AJ11/AJ10-1 -> -0.015206511 | AM11: Market Beta Weight | AN11: =1-AN8 -> 0.25 | AP11: 45537 | AQ11: 276.7 | AR11: =AQ11/AQ10-1 -> 0.061454657 | AT11: 24852.15 | AU11: =AT11/AT10-1 -> -0.015206511 | AW11: Market Beta Weight | AX11: =1-AX8 -> 0.25 | AZ11: 45908 | BA11: 642.1 | BB11: =BA11/BA10-1 -> 0.062639636 | BD11: 25114 | BE11: =BD11/BD10-1 -> 0.015076189 | BG11: Market Beta Weight | BH11: =1-BH8 -> 0.25
B12: 45544 | C12: 3743.41 | D12: =C12/C11-1 -> 0.019347232 | F12: 25356.5 | G12: =F12/F11-1 -> 0.020294019 | L12: SUMMARY OUTPUT | V12: 45544 | W12: 713.96 | X12: =W12/W11-1 -> 0.10467113 | Z12: 25356.5 | AA12: =Z12/Z11-1 -> 0.020294019 | AF12: 45544 | AG12: 2233.65 | AH12: =AG12/AG11-1 -> 0.067664393 | AJ12: 25356.5 | AK12: =AJ12/AJ11-1 -> 0.020294019 | AP12: 45544 | AQ12: 273.49 | AR12: =AQ12/AQ11-1 -> -0.011601012 | AT12: 25356.5 | AU12: =AT12/AT11-1 -> 0.020294019 | AZ12: 45915 | BA12: 609.1 | BB12: =BA12/BA11-1 -> -0.051393864 | BD12: 25327.05 | BE12: =BD12/BD11-1 -> 0.0084833161
B13: 45551 | C13: 3773.43 | D13: =C13/C12-1 -> 0.0080194261 | F13: 25790.95 | G13: =F13/F12-1 -> 0.017133674 | I13: Adjusted Beta | J13: =(J7*J8)+(J10*J11) -> 0.98250876 | V13: 45551 | W13: 728.37 | X13: =W13/W12-1 -> 0.020183204 | Z13: 25790.95 | AA13: =Z13/Z12-1 -> 0.017133674 | AC13: Adjusted Beta | AD13: =(AD7*AD8)+(AD10*AD11) -> 1.4300664 | AF13: 45551 | AG13: 2211.01 | AH13: =AG13/AG12-1 -> -0.010135876 | AJ13: 25790.95 | AK13: =AJ13/AJ12-1 -> 0.017133674 | AM13: Adjusted Beta | AN13: =(AN7*AN8)+(AN10*AN11) -> 0.67626297 | AP13: 45551 | AQ13: 249.46 | AR13: =AQ13/AQ12-1 -> -0.087864273 | AT13: 25790.95 | AU13: =AT13/AT12-1 -> 0.017133674 | AW13: Adjusted Beta | AX13: =(AX7*AX8)+(AX10*AX11) -> 1.1729344 | AZ13: 45922 | BA13: 567.45 | BB13: =BA13/BA12-1 -> -0.068379576 | BD13: 24654.7 | BE13: =BD13/BD12-1 -> -0.026546716 | BG13: Adjusted Beta | BH13: =(BH7*BH8)+(BH10*BH11) -> 0.45389313
B14: 45558 | C14: 3792.8 | D14: =C14/C13-1 -> 0.0051332607 | F14: 26178.95 | G14: =F14/F13-1 -> 0.015044037 | L14: Regression Statistics | V14: 45558 | W14: 704.64 | X14: =W14/W13-1 -> -0.032579596 | Z14: 26178.95 | AA14: =Z14/Z13-1 -> 0.015044037 | AF14: 45558 | AG14: 2396.9 | AH14: =AG14/AG13-1 -> 0.084074699 | AJ14: 26178.95 | AK14: =AJ14/AJ13-1 -> 0.015044037 | AP14: 45558 | AQ14: 257.23 | AR14: =AQ14/AQ13-1 -> 0.031147278 | AT14: 26178.95 | AU14: =AT14/AT13-1 -> 0.015044037 | AZ14: 45929 | BA14: 611.85 | BB14: =BA14/BA13-1 -> 0.078244779 | BD14: 24894.25 | BE14: =BD14/BD13-1 -> 0.0097162002
B15: 45565 | C15: 3647.12 | D15: =C15/C14-1 -> -0.038409618 | F15: 25014.6 | G15: =F15/F14-1 -> -0.044476574 | L15: Multiple R | M15: 0.56769367 | V15: 45565 | W15: 710.87 | X15: =W15/W14-1 -> 0.0088413942 | Z15: 25014.6 | AA15: =Z15/Z14-1 -> -0.044476574 | AF15: 45565 | AG15: 2352.07 | AH15: =AG15/AG14-1 -> -0.018703325 | AJ15: 25014.6 | AK15: =AJ15/AJ14-1 -> -0.044476574 | AP15: 45565 | AQ15: 270.68 | AR15: =AQ15/AQ14-1 -> 0.052287836 | AT15: 25014.6 | AU15: =AT15/AT14-1 -> -0.044476574 | AZ15: 45936 | BA15: 702.05 | BB15: =BA15/BA14-1 -> 0.14742175 | BD15: 25285.35 | BE15: =BD15/BD14-1 -> 0.015710455
B16: 45572 | C16: 3452.65 | D16: =C16/C15-1 -> -0.053321525 | F16: 24964.25 | G16: =F16/F15-1 -> -0.0020128245 | L16: R Square | M16: 0.32227611 | V16: 45572 | W16: 718.2 | X16: =W16/W15-1 -> 0.010311309 | Z16: 24964.25 | AA16: =Z16/Z15-1 -> -0.0020128245 | AF16: 45572 | AG16: 2509.68 | AH16: =AG16/AG15-1 -> 0.06700906 | AJ16: 24964.25 | AK16: =AJ16/AJ15-1 -> -0.0020128245 | AP16: 45572 | AQ16: 303.67 | AR16: =AQ16/AQ15-1 -> 0.12187823 | AT16: 24964.25 | AU16: =AT16/AT15-1 -> -0.0020128245 | AZ16: 45943 | BA16: 714.55 | BB16: =BA16/BA15-1 -> 0.017805 | BD16: 25709.85 | BE16: =BD16/BD15-1 -> 0.016788377
B17: 45579 | C17: 3360.28 | D17: =C17/C16-1 -> -0.026753363 | F17: 24854.05 | G17: =F17/F16-1 -> -0.0044143125 | L17: Adjusted R Square | M17: 0.31569626 | V17: 45579 | W17: 716.85 | X17: =W17/W16-1 -> -0.0018796992 | Z17: 24854.05 | AA17: =Z17/Z16-1 -> -0.0044143125 | AF17: 45579 | AG17: 2392.84 | AH17: =AG17/AG16-1 -> -0.046555736 | AJ17: 24854.05 | AK17: =AJ17/AJ16-1 -> -0.0044143125 | AP17: 45579 | AQ17: 318.14 | AR17: =AQ17/AQ16-1 -> 0.04765041 | AT17: 24854.05 | AU17: =AT17/AT16-1 -> -0.0044143125 | AZ17: 45950 | BA17: 743.8 | BB17: =BA17/BA16-1 -> 0.040934854 | BD17: 25795.15 | BE17: =BD17/BD16-1 -> 0.0033177945
B18: 45586 | C18: 3246.1 | D18: =C18/C17-1 -> -0.033979311 | F18: 24180.8 | G18: =F18/F17-1 -> -0.027088141 | L18: Standard Error | M18: 0.026348006 | V18: 45586 | W18: 669.74 | X18: =W18/W17-1 -> -0.065718072 | Z18: 24180.8 | AA18: =Z18/Z17-1 -> -0.027088141 | AF18: 45586 | AG18: 2120.76 | AH18: =AG18/AG17-1 -> -0.11370589 | AJ18: 24180.8 | AK18: =AJ18/AJ17-1 -> -0.027088141 | AP18: 45586 | AQ18: 348.7 | AR18: =AQ18/AQ17-1 -> 0.096058339 | AT18: 24180.8 | AU18: =AT18/AT17-1 -> -0.027088141 | AZ18: 45957 | BA18: 708 | BB18: =BA18/BA17-1 -> -0.048131218 | BD18: 25722.1 | BE18: =BD18/BD17-1 -> -0.0028319277
B19: 45593 | C19: 3273.08 | D19: =C19/C18-1 -> 0.0083115123 | F19: 24304.35 | G19: =F19/F18-1 -> 0.0051094257 | L19: Observations | M19: 105 | V19: 45593 | W19: 668.84 | X19: =W19/W18-1 -> -0.0013438051 | Z19: 24304.35 | AA19: =Z19/Z18-1 -> 0.0051094257 | AF19: 45593 | AG19: 2270.74 | AH19: =AG19/AG18-1 -> 0.070719931 | AJ19: 24304.35 | AK19: =AJ19/AJ18-1 -> 0.0051094257 | AP19: 45593 | AQ19: 339.37 | AR19: =AQ19/AQ18-1 -> -0.026756524 | AT19: 24304.35 | AU19: =AT19/AT18-1 -> 0.0051094257 | AZ19: 45964 | BA19: 606.25 | BB19: =BA19/BA18-1 -> -0.14371469 | BD19: 25492.3 | BE19: =BD19/BD18-1 -> -0.0089339517
B20: 45600 | C20: 3166.3 | D20: =C20/C19-1 -> -0.032623706 | F20: 24148.2 | G20: =F20/F19-1 -> -0.0064247758 | V20: 45600 | W20: 692.07 | X20: =W20/W19-1 -> 0.034731774 | Z20: 24148.2 | AA20: =Z20/Z19-1 -> -0.0064247758 | AF20: 45600 | AG20: 1980.84 | AH20: =AG20/AG19-1 -> -0.12766763 | AJ20: 24148.2 | AK20: =AJ20/AJ19-1 -> -0.0064247758 | AP20: 45600 | AQ20: 334.7 | AR20: =AQ20/AQ19-1 -> -0.013760792 | AT20: 24148.2 | AU20: =AT20/AT19-1 -> -0.0064247758 | AZ20: 45971 | BA20: 574.75 | BB20: =BA20/BA19-1 -> -0.051958763 | BD20: 25910.05 | BE20: =BD20/BD19-1 -> 0.016387301
B21: 45607 | C21: 3163.77 | D21: =C21/C20-1 -> -0.00079903989 | F21: 23532.7 | G21: =F21/F20-1 -> -0.025488442 | L21: ANOVA | V21: 45607 | W21: 651.99 | X21: =W21/W20-1 -> -0.057913217 | Z21: 23532.7 | AA21: =Z21/Z20-1 -> -0.025488442 | AF21: 45607 | AG21: 1865.88 | AH21: =AG21/AG20-1 -> -0.058035985 | AJ21: 23532.7 | AK21: =AJ21/AJ20-1 -> -0.025488442 | AP21: 45607 | AQ21: 325.71 | AR21: =AQ21/AQ20-1 -> -0.026859875 | AT21: 23532.7 | AU21: =AT21/AT20-1 -> -0.025488442 | AZ21: 45978 | BA21: 570.95 | BB21: =BA21/BA20-1 -> -0.0066115702 | BD21: 26068.15 | BE21: =BD21/BD20-1 -> 0.0061018794
B22: 45614 | C22: 3287.98 | D22: =C22/C21-1 -> 0.039260123 | F22: 23907.25 | G22: =F22/F21-1 -> 0.015916151 | M22: df | N22: SS | O22: MS | P22: F | Q22: Significance F | V22: 45614 | W22: 704.39 | X22: =W22/W21-1 -> 0.080369331 | Z22: 23907.25 | AA22: =Z22/Z21-1 -> 0.015916151 | AF22: 45614 | AG22: 1974.55 | AH22: =AG22/AG21-1 -> 0.058240616 | AJ22: 23907.25 | AK22: =AJ22/AJ21-1 -> 0.015916151 | AP22: 45614 | AQ22: 395.86 | AR22: =AQ22/AQ21-1 -> 0.21537564 | AT22: 23907.25 | AU22: =AT22/AT21-1 -> 0.015916151 | AZ22: 45985 | BA22: 558.1 | BB22: =BA22/BA21-1 -> -0.022506349 | BD22: 26202.95 | BE22: =BD22/BD21-1 -> 0.0051710612
B23: 45621 | C23: 3228.66 | D23: =C23/C22-1 -> -0.018041472 | F23: 24131.1 | G23: =F23/F22-1 -> 0.0093632685 | L23: Regression | M23: 1 | N23: 0.034002281 | O23: 0.034002281 | P23: 48.979296 | Q23: 2.699382e-10 | V23: 45621 | W23: 722.34 | X23: =W23/W22-1 -> 0.025483042 | Z23: 24131.1 | AA23: =Z23/Z22-1 -> 0.0093632685 | AF23: 45621 | AG23: 1962.91 | AH23: =AG23/AG22-1 -> -0.0058950141 | AJ23: 24131.1 | AK23: =AJ23/AJ22-1 -> 0.0093632685 | AP23: 45621 | AQ23: 385.45 | AR23: =AQ23/AQ22-1 -> -0.026297176 | AT23: 24131.1 | AU23: =AT23/AT22-1 -> 0.0093632685 | AZ23: 45992 | BA23: 527.9 | BB23: =BA23/BA22-1 -> -0.054112166 | BD23: 26186.45 | BE23: =BD23/BD22-1 -> -0.00062970009
B24: 45628 | C24: 3448.37 | D24: =C24/C23-1 -> 0.068049903 | F24: 24677.8 | G24: =F24/F23-1 -> 0.022655411 | L24: Residual | M24: 103 | N24: 0.071504395 | O24: 0.00069421743 | V24: 45628 | W24: 728.37 | X24: =W24/W23-1 -> 0.0083478694 | Z24: 24677.8 | AA24: =Z24/Z23-1 -> 0.022655411 | AF24: 45628 | AG24: 2109.97 | AH24: =AG24/AG23-1 -> 0.07491938 | AJ24: 24677.8 | AK24: =AJ24/AJ23-1 -> 0.022655411 | AP24: 45628 | AQ24: 412.67 | AR24: =AQ24/AQ23-1 -> 0.070618757 | AT24: 24677.8 | AU24: =AT24/AT23-1 -> 0.022655411 | AZ24: 45999 | BA24: 527.45 | BB24: =BA24/BA23-1 -> -0.00085243417 | BD24: 26046.95 | BE24: =BD24/BD23-1 -> -0.0053271826
B25: 45635 | C25: 3486.88 | D25: =C25/C24-1 -> 0.011167595 | F25: 24768.3 | G25: =F25/F24-1 -> 0.0036672637 | L25: Total | M25: 104 | N25: 0.10550668 | V25: 45635 | W25: 744.92 | X25: =W25/W24-1 -> 0.022721968 | Z25: 24768.3 | AA25: =Z25/Z24-1 -> 0.0036672637 | AF25: 45635 | AG25: 2069.45 | AH25: =AG25/AG24-1 -> -0.019204065 | AJ25: 24768.3 | AK25: =AJ25/AJ24-1 -> 0.0036672637 | AP25: 45635 | AQ25: 443.14 | AR25: =AQ25/AQ24-1 -> 0.073836237 | AT25: 24768.3 | AU25: =AT25/AT24-1 -> 0.0036672637 | AZ25: 46006 | BA25: 510.3 | BB25: =BA25/BA24-1 -> -0.03251493 | BD25: 25966.4 | BE25: =BD25/BD24-1 -> -0.0030924926
B26: 45642 | C26: 3335.24 | D26: =C26/C25-1 -> -0.043488735 | F26: 23587.5 | G26: =F26/F25-1 -> -0.047673841 | V26: 45642 | W26: 717.1 | X26: =W26/W25-1 -> -0.037346292 | Z26: 23587.5 | AA26: =Z26/Z25-1 -> -0.047673841 | AF26: 45642 | AG26: 1991.79 | AH26: =AG26/AG25-1 -> -0.037526879 | AJ26: 23587.5 | AK26: =AJ26/AJ25-1 -> -0.047673841 | AP26: 45642 | AQ26: 418.9 | AR26: =AQ26/AQ25-1 -> -0.054700546 | AT26: 23587.5 | AU26: =AT26/AT25-1 -> -0.047673841 | AZ26: 46013 | BA26: 493.3 | BB26: =BA26/BA25-1 -> -0.033313737 | BD26: 26042.3 | BE26: =BD26/BD25-1 -> 0.0029230082
B27: 45649 | C27: 3288.48 | D27: =C27/C26-1 -> -0.014019981 | F27: 23813.4 | G27: =F27/F26-1 -> 0.0095771065 | M27: Coefficients | N27: Standard Error | O27: t Stat | P27: P-value | Q27: Lower 95% | R27: Upper 95% | S27: Lower 95.0% | T27: Upper 95.0% | V27: 45649 | W27: 719.54 | X27: =W27/W26-1 -> 0.0034025938 | Z27: 23813.4 | AA27: =Z27/Z26-1 -> 0.0095771065 | AF27: 45649 | AG27: 1933.19 | AH27: =AG27/AG26-1 -> -0.029420772 | AJ27: 23813.4 | AK27: =AJ27/AJ26-1 -> 0.0095771065 | AP27: 45649 | AQ27: 412.5 | AR27: =AQ27/AQ26-1 -> -0.015278109 | AT27: 23813.4 | AU27: =AT27/AT26-1 -> 0.0095771065 | AZ27: 46020 | BA27: 500.75 | BB27: =BA27/BA26-1 -> 0.015102372 | BD27: 26328.55 | BE27: =BD27/BD26-1 -> 0.010991733
B28: 45656 | C28: 3430.04 | D28: =C28/C27-1 -> 0.043047244 | F28: 24004.75 | G28: =F28/F27-1 -> 0.0080353918 | L28: Intercept | M28: 0.0041788452 | N28: 0.002571365 | O28: 1.6251466 | P28: 0.10718747 | Q28: -0.00092085089 | R28: 0.0092785412 | S28: -0.00092085089 | T28: 0.0092785412 | V28: 45656 | W28: 775.53 | X28: =W28/W27-1 -> 0.077813603 | Z28: 24004.75 | AA28: =Z28/Z27-1 -> 0.0080353918 | AF28: 45656 | AG28: 2000.26 | AH28: =AG28/AG27-1 -> 0.034693951 | AJ28: 24004.75 | AK28: =AJ28/AJ27-1 -> 0.0080353918 | AP28: 45656 | AQ28: 390.3 | AR28: =AQ28/AQ27-1 -> -0.053818182 | AT28: 24004.75 | AU28: =AT28/AT27-1 -> 0.0080353918 | AZ28: 46027 | BA28: 488.45 | BB28: =BA28/BA27-1 -> -0.024563155 | BD28: 25683.3 | BE28: =BD28/BD27-1 -> -0.024507616
B29: 45663 | C29: 3418.71 | D29: =C29/C28-1 -> -0.0033031685 | F29: 23431.5 | G29: =F29/F28-1 -> -0.02388069 | L29: X Variable 1 | M29: 0.97667835 | N29: 0.13955496 | O29: 6.998521 | P29: 2.699382e-10 | Q29: 0.69990399 | R29: 1.2534527 | S29: 0.69990399 | T29: 1.2534527 | V29: 45663 | W29: 624.92 | X29: =W29/W28-1 -> -0.19420267 | Z29: 23431.5 | AA29: =Z29/Z28-1 -> -0.02388069 | AF29: 45663 | AG29: 1883.41 | AH29: =AG29/AG28-1 -> -0.058417406 | AJ29: 23431.5 | AK29: =AJ29/AJ28-1 -> -0.02388069 | AP29: 45663 | AQ29: 366.6 | AR29: =AQ29/AQ28-1 -> -0.060722521 | AT29: 23431.5 | AU29: =AT29/AT28-1 -> -0.02388069 | AZ29: 46034 | BA29: 454.3 | BB29: =BA29/BA28-1 -> -0.069915037 | BD29: 25694.35 | BE29: =BD29/BD28-1 -> 0.00043024066
B30: 45670 | C30: 3336.38 | D30: =C30/C29-1 -> -0.024082183 | F30: 23203.2 | G30: =F30/F29-1 -> -0.0097432943 | V30: 45670 | W30: 500.04 | X30: =W30/W29-1 -> -0.19983358 | Z30: 23203.2 | AA30: =Z30/Z29-1 -> -0.0097432943 | AF30: 45670 | AG30: 1759.83 | AH30: =AG30/AG29-1 -> -0.065615028 | AJ30: 23203.2 | AK30: =AJ30/AJ29-1 -> -0.0097432943 | AP30: 45670 | AQ30: 367.25 | AR30: =AQ30/AQ29-1 -> 0.0017730496 | AT30: 23203.2 | AU30: =AT30/AT29-1 -> -0.0097432943 | AZ30: 46041 | BA30: 456.9 | BB30: =BA30/BA29-1 -> 0.0057230905 | BD30: 25048.65 | BE30: =BD30/BD29-1 -> -0.025130038
B31: 45677 | C31: 3380.85 | D31: =C31/C30-1 -> 0.013328817 | F31: 23092.2 | G31: =F31/F30-1 -> -0.0047838229 | V31: 45677 | W31: 457.41 | X31: =W31/W30-1 -> -0.08525318 | Z31: 23092.2 | AA31: =Z31/Z30-1 -> -0.0047838229 | AF31: 45677 | AG31: 1684.25 | AH31: =AG31/AG30-1 -> -0.04294733 | AJ31: 23092.2 | AK31: =AJ31/AJ30-1 -> -0.0047838229 | AP31: 45677 | AQ31: 336.3 | AR31: =AQ31/AQ30-1 -> -0.084275017 | AT31: 23092.2 | AU31: =AT31/AT30-1 -> -0.0047838229 | AZ31: 46048 | BA31: 426.7 | BB31: =BA31/BA30-1 -> -0.066097614 | BD31: 24825.45 | BE31: =BD31/BD30-1 -> -0.0089106599
B32: 45684 | C32: 3529.76 | D32: =C32/C31-1 -> 0.044045137 | F32: 23482.15 | G32: =F32/F31-1 -> 0.016886654 | V32: 45684 | W32: 503.98 | X32: =W32/W31-1 -> 0.10181238 | Z32: 23482.15 | AA32: =Z32/Z31-1 -> 0.016886654 | AF32: 45684 | AG32: 1746.54 | AH32: =AG32/AG31-1 -> 0.036983821 | AJ32: 23482.15 | AK32: =AJ32/AJ31-1 -> 0.016886654 | AP32: 45684 | AQ32: 331.5 | AR32: =AQ32/AQ31-1 -> -0.014272971 | AT32: 23482.15 | AU32: =AT32/AT31-1 -> 0.016886654 | AZ32: 46055 | BA32: 427.6 | BB32: =BA32/BA31-1 -> 0.0021092102 | BD32: 25693.7 | BE32: =BD32/BD31-1 -> 0.03497419
B33: 45691 | C33: 3403.36 | D33: =C33/C32-1 -> -0.0358098 | F33: 23559.95 | G33: =F33/F32-1 -> 0.0033131549 | V33: 45691 | W33: 537.83 | X33: =W33/W32-1 -> 0.067165364 | Z33: 23559.95 | AA33: =Z33/Z32-1 -> 0.0033131549 | AF33: 45691 | AG33: 1799.95 | AH33: =AG33/AG32-1 -> 0.030580462 | AJ33: 23559.95 | AK33: =AJ33/AJ32-1 -> 0.0033131549 | AP33: 45691 | AQ33: 378 | AR33: =AQ33/AQ32-1 -> 0.14027149 | AT33: 23559.95 | AU33: =AT33/AT32-1 -> 0.0033131549 | AZ33: 46062 | BA33: 436.75 | BB33: =BA33/BA32-1 -> 0.021398503 | BD33: 25471.1 | BE33: =BD33/BD32-1 -> -0.0086636024
B34: 45698 | C34: 3193.13 | D34: =C34/C33-1 -> -0.061771308 | F34: 22929.25 | G34: =F34/F33-1 -> -0.026770006 | V34: 45698 | W34: 486.97 | X34: =W34/W33-1 -> -0.094565197 | Z34: 22929.25 | AA34: =Z34/Z33-1 -> -0.026770006 | AF34: 45698 | AG34: 1771.92 | AH34: =AG34/AG33-1 -> -0.015572655 | AJ34: 22929.25 | AK34: =AJ34/AJ33-1 -> -0.026770006 | AP34: 45698 | AQ34: 366.75 | AR34: =AQ34/AQ33-1 -> -0.029761905 | AT34: 22929.25 | AU34: =AT34/AT33-1 -> -0.026770006 | AZ34: 46069 | BA34: 410.6 | BB34: =BA34/BA33-1 -> -0.05987407 | BD34: 25571.25 | BE34: =BD34/BD33-1 -> 0.0039319071
B35: 45705 | C35: 3159.99 | D35: =C35/C34-1 -> -0.010378531 | F35: 22795.9 | G35: =F35/F34-1 -> -0.0058157157 | V35: 45705 | W35: 483.83 | X35: =W35/W34-1 -> -0.0064480358 | Z35: 22795.9 | AA35: =Z35/Z34-1 -> -0.0058157157 | AF35: 45705 | AG35: 1641.5 | AH35: =AG35/AG34-1 -> -0.073603774 | AJ35: 22795.9 | AK35: =AJ35/AJ34-1 -> -0.0058157157 | AP35: 45705 | AQ35: 345.3 | AR35: =AQ35/AQ34-1 -> -0.058486708 | AT35: 22795.9 | AU35: =AT35/AT34-1 -> -0.0058157157 | AZ35: 46076 | BA35: 437.45 | BB35: =BA35/BA34-1 -> 0.065392109 | BD35: 25178.65 | BE35: =BD35/BD34-1 -> -0.01535318
B36: 45712 | C36: 3057.98 | D36: =C36/C35-1 -> -0.032281748 | F36: 22124.7 | G36: =F36/F35-1 -> -0.029443891 | V36: 45712 | W36: 460.9 | X36: =W36/W35-1 -> -0.047392679 | Z36: 22124.7 | AA36: =Z36/Z35-1 -> -0.029443891 | AF36: 45712 | AG36: 1870.68 | AH36: =AG36/AG35-1 -> 0.1396162 | AJ36: 22124.7 | AK36: =AJ36/AJ35-1 -> -0.029443891 | AP36: 45712 | AQ36: 318.1 | AR36: =AQ36/AQ35-1 -> -0.078772082 | AT36: 22124.7 | AU36: =AT36/AT35-1 -> -0.029443891 | AZ36: 46083 | BA36: 457.15 | BB36: =BA36/BA35-1 -> 0.045033718 | BD36: 24450.45 | BE36: =BD36/BD35-1 -> -0.028921328
B37: 45719 | C37: 3060.07 | D37: =C37/C36-1 -> 0.00068345771 | F37: 22552.5 | G37: =F37/F36-1 -> 0.019335855 | V37: 45719 | W37: 430.44 | X37: =W37/W36-1 -> -0.066088089 | Z37: 22552.5 | AA37: =Z37/Z36-1 -> 0.019335855 | AF37: 45719 | AG37: 1713.42 | AH37: =AG37/AG36-1 -> -0.084065687 | AJ37: 22552.5 | AK37: =AJ37/AJ36-1 -> 0.019335855 | AP37: 45719 | AQ37: 376.2 | AR37: =AQ37/AQ36-1 -> 0.18264697 | AT37: 22552.5 | AU37: =AT37/AT36-1 -> 0.019335855 | AZ37: 46090 | BA37: 521.8 | BB37: =BA37/BA36-1 -> 0.14141967 | BD37: 23151.1 | BE37: =BD37/BD36-1 -> -0.053142171
B38: 45726 | C38: 2991.3 | D38: =C38/C37-1 -> -0.022473342 | F38: 22397.2 | G38: =F38/F37-1 -> -0.0068861545 | V38: 45726 | W38: 429.64 | X38: =W38/W37-1 -> -0.0018585633 | Z38: 22397.2 | AA38: =Z38/Z37-1 -> -0.0068861545 | AF38: 45726 | AG38: 1751.86 | AH38: =AG38/AG37-1 -> 0.022434663 | AJ38: 22397.2 | AK38: =AJ38/AJ37-1 -> -0.0068861545 | AP38: 45726 | AQ38: 335.65 | AR38: =AQ38/AQ37-1 -> -0.10778841 | AT38: 22397.2 | AU38: =AT38/AT37-1 -> -0.0068861545 | AZ38: 46097 | BA38: 543.8 | BB38: =BA38/BA37-1 -> 0.042161748 | BD38: 23114.5 | BE38: =BD38/BD37-1 -> -0.0015809184
B39: 45733 | C39: 3142.9 | D39: =C39/C38-1 -> 0.050680306 | F39: 23350.4 | G39: =F39/F38-1 -> 0.042558891 | V39: 45733 | W39: 469.83 | X39: =W39/W38-1 -> 0.093543432 | Z39: 23350.4 | AA39: =Z39/Z38-1 -> 0.042558891 | AF39: 45733 | AG39: 1867.22 | AH39: =AG39/AG38-1 -> 0.065850011 | AJ39: 23350.4 | AK39: =AJ39/AJ38-1 -> 0.042558891 | AP39: 45733 | AQ39: 334.95 | AR39: =AQ39/AQ38-1 -> -0.0020855057 | AT39: 23350.4 | AU39: =AT39/AT38-1 -> 0.042558891 | AZ39: 46104 | BA39: 490 | BB39: =BA39/BA38-1 -> -0.098933431 | BD39: 22819.6 | BE39: =BD39/BD38-1 -> -0.012758225
B40: 45740 | C40: 3044.17 | D40: =C40/C39-1 -> -0.031413663 | F40: 23519.35 | G40: =F40/F39-1 -> 0.0072354221 | V40: 45740 | W40: 465.89 | X40: =W40/W39-1 -> -0.008386012 | Z40: 23519.35 | AA40: =Z40/Z39-1 -> 0.0072354221 | AF40: 45740 | AG40: 1989.75 | AH40: =AG40/AG39-1 -> 0.065621619 | AJ40: 23519.35 | AK40: =AJ40/AJ39-1 -> 0.0072354221 | AP40: 45740 | AQ40: 321.55 | AR40: =AQ40/AQ39-1 -> -0.040005971 | AT40: 23519.35 | AU40: =AT40/AT39-1 -> 0.0072354221 | AZ40: 46111 | BA40: 427.55 | BB40: =BA40/BA39-1 -> -0.12744898 | BD40: 22713.1 | BE40: =BD40/BD39-1 -> -0.0046670406
B41: 45747 | C41: 3056.94 | D41: =C41/C40-1 -> 0.0041949037 | F41: 22904.45 | G41: =F41/F40-1 -> -0.02614443 | V41: 45747 | W41: 485.73 | X41: =W41/W40-1 -> 0.04258516 | Z41: 22904.45 | AA41: =Z41/Z40-1 -> -0.02614443 | AF41: 45747 | AG41: 1977.03 | AH41: =AG41/AG40-1 -> -0.0063927629 | AJ41: 22904.45 | AK41: =AJ41/AJ40-1 -> -0.02614443 | AP41: 45747 | AQ41: 327.6 | AR41: =AQ41/AQ40-1 -> 0.018815114 | AT41: 22904.45 | AU41: =AT41/AT40-1 -> -0.02614443 | AZ41: 46118 | BA41: 495.1 | BB41: =BA41/BA40-1 -> 0.15799322 | BD41: 24050.6 | BE41: =BD41/BD40-1 -> 0.058886722
... B59: 45873 | C59: 3448.88 | D59: =C59/C58-1 -> 0.04348668 | F59: 24363.3 | G59: =F59/F58-1 -> -0.0082249998 | V59: 45873 | W59: 526.56 | X59: =W59/W58-1 -> -0.09393444 | Z59: 24363.3 | AA59: =Z59/Z58-1 -> -0.0082249998 | AF59: 45873 | AG59: 1968.89 | AH59: =AG59/AG58-1 -> 0.031826472 | AJ59: 24363.3 | AK59: =AJ59/AJ58-1 -> -0.0082249998 | AP59: 45873 | AQ59: 275.7 | AR59: =AQ59/AQ58-1 -> 0.0047376093 | AT59: 24363.3 | AU59: =AT59/AT58-1 -> -0.0082249998 | AZ59: 46244 | BA59: 894.5 | BB59: =BA59/BA58-1 -> 0.098219767 | BD59: 24435.95 | BE59: =BD59/BD58-1 -> -0.0054821505
B60: 45880 | C60: 3477.99 | D60: =C60/C59-1 -> 0.0084404212 | F60: 24631.3 | G60: =F60/F59-1 -> 0.011000152 | V60: 45880 | W60: 531.94 | X60: =W60/W59-1 -> 0.010217259 | Z60: 24631.3 | AA60: =Z60/Z59-1 -> 0.011000152 | AF60: 45880 | AG60: 1998.21 | AH60: =AG60/AG59-1 -> 0.014891639 | AJ60: 24631.3 | AK60: =AJ60/AJ59-1 -> 0.011000152 | AP60: 45880 | AQ60: 273.15 | AR60: =AQ60/AQ59-1 -> -0.0092491839 | AT60: 24631.3 | AU60: =AT60/AT59-1 -> 0.011000152
B61: 45887 | C61: 3609.16 | D61: =C61/C60-1 -> 0.037714312 | F61: 24870.1 | G61: =F61/F60-1 -> 0.0096949816 | V61: 45887 | W61: 509.66 | X61: =W61/W60-1 -> -0.041884423 | Z61: 24870.1 | AA61: =Z61/Z60-1 -> 0.0096949816 | AF61: 45887 | AG61: 2109.7 | AH61: =AG61/AG60-1 -> 0.055794936 | AJ61: 24870.1 | AK61: =AJ61/AJ60-1 -> 0.0096949816 | AP61: 45887 | AQ61: 304.95 | AR61: =AQ61/AQ60-1 -> 0.11641955 | AT61: 24870.1 | AU61: =AT61/AT60-1 -> 0.0096949816
B62: 45894 | C62: 3616.93 | D62: =C62/C61-1 -> 0.0021528555 | F62: 24426.85 | G62: =F62/F61-1 -> -0.017822606 | V62: 45894 | W62: 502.68 | X62: =W62/W61-1 -> -0.013695405 | Z62: 24426.85 | AA62: =Z62/Z61-1 -> -0.017822606 | AF62: 45894 | AG62: 2249.11 | AH62: =AG62/AG61-1 -> 0.066080485 | AJ62: 24426.85 | AK62: =AJ62/AJ61-1 -> -0.017822606 | AP62: 45894 | AQ62: 287.9 | AR62: =AQ62/AQ61-1 -> -0.055910805 | AT62: 24426.85 | AU62: =AT62/AT61-1 -> -0.017822606
B63: 45901 | C63: 3653.31 | D63: =C63/C62-1 -> 0.010058254 | F63: 24741 | G63: =F63/F62-1 -> 0.012860848 | V63: 45901 | W63: 501.95 | X63: =W63/W62-1 -> -0.0014522161 | Z63: 24741 | AA63: =Z63/Z62-1 -> 0.012860848 | AF63: 45901 | AG63: 2189.77 | AH63: =AG63/AG62-1 -> -0.02638377 | AJ63: 24741 | AK63: =AJ63/AJ62-1 -> 0.012860848 | AP63: 45901 | AQ63: 278.95 | AR63: =AQ63/AQ62-1 -> -0.031087183 | AT63: 24741 | AU63: =AT63/AT62-1 -> 0.012860848
B64: 45908 | C64: 3560.22 | D64: =C64/C63-1 -> -0.025481002 | F64: 25114 | G64: =F64/F63-1 -> 0.015076189 | V64: 45908 | W64: 502.75 | X64: =W64/W63-1 -> 0.0015937842 | Z64: 25114 | AA64: =Z64/Z63-1 -> 0.015076189 | AF64: 45908 | AG64: 2180.8 | AH64: =AG64/AG63-1 -> -0.0040963206 | AJ64: 25114 | AK64: =AJ64/AJ63-1 -> 0.015076189 | AP64: 45908 | AQ64: 282.25 | AR64: =AQ64/AQ63-1 -> 0.011830077 | AT64: 25114 | AU64: =AT64/AT63-1 -> 0.015076189
B65: 45915 | C65: 3455.86 | D65: =C65/C64-1 -> -0.029312795 | F65: 25327.05 | G65: =F65/F64-1 -> 0.0084833161 | V65: 45915 | W65: 511.4 | X65: =W65/W64-1 -> 0.01720537 | Z65: 25327.05 | AA65: =Z65/Z64-1 -> 0.0084833161 | AF65: 45915 | AG65: 2148.49 | AH65: =AG65/AG64-1 -> -0.014815664 | AJ65: 25327.05 | AK65: =AJ65/AJ64-1 -> 0.0084833161 | AP65: 45915 | AQ65: 293 | AR65: =AQ65/AQ64-1 -> 0.038086802 | AT65: 25327.05 | AU65: =AT65/AT64-1 -> 0.0084833161
B66: 45922 | C66: 3316.42 | D66: =C66/C65-1 -> -0.040348857 | F66: 24654.7 | G66: =F66/F65-1 -> -0.026546716 | V66: 45922 | W66: 455.8 | X66: =W66/W65-1 -> -0.10872116 | Z66: 24654.7 | AA66: =Z66/Z65-1 -> -0.026546716 | AF66: 45922 | AG66: 2010.68 | AH66: =AG66/AG65-1 -> -0.064142723 | AJ66: 24654.7 | AK66: =AJ66/AJ65-1 -> -0.026546716 | AP66: 45922 | AQ66: 272.5 | AR66: =AQ66/AQ65-1 -> -0.06996587 | AT66: 24654.7 | AU66: =AT66/AT65-1 -> -0.026546716
B67: 45929 | C67: 3442.01 | D67: =C67/C66-1 -> 0.037869148 | F67: 24894.25 | G67: =F67/F66-1 -> 0.0097162002 | V67: 45929 | W67: 492.15 | X67: =W67/W66-1 -> 0.07974989 | Z67: 24894.25 | AA67: =Z67/Z66-1 -> 0.0097162002 | AF67: 45929 | AG67: 2081.48 | AH67: =AG67/AG66-1 -> 0.035211968 | AJ67: 24894.25 | AK67: =AJ67/AJ66-1 -> 0.0097162002 | AP67: 45929 | AQ67: 284.45 | AR67: =AQ67/AQ66-1 -> 0.043853211 | AT67: 24894.25 | AU67: =AT67/AT66-1 -> 0.0097162002
B68: 45936 | C68: 3520.35 | D68: =C68/C67-1 -> 0.022759957 | F68: 25285.35 | G68: =F68/F67-1 -> 0.015710455 | V68: 45936 | W68: 484.85 | X68: =W68/W67-1 -> -0.014832876 | Z68: 25285.35 | AA68: =Z68/Z67-1 -> 0.015710455 | AF68: 45936 | AG68: 2016.16 | AH68: =AG68/AG67-1 -> -0.031381517 | AJ68: 25285.35 | AK68: =AJ68/AJ67-1 -> 0.015710455 | AP68: 45936 | AQ68: 342.65 | AR68: =AQ68/AQ67-1 -> 0.20460538 | AT68: 25285.35 | AU68: =AT68/AT67-1 -> 0.015710455
B69: 45943 | C69: 3662.78 | D69: =C69/C68-1 -> 0.040459045 | F69: 25709.85 | G69: =F69/F68-1 -> 0.016788377 | V69: 45943 | W69: 489.85 | X69: =W69/W68-1 -> 0.010312468 | Z69: 25709.85 | AA69: =Z69/Z68-1 -> 0.016788377 | AF69: 45943 | AG69: 1957.42 | AH69: =AG69/AG68-1 -> -0.029134592 | AJ69: 25709.85 | AK69: =AJ69/AJ68-1 -> 0.016788377 | AP69: 45943 | AQ69: 334.1 | AR69: =AQ69/AQ68-1 -> -0.024952576 | AT69: 25709.85 | AU69: =AT69/AT68-1 -> 0.016788377
B70: 45950 | C70: 3702.75 | D70: =C70/C69-1 -> 0.010912476 | F70: 25795.15 | G70: =F70/F69-1 -> 0.0033177945 | V70: 45950 | W70: 495.3 | X70: =W70/W69-1 -> 0.011125855 | Z70: 25795.15 | AA70: =Z70/Z69-1 -> 0.0033177945 | AF70: 45950 | AG70: 2033.81 | AH70: =AG70/AG69-1 -> 0.039025861 | AJ70: 25795.15 | AK70: =AJ70/AJ69-1 -> 0.0033177945 | AP70: 45950 | AQ70: 365.6 | AR70: =AQ70/AQ69-1 -> 0.094283149 | AT70: 25795.15 | AU70: =AT70/AT69-1 -> 0.0033177945
B71: 45957 | C71: 3734.45 | D71: =C71/C70-1 -> 0.0085612045 | F71: 25722.1 | G71: =F71/F70-1 -> -0.0028319277 | V71: 45957 | W71: 509.7 | X71: =W71/W70-1 -> 0.029073289 | Z71: 25722.1 | AA71: =Z71/Z70-1 -> -0.0028319277 | AF71: 45957 | AG71: 2163.55 | AH71: =AG71/AG70-1 -> 0.063791603 | AJ71: 25722.1 | AK71: =AJ71/AJ70-1 -> -0.0028319277 | AP71: 45957 | AQ71: 355.85 | AR71: =AQ71/AQ70-1 -> -0.02666849 | AT71: 25722.1 | AU71: =AT71/AT70-1 -> -0.0028319277
... B112: 46244 | C112: 5128 | D112: =C112/C111-1 -> 0.03784659 | F112: 24471.7 | G112: =F112/F111-1 -> -0.0040271625 | V112: 46244 | W112: 596.7 | X112: =W112/W111-1 -> -0.015833746 | Z112: 24435.95 | AA112: =Z112/Z111-1 -> -0.0054821505 | AF112: 46244 | AG112: 5328 | AH112: =AG112/AG111-1 -> 0.010047393 | AJ112: 24435.95 | AK112: =AJ112/AJ111-1 -> -0.0054821505 | AP112: 46244 | AQ112: 833.1 | AR112: =AQ112/AQ111-1 -> 0.15804837 | AT112: 24435.95 | AU112: =AT112/AT111-1 -> -0.0054821505
B113: 46246 | C113: 5099 | D113: =C113/C112-1 -> -0.0056552262 | F113: 24435.95 | G113: =F113/F112-1 -> -0.0014608711

Sheet Beta - comps
B3: S.No. | C3: Name | D3: CMP Rs. | E3: Mar Cap Rs.Cr. | F3: Debt Rs.Cr. | G3: Debt / Eq
B4: 1 | C4: Titan Company | D4: =Teaser!B11 -> 5169 | E4: 448931.97 | F4: 30621 | G4: 1.95
B5: 2 | C5: Kalyan Jewellers | D5: 613.4 | E5: 63311.81 | F5: 6117.33 | G5: 0.97
B6: 3 | C6: Thangamayil Jew. | D6: 5270 | E6: 16398.54 | F6: 913.21 | G6: 0.64
B7: 4 | C7: Bluestone Jewel | D7: 874.3 | E7: 13388.55 | F7: 1699.09 | G7: 0.94
B8: 5 | C8: Sky Gold & Diam. | D8: 773.95 | E8: 11993.66 | F8: 869.11 | G8: 0.73

Sheet Market Return
B3: Return on Markets
B5: Year | C5: TRI
B6: 2005 | C6: 0.393 | E6: Average Return | F6: {=GEOMEAN(1+C6:C26)-1} -> 0.14226283
B7: 2006 | C7: 0.419 | E7: Total Market Return | F7: =F6 -> 0.14226283
B8: 2007 | C8: 0.568
B9: 2008 | C9: -0.513
B10: 2009 | C10: 0.776
B11: 2010 | C11: 0.192
B12: 2011 | C12: -0.238
B13: 2012 | C13: 0.294
B14: 2013 | C14: 0.081
B15: 2014 | C15: 0.329
B16: 2015 | C16: -0.03
B17: 2016 | C17: 0.044
B18: 2017 | C18: 0.303
B19: 2018 | C19: 0.046
... B26: 2025 | C26: 0.119
B27: 2026 YTD* | C27: -0.081
B29: *The 2026 YTD figure is an absolute return as of June 30, 2026. It does not represent a complete calendar-year return.

Sheet Raw FS
B2: Particulars | C2: 42064 | D2: 42430 | E2: 42795 | F2: 43160 | G2: 43525 | H2: 43891 | I2: 44256 | J2: 44621 | K2: 44986 | L2: 45352 | M2: 45717 | N2: 46082
B3: Equity Capital | C3: 89 | D3: 89 | E3: 89 | F3: 89 | G3: 89 | H3: 89 | I3: 89 | J3: 89 | K3: 89 | L3: 89 | M3: 89 | N3: 89
B4: Reserves | C4: 2995 | D4: 3418 | E4: 4144 | F4: 5001 | G4: 5981 | H4: 6580 | I4: 7408 | J4: 9214 | K4: 11762 | L4: 9304 | M4: 11535 | N4: 15614
B6: Borrowings
B7: Long term Borrowings | C7: 0 | D7: 0 | E7: 0 | F7: 0 | G7: 32 | H7: 17 | I7: 9 | J7: 2 | K7: 0 | L7: 3302 | M7: 595 | N7: 93
B8: Short term Borrowings | C8: 100 | D8: 113 | E8: 1882 | F8: 1691 | G8: 2353 | H8: 2291 | I8: 4367 | J8: 5914 | K8: 7494 | L8: 9877 | M8: 17501 | N8: 27355
B9: Lease Liabilities | C9: 0 | D9: 0 | E9: 0 | F9: 0 | G9: 0 | H9: 1243 | I9: 1256 | J9: 1359 | K9: 1873 | L9: 2349 | M9: 2681 | N9: 3173
B10: Other Borrowings | C10: 0 | D10: 0 | E10: 0 | F10: 0 | G10: 8 | H10: 11 | I10: 6 | J10: 0 | K10: 0 | L10: 0 | M10: 0 | N10: 0
B11: Other Liabilities -
B12: Non controlling int | C12: 0 | D12: 0 | E12: 26 | F12: -2 | G12: 14 | H12: 4 | I12: 5 | J12: 30 | K12: 53 | L12: 0 | M12: 0 | N12: 0
B13: Trade Payables | C13: 1940 | D13: 1655 | E13: 783 | F13: 878 | G13: 906 | H13: 596 | I13: 789 | J13: 1294 | K13: 1214 | L13: 1410 | M13: 1963 | N13: 2864
B14: Advance from Customers | C14: 160 | D14: 710 | E14: 943 | F14: 233 | G14: 290 | H14: 386 | I14: 479 | J14: 532 | K14: 718 | L14: 1085 | M14: 2140 | N14: 4745
B15: Other liability items | C15: 585 | D15: 358 | E15: 541 | F15: 1631 | G15: 2037 | H15: 2327 | I15: 2036 | J15: 2754 | K15: 3817 | L15: 4131 | M15: 4141 | N15: 6628
B16: Total Liabilities | C16: 5868 | D16: 6342 | E16: 8408 | F16: 9521 | G16: 11710 | H16: 13544 | I16: 16444 | J16: 21188 | K16: 27020 | L16: 31547 | M16: 40645 | N16: 60561
B18: Fixed Assets -
B19: Land | C19: 104 | D19: 85 | E19: 85 | F19: 85 | G19: 85 | H19: 108 | I19: 108 | J19: 136 | K19: 144 | L19: 163 | M19: 163 | N19: 440
B20: Building | C20: 156 | D20: 137 | E20: 198 | F20: 341 | G20: 386 | H20: 1473 | I20: 1617 | J20: 1853 | K20: 2403 | L20: 3546 | M20: 4177 | N20: 5239
B21: Plant Machinery | C21: 719 | D21: 445 | E21: 473 | F21: 563 | G21: 630 | H21: 724 | I21: 739 | J21: 768 | K21: 838 | L21: 899 | M21: 1012 | N21: 1197
B22: Equipments | C22: 24 | D22: 18 | E22: 24 | F22: 34 | G22: 50 | H22: 70 | I22: 76 | J22: 96 | K22: 130 | L22: 110 | M22: 127 | N22: 176
B23: Computers | C23: 0 | D23: 0 | E23: 46 | F23: 72 | G23: 92 | H23: 119 | I23: 142 | J23: 159 | K23: 204 | L23: 212 | M23: 228 | N23: 264
B24: Furniture n fittings | C24: 189 | D24: 107 | E24: 138 | F24: 203 | G24: 251 | H24: 313 | I24: 309 | J24: 321 | K24: 376 | L24: 173 | M24: 193 | N24: 379
B25: Vehicles | C25: 17 | D25: 11 | E25: 10 | F25: 16 | G25: 22 | H25: 28 | I25: 30 | J25: 38 | K25: 40 | L25: 50 | M25: 57 | N25: 68
B26: Intangible Assets | C26: 0 | D26: 13 | E26: 318 | F26: 319 | G26: 319 | H26: 333 | I26: 320 | J26: 320 | K26: 320 | L26: 320 | M26: 320 | N26: 1782
B27: Other fixed assets | C27: 73 | D27: 20 | E27: 26 | F27: 69 | G27: 96 | H27: 135 | I27: 158 | J27: 157 | K27: 205 | L27: 305 | M27: 369 | N27: 540
B28: Gross Block | C28: 1282 | D28: 836 | E28: 1318 | F28: 1704 | G28: 1931 | H28: 3303 | I28: 3499 | J28: 3848 | K28: 4660 | L28: 5778 | M28: 6646 | N28: 10085
B29: Accumulated Depreciation | C29: 583 | D29: 66 | E29: 130 | F29: 230 | G29: 365 | H29: 670 | I29: 976 | J29: 1304 | K29: 1662 | L29: 2069 | M29: 2584 | N29: 3207
B30: Net Block | C30: =C28-C29 -> 699 | D30: =D28-D29 -> 770 | E30: =E28-E29 -> 1188 | F30: =F28-F29 -> 1474 | G30: =G28-G29 -> 1566 | H30: =H28-H29 -> 2633 | I30: =I28-I29 -> 2523 | J30: =J28-J29 -> 2544 | ... N30: =N28-N29 -> 6878
B32: CWIP | C32: 55 | D32: 107 | E32: 152 | F32: 43 | G32: 32 | H32: 18 | I32: 32 | J32: 85 | K32: 144 | L32: 97 | M32: 105 | N32: 163
B33: Investments | C33: 3 | D33: 30 | E33: 431 | F33: 36 | G33: 108 | H33: 158 | I33: 2824 | J33: 294 | K33: 2515 | L33: 2345 | M33: 1988 | N33: 3506
B35: Other Assets -
B36: Inventories | C36: 4049 | D36: 4447 | E36: 4926 | F36: 5925 | G36: 7039 | H36: 8103 | I36: 8408 | J36: 13609 | K36: 16584 | L36: 19051 | M36: 28184 | N36: 42743
B37: Trade receivables | C37: 190 | D37: 192 | E37: 208 | F37: 296 | G37: 420 | H37: 312 | I37: 366 | J37: 565 | K37: 674 | L37: 1018 | M37: 1068 | N37: 916
B38: Cash Equivalents | C38: 214 | D38: 116 | E38: 779 | F38: 618 | G38: 1066 | H38: 381 | I38: 560 | J38: 1573 | K38: 1343 | L38: 1526 | M38: 1584 | N38: 1917
B39: Loans n Advances | C39: 47 | D39: 87 | E39: 122 | F39: 141 | G39: 25 | H39: 142 | I39: 109 | J39: 29 | K39: 167 | L39: 151 | M39: 324 | N39: 399
B40: Other asset items | C40: 611 | D40: 591 | E40: 602 | F40: 988 | G40: 1452 | H40: 1797 | I40: 1622 | J40: 2489 | K40: 2595 | L40: 3650 | M40: 3330 | N40: 4039
B41: Total Assets | C41: 5868 | D41: 6342 | E41: 8408 | F41: 9521 | G41: 11710 | H41: 13544 | I41: 16444 | J41: 21188 | K41: 27020 | L41: 31547 | M41: 40645 | N41: 60561

Sheet Comps_Data
B2: S.No. | C2: Name | D2: Ticker | E2: CMP Rs. | F2: No. Eq. Shares Cr. | G2: Market Cap | H2: Debt Rs.Cr. | I2: Cash End PY Rs.Cr. | J2: Net debt | K2: EV Rs.Cr. | L2: Sales Rs.Cr. | M2: EBITDA | N2: NP 12M Rs.Cr. | O2: EV / EBITDA
B3: 1 | C3: Titan Company | D3: TITAN | E3: =Teaser!B11 -> 5169 | F3: 88.78 | G3: =F3*E3 -> 458903.82 | H3: 30621 | I3: 1584 | J3: =H3-I3 -> 29037 | K3: 479699.31 | L3: 92417 | M3: =K3/O3 -> 10012.509 | N3: 5760 | O3: 47.91
B4: 2 | C4: Kalyan Jewellers | D4: KALYANKJIL | E4: 615.8 | F4: 103.28 | G4: =F4*E4 -> 63599.824 | H4: 6117.33 | I4: 1031.07 | J4: =H4-I4 -> 5086.26 | K4: 67567.5 | L4: 39063.32 | M4: =K4/O4 -> 2833.0189 | N4: 1434.98 | O4: 23.85
B5: 3 | C5: Thangamayil Jew. | D5: THANGAMAYL | E5: 5440.5 | F5: 3.11 | G5: =F5*E5 -> 16919.955 | H5: 913.21 | I5: 241.79 | J5: =H5-I5 -> 671.42 | K5: 17654.38 | L5: 9622.28 | M5: =K5/O5 -> 636.8824 | N5: 391.04 | O5: 27.72
B6: 4 | C6: Bluestone Jewel | D6: BLUESTONE | E6: 794.7 | F6: 15.27 | G6: =F6*E6 -> 12135.069 | H6: 1983.89 | I6: 186.89 | J6: =H6-I6 -> 1797 | K6: 14388.71 | L6: 2680.6 | M6: =K6/O6 -> 488.41514 | N6: 53.89 | O6: 29.46
B7: 5 | C7: Sky Gold & Diam. | D7: SKYGOLD | E7: 811.4 | F7: 15.49 | G7: =F7*E7 -> 12568.586 | H7: 869.11 | I7: 175.13 | J7: =H7-I7 -> 693.98 | K7: 13085.52 | L7: 7176.44 | M7: =K7/O7 -> 559.68862 | N7: 343.15 | O7: 23.38
B8: 6 | C8: PC Jeweller | D8: PCJEWELLER | E8: 10.94 | F8: 975.21 | G8: =F8*E8 -> 10668.797 | H8: 1166.56 | I8: 63.78 | J8: =H8-I8 -> 1102.78 | K8: 10997.06 | L8: 3505.01 | M8: =K8/O8 -> 901.39836 | N8: 774.41 | O8: 12.2
B9: 7 | C9: P N Gadgil Jewe. | D9: PNGJL | E9: 598 | F9: 14.72 | G9: =F9*E9 -> 8802.56 | H9: 1737.09 | I9: 528.69 | J9: =H9-I9 -> 1208.4 | K9: 10153.18 | L9: 11437.52 | M9: =K9/O9 -> 773.28104 | N9: 445.82 | O9: 13.13
B10: 8 | C10: Ethos | D10: ETHOS | E10: 2875.1 | F10: 2.68 | G10: =F10*E10 -> 7705.268 | H10: 322.32 | I10: 220.02 | J10: =H10-I10 -> 102.3 | K10: 7277.25 | L10: 1727.63 | M10: =K10/O10 -> 271.74197 | N10: 105.78 | O10: 26.78
B11: 9 | C11: Timex Group | D11: TIMEX | E11: 653.75 | F11: 10.1 | G11: =F11*E11 -> 6602.875 | H11: 71.41 | I11: 0.02 | J11: =H11-I11 -> 71.39 | K11: 6109.62 | L11: 848.55 | M11: =K11/O11 -> 129.96426 | N11: 85.79 | O11: 47.01
B12: 10 | C12: Senco Gold | D12: SENCO | E12: 354.85 | F12: 16.39 | G12: =F12*E12 -> 5815.9915 | H12: 2699.11 | I12: 590.85 | J12: =H12-I12 -> 2108.26 | K12: 7841.16 | L12: 9659.79 | M12: =K12/O12 -> 1075.6049 | N12: 570.8 | O12: 7.29
B26: 11 | C26: Goldiam Intl. | D26: 360 | E26: 15.06 | F26: =E26*D26 -> 5421.6 | G26: 77.01 | H26: 182.03 | I26: 5191.04 | K26: 1073.15 | L26: =I26/M26 -> 305.53502 | M26: 16.99 | O26: 210.96
B27: 12 | C27: KDDL Ltd | D27: 3998.05 | E27: 1.23 | F27: =E27*D27 -> 4917.6015 | G27: 511.83 | H27: 516.9 | I27: 4694.08 | K27: 2322.23 | L27: =I27/M27 -> 391.17333 | M27: 12 | O27: 150.24
B28: 13 | C28: Vaibhav Global | D28: 226 | E28: 16.76 | F28: =E28*D28 -> 3787.76 | G28: 415.84 | H28: 129.26 | I28: 3832.59 | K28: 3795.13 | L28: =I28/M28 -> 426.79176 | M28: 8.98 | O28: 284.87
B29: 14 | C29: D.P. Abhushan | D29: 1481 | E29: 2.28 | F29: =E29*D29 -> 3376.68 | G29: 290.04 | H29: 22.9 | I29: 3645.13 | K29: 4377.16 | L29: =I29/M29 -> 348.48279 | M29: 10.46 | O29: 239.86
B30: 15 | C30: Rajesh Exports | D30: 79.5 | E30: 29.53 | F30: =E30*D30 -> 2347.635 | G30: 1015.9 | H30: 1891.23 | I30: 747.97 | K30: 887509.97 | L30: =I30/M30 -> 397.85638 | M30: 1.88 | O30: 169.22

Sheet Hist Share Price
B2: TITAN DAILY SHARE PRICE - LAST 5 YEARS | L2: Date | M2: Vol.
B3: Date | C3: Price | L3: 46261 | M3: 1.10M
B4: 46261 | C4: 5139.3 | L4: 46260 | M4: 377.62K
B5: 46260 | C5: 5100 | L5: 46259 | M5: 347.52K
B6: 46259 | C6: 5124.8 | L6: 46258 | M6: 256.38K
B7: 46258 | C7: 5079 | L7: 46255 | M7: 352.38K
B8: 46255 | C8: 5086.1 | L8: 46254 | M8: 614.44K
B9: 46254 | C9: 5068 | L9: 46253 | M9: 412.98K
B10: 46253 | C10: 5068 | L10: 46252 | M10: 354.87K
B11: 46252 | C11: 5048.6 | L11: 46251 | M11: 565.26K
B12: 46251 | C12: 5068.5 | L12: 46248 | M12: 587.76K
B13: 46248 | C13: 5056.2 | L13: 46247 | M13: 533.27K
B14: 46247 | C14: 5063.7 | L14: 46246 | M14: 1.11M
B15: 46246 | C15: 5099 | L15: 46245 | M15: 1.66M
... B1243: 44438 | C1243: 1878.45 | L1243: 44435 | M1243: 1.02M
B1244: 44435 | C1244: 1822.55
